[
  {
    "date": "2025-09-11",
    "code": "3491",
    "name": "昇達科",
    "market": "TPEX",
    "foreign_ratio": 0.0,
    "trust_ratio": 0.01352302612989729,
    "dealer_ratio": 0.0,
    "three_inst_ratio": 0.01352302612989729,
    "three_inst_ratio_change_20": 0.0
  },
  {
    "date": "2025-09-12",
    "code": "3491",
    "name": "昇達科",
    "market": "TPEX",
    "foreign_ratio": 0.0,
    "trust_ratio": 0.08564583215601618,
    "dealer_ratio": 0.0,
    "three_inst_ratio": 0.08564583215601618,
    "three_inst_ratio_change_20": 0.0
  },
  {
    "date": "2025-09-15",
    "code": "3491",
    "name": "昇達科",
    "market": "TPEX",
    "foreign_ratio": 0.0,
    "trust_ratio": 0.11118932595693327,
    "dealer_ratio": 0.0,
    "three_inst_ratio": 0.11118932595693327,
    "three_inst_ratio_change_20": 0.0
  },
  {
    "date": "2025-09-16",
    "code": "3491",
    "name": "昇達科",
    "market": "TPEX",
    "foreign_ratio": 0.0,
    "trust_ratio": 0.3305628609530449,
    "dealer_ratio": 0.0,
    "three_inst_ratio": 0.3305628609530449,
    "three_inst_ratio_change_20": 0.0
  },
  {
    "date": "2025-09-17",
    "code": "3491",
    "name": "昇達科",
    "market": "TPEX",
    "foreign_ratio": 0.0,
    "trust_ratio": 0.3305628609530449,
    "dealer_ratio": 0.0,
    "three_inst_ratio": 0.3305628609530449,
    "three_inst_ratio_change_20": 0.0
  },
  {
    "date": "2025-09-18",
    "code": "3491",
    "name": "昇達科",
    "market": "TPEX",
    "foreign_ratio": 0.0,
    "trust_ratio": 0.7422638786854735,
    "dealer_ratio": 0.0,
    "three_inst_ratio": 0.7422638786854735,
    "three_inst_ratio_change_20": 0.0
  },
  {
    "date": "2025-09-19",
    "code": "3491",
    "name": "昇達科",
    "market": "TPEX",
    "foreign_ratio": 0.0,
    "trust_ratio": 0.7547351138941566,
    "dealer_ratio": 0.0,
    "three_inst_ratio": 0.7547351138941566,
    "three_inst_ratio_change_20": 0.0
  },
  {
    "date": "2025-09-22",
    "code": "3491",
    "name": "昇達科",
    "market": "TPEX",
    "foreign_ratio": 0.0,
    "trust_ratio": 0.7983093092016034,
    "dealer_ratio": 0.0,
    "three_inst_ratio": 0.7983093092016034,
    "three_inst_ratio_change_20": 0.0
  },
  {
    "date": "2025-09-23",
    "code": "3491",
    "name": "昇達科",
    "market": "TPEX",
    "foreign_ratio": 0.0,
    "trust_ratio": 0.8749397906043547,
    "dealer_ratio": 0.0,
    "three_inst_ratio": 0.8749397906043547,
    "three_inst_ratio_change_20": 0.0
  },
  {
    "date": "2025-09-24",
    "code": "3491",
    "name": "昇達科",
    "market": "TPEX",
    "foreign_ratio": 0.0,
    "trust_ratio": 0.8779449075221096,
    "dealer_ratio": 0.0,
    "three_inst_ratio": 0.8779449075221096,
    "three_inst_ratio_change_20": 0.0
  },
  {
    "date": "2025-09-25",
    "code": "3491",
    "name": "昇達科",
    "market": "TPEX",
    "foreign_ratio": 0.0,
    "trust_ratio": 0.8989807259463944,
    "dealer_ratio": 0.0,
    "three_inst_ratio": 0.8989807259463944,
    "three_inst_ratio_change_20": 0.0
  },
  {
    "date": "2025-09-26",
    "code": "3491",
    "name": "昇達科",
    "market": "TPEX",
    "foreign_ratio": 0.0,
    "trust_ratio": 0.9155088689940466,
    "dealer_ratio": 0.0,
    "three_inst_ratio": 0.9155088689940466,
    "three_inst_ratio_change_20": 0.0
  },
  {
    "date": "2025-09-30",
    "code": "3491",
    "name": "昇達科",
    "market": "TPEX",
    "foreign_ratio": 0.0,
    "trust_ratio": 0.9155088689940466,
    "dealer_ratio": 0.0,
    "three_inst_ratio": 0.9155088689940466,
    "three_inst_ratio_change_20": 0.0
  },
  {
    "date": "2025-10-01",
    "code": "3491",
    "name": "昇達科",
    "market": "TPEX",
    "foreign_ratio": 0.0,
    "trust_ratio": 0.9335395705005763,
    "dealer_ratio": 0.0,
    "three_inst_ratio": 0.9335395705005763,
    "three_inst_ratio_change_20": 0.0
  },
  {
    "date": "2025-10-02",
    "code": "3491",
    "name": "昇達科",
    "market": "TPEX",
    "foreign_ratio": 0.0,
    "trust_ratio": 0.9771137658080232,
    "dealer_ratio": 0.0,
    "three_inst_ratio": 0.9771137658080232,
    "three_inst_ratio_change_20": 0.0
  },
  {
    "date": "2025-10-03",
    "code": "3491",
    "name": "昇達科",
    "market": "TPEX",
    "foreign_ratio": 0.0,
    "trust_ratio": 0.9771137658080232,
    "dealer_ratio": 0.0,
    "three_inst_ratio": 0.9771137658080232,
    "three_inst_ratio_change_20": 0.0
  },
  {
    "date": "2025-10-07",
    "code": "3491",
    "name": "昇達科",
    "market": "TPEX",
    "foreign_ratio": 0.0,
    "trust_ratio": 0.9771137658080232,
    "dealer_ratio": 0.0,
    "three_inst_ratio": 0.9771137658080232,
    "three_inst_ratio_change_20": 0.0
  },
  {
    "date": "2025-10-08",
    "code": "3491",
    "name": "昇達科",
    "market": "TPEX",
    "foreign_ratio": 0.0,
    "trust_ratio": 0.9996521426911853,
    "dealer_ratio": 0.0,
    "three_inst_ratio": 0.9996521426911853,
    "three_inst_ratio_change_20": 0.0
  },
  {
    "date": "2025-10-09",
    "code": "3491",
    "name": "昇達科",
    "market": "TPEX",
    "foreign_ratio": 0.0,
    "trust_ratio": 1.0011547011500628,
    "dealer_ratio": 0.0,
    "three_inst_ratio": 1.0011547011500628,
    "three_inst_ratio_change_20": 0.0
  },
  {
    "date": "2025-10-13",
    "code": "3491",
    "name": "昇達科",
    "market": "TPEX",
    "foreign_ratio": 0.0,
    "trust_ratio": 1.1303747286135257,
    "dealer_ratio": 0.0,
    "three_inst_ratio": 1.1303747286135257,
    "three_inst_ratio_change_20": 0.0
  },
  {
    "date": "2025-10-14",
    "code": "3491",
    "name": "昇達科",
    "market": "TPEX",
    "foreign_ratio": 0.0,
    "trust_ratio": 1.1904770669686249,
    "dealer_ratio": 0.0,
    "three_inst_ratio": 1.1904770669686249,
    "three_inst_ratio_change_20": 1.1769540408387276
  },
  {
    "date": "2025-10-15",
    "code": "3491",
    "name": "昇達科",
    "market": "TPEX",
    "foreign_ratio": 0.0,
    "trust_ratio": 1.6788085661038048,
    "dealer_ratio": 0.0,
    "three_inst_ratio": 1.6788085661038048,
    "three_inst_ratio_change_20": 1.5931627339477887
  },
  {
    "date": "2025-10-16",
    "code": "3491",
    "name": "昇達科",
    "market": "TPEX",
    "foreign_ratio": 0.0,
    "trust_ratio": 1.7734697490130857,
    "dealer_ratio": 0.0,
    "three_inst_ratio": 1.7734697490130857,
    "three_inst_ratio_change_20": 1.6622804230561525
  },
  {
    "date": "2025-10-17",
    "code": "3491",
    "name": "昇達科",
    "market": "TPEX",
    "foreign_ratio": 0.0,
    "trust_ratio": 1.7738138349001686,
    "dealer_ratio": 0.0,
    "three_inst_ratio": 1.7738138349001686,
    "three_inst_ratio_change_20": 1.4432509739471238
  },
  {
    "date": "2025-10-20",
    "code": "3491",
    "name": "昇達科",
    "market": "TPEX",
    "foreign_ratio": 0.0,
    "trust_ratio": 1.774189474514888,
    "dealer_ratio": 0.0,
    "three_inst_ratio": 1.774189474514888,
    "three_inst_ratio_change_20": 1.4436266135618432
  },
  {
    "date": "2025-10-21",
    "code": "3491",
    "name": "昇達科",
    "market": "TPEX",
    "foreign_ratio": 0.0,
    "trust_ratio": 1.774189474514888,
    "dealer_ratio": 0.0,
    "three_inst_ratio": 1.774189474514888,
    "three_inst_ratio_change_20": 1.0319255958294145
  },
  {
    "date": "2025-10-22",
    "code": "3491",
    "name": "昇達科",
    "market": "TPEX",
    "foreign_ratio": 0.0,
    "trust_ratio": 1.7817022668092757,
    "dealer_ratio": 0.0,
    "three_inst_ratio": 1.7817022668092757,
    "three_inst_ratio_change_20": 1.0269671529151192
  },
  {
    "date": "2025-10-23",
    "code": "3491",
    "name": "昇達科",
    "market": "TPEX",
    "foreign_ratio": 0.0,
    "trust_ratio": 1.8418046051643746,
    "dealer_ratio": 0.0,
    "three_inst_ratio": 1.8418046051643746,
    "three_inst_ratio_change_20": 1.0434952959627712
  },
  {
    "date": "2025-10-27",
    "code": "3491",
    "name": "昇達科",
    "market": "TPEX",
    "foreign_ratio": 0.0,
    "trust_ratio": 2.29106958436874,
    "dealer_ratio": 0.0,
    "three_inst_ratio": 2.29106958436874,
    "three_inst_ratio_change_20": 1.416129793764385
  },
  {
    "date": "2025-10-28",
    "code": "3491",
    "name": "昇達科",
    "market": "TPEX",
    "foreign_ratio": 0.0,
    "trust_ratio": 2.4458331056331204,
    "dealer_ratio": 0.0,
    "three_inst_ratio": 2.4458331056331204,
    "three_inst_ratio_change_20": 1.5678881981110107
  },
  {
    "date": "2025-10-29",
    "code": "3491",
    "name": "昇達科",
    "market": "TPEX",
    "foreign_ratio": 0.0,
    "trust_ratio": 2.5945863930619906,
    "dealer_ratio": 0.0,
    "three_inst_ratio": 2.5945863930619906,
    "three_inst_ratio_change_20": 1.6956056671155961
  },
  {
    "date": "2025-10-30",
    "code": "3491",
    "name": "昇達科",
    "market": "TPEX",
    "foreign_ratio": 0.0,
    "trust_ratio": 3.290270959522262,
    "dealer_ratio": 0.0,
    "three_inst_ratio": 3.290270959522262,
    "three_inst_ratio_change_20": 2.3747620905282156
  },
  {
    "date": "2025-10-31",
    "code": "3491",
    "name": "昇達科",
    "market": "TPEX",
    "foreign_ratio": 0.0,
    "trust_ratio": 3.290270959522262,
    "dealer_ratio": 0.0,
    "three_inst_ratio": 3.290270959522262,
    "three_inst_ratio_change_20": 2.3747620905282156
  },
  {
    "date": "2025-11-03",
    "code": "3491",
    "name": "昇達科",
    "market": "TPEX",
    "foreign_ratio": 0.0,
    "trust_ratio": 3.3416584588158713,
    "dealer_ratio": 0.0,
    "three_inst_ratio": 3.3416584588158713,
    "three_inst_ratio_change_20": 2.408118888315295
  },
  {
    "date": "2025-11-04",
    "code": "3491",
    "name": "昇達科",
    "market": "TPEX",
    "foreign_ratio": 0.0,
    "trust_ratio": 3.3416584588158713,
    "dealer_ratio": 0.0,
    "three_inst_ratio": 3.3416584588158713,
    "three_inst_ratio_change_20": 2.364544693007848
  },
  {
    "date": "2025-11-05",
    "code": "3491",
    "name": "昇達科",
    "market": "TPEX",
    "foreign_ratio": 0.0,
    "trust_ratio": 3.3420340984305916,
    "dealer_ratio": 0.0,
    "three_inst_ratio": 3.3420340984305916,
    "three_inst_ratio_change_20": 2.3649203326225683
  },
  {
    "date": "2025-11-06",
    "code": "3491",
    "name": "昇達科",
    "market": "TPEX",
    "foreign_ratio": 0.0,
    "trust_ratio": 3.3555571245604883,
    "dealer_ratio": 0.0,
    "three_inst_ratio": 3.3555571245604883,
    "three_inst_ratio_change_20": 2.378443358752465
  },
  {
    "date": "2025-11-07",
    "code": "3491",
    "name": "昇達科",
    "market": "TPEX",
    "foreign_ratio": 0.0,
    "trust_ratio": 3.490787385859461,
    "dealer_ratio": 0.0,
    "three_inst_ratio": 3.490787385859461,
    "three_inst_ratio_change_20": 2.4911352431682756
  },
  {
    "date": "2025-11-10",
    "code": "3491",
    "name": "昇達科",
    "market": "TPEX",
    "foreign_ratio": 0.0,
    "trust_ratio": 3.5478846072968055,
    "dealer_ratio": 0.0,
    "three_inst_ratio": 3.5478846072968055,
    "three_inst_ratio_change_20": 2.5467299061467426
  },
  {
    "date": "2025-11-11",
    "code": "3491",
    "name": "昇達科",
    "market": "TPEX",
    "foreign_ratio": 0.0,
    "trust_ratio": 3.5478846072968055,
    "dealer_ratio": 0.0,
    "three_inst_ratio": 3.5478846072968055,
    "three_inst_ratio_change_20": 2.41750987868328
  },
  {
    "date": "2025-11-12",
    "code": "3491",
    "name": "昇達科",
    "market": "TPEX",
    "foreign_ratio": 0.0,
    "trust_ratio": 3.707155803937818,
    "dealer_ratio": 0.0,
    "three_inst_ratio": 3.707155803937818,
    "three_inst_ratio_change_20": 2.516678736969193
  },
  {
    "date": "2025-11-13",
    "code": "3491",
    "name": "昇達科",
    "market": "TPEX",
    "foreign_ratio": 0.0,
    "trust_ratio": 3.7176737131499604,
    "dealer_ratio": 0.0,
    "three_inst_ratio": 3.7176737131499604,
    "three_inst_ratio_change_20": 2.0388651470461556
  },
  {
    "date": "2025-11-14",
    "code": "3491",
    "name": "昇達科",
    "market": "TPEX",
    "foreign_ratio": 0.0,
    "trust_ratio": 3.7582427915396526,
    "dealer_ratio": 0.0,
    "three_inst_ratio": 3.7582427915396526,
    "three_inst_ratio_change_20": 1.9847730425265668
  },
  {
    "date": "2025-11-17",
    "code": "3491",
    "name": "昇達科",
    "market": "TPEX",
    "foreign_ratio": 0.0,
    "trust_ratio": 3.7582427915396526,
    "dealer_ratio": 0.0,
    "three_inst_ratio": 3.7582427915396526,
    "three_inst_ratio_change_20": 1.984428956639484
  },
  {
    "date": "2025-11-18",
    "code": "3491",
    "name": "昇達科",
    "market": "TPEX",
    "foreign_ratio": 0.0,
    "trust_ratio": 3.768760700751795,
    "dealer_ratio": 0.0,
    "three_inst_ratio": 3.768760700751795,
    "three_inst_ratio_change_20": 1.994571226236907
  },
  {
    "date": "2025-11-19",
    "code": "3491",
    "name": "昇達科",
    "market": "TPEX",
    "foreign_ratio": 0.0,
    "trust_ratio": 3.6996430116434302,
    "dealer_ratio": 0.0,
    "three_inst_ratio": 3.6996430116434302,
    "three_inst_ratio_change_20": 1.9254535371285422
  },
  {
    "date": "2025-11-20",
    "code": "3491",
    "name": "昇達科",
    "market": "TPEX",
    "foreign_ratio": 0.0,
    "trust_ratio": 3.699192244105767,
    "dealer_ratio": 0.0,
    "three_inst_ratio": 3.699192244105767,
    "three_inst_ratio_change_20": 1.9174899772964915
  },
  {
    "date": "2025-11-21",
    "code": "3491",
    "name": "昇達科",
    "market": "TPEX",
    "foreign_ratio": 0.0,
    "trust_ratio": 3.699192244105767,
    "dealer_ratio": 0.0,
    "three_inst_ratio": 3.699192244105767,
    "three_inst_ratio_change_20": 1.8573876389413926
  },
  {
    "date": "2025-11-24",
    "code": "3491",
    "name": "昇達科",
    "market": "TPEX",
    "foreign_ratio": 0.0,
    "trust_ratio": 3.7412638809543366,
    "dealer_ratio": 0.0,
    "three_inst_ratio": 3.7412638809543366,
    "three_inst_ratio_change_20": 1.4501942965855967
  },
  {
    "date": "2025-11-25",
    "code": "3491",
    "name": "昇達科",
    "market": "TPEX",
    "foreign_ratio": 0.0,
    "trust_ratio": 3.744268997872092,
    "dealer_ratio": 0.0,
    "three_inst_ratio": 3.744268997872092,
    "three_inst_ratio_change_20": 1.2984358922389716
  },
  {
    "date": "2025-11-26",
    "code": "3491",
    "name": "昇達科",
    "market": "TPEX",
    "foreign_ratio": 0.0,
    "trust_ratio": 3.76831143577259,
    "dealer_ratio": 0.0,
    "three_inst_ratio": 3.76831143577259,
    "three_inst_ratio_change_20": 1.1737250427105996
  },
  {
    "date": "2025-11-27",
    "code": "3491",
    "name": "昇達科",
    "market": "TPEX",
    "foreign_ratio": 0.0,
    "trust_ratio": 3.759296085019325,
    "dealer_ratio": 0.0,
    "three_inst_ratio": 3.759296085019325,
    "three_inst_ratio_change_20": 0.46902512549706277
  },
  {
    "date": "2025-11-28",
    "code": "3491",
    "name": "昇達科",
    "market": "TPEX",
    "foreign_ratio": 0.0,
    "trust_ratio": 3.783337020361365,
    "dealer_ratio": 0.0,
    "three_inst_ratio": 3.783337020361365,
    "three_inst_ratio_change_20": 0.49306606083910287
  },
  {
    "date": "2025-12-01",
    "code": "3491",
    "name": "昇達科",
    "market": "TPEX",
    "foreign_ratio": 0.0,
    "trust_ratio": 3.8021190010973336,
    "dealer_ratio": 0.0,
    "three_inst_ratio": 3.8021190010973336,
    "three_inst_ratio_change_20": 0.46046054228146227
  },
  {
    "date": "2025-12-02",
    "code": "3491",
    "name": "昇達科",
    "market": "TPEX",
    "foreign_ratio": 0.0,
    "trust_ratio": 3.8216522610627406,
    "dealer_ratio": 0.0,
    "three_inst_ratio": 3.8216522610627406,
    "three_inst_ratio_change_20": 0.47999380224686927
  },
  {
    "date": "2025-12-03",
    "code": "3491",
    "name": "昇達科",
    "market": "TPEX",
    "foreign_ratio": 0.0,
    "trust_ratio": 3.8156420272272307,
    "dealer_ratio": 0.0,
    "three_inst_ratio": 3.8156420272272307,
    "three_inst_ratio_change_20": 0.47360792879663904
  },
  {
    "date": "2025-12-04",
    "code": "3491",
    "name": "昇達科",
    "market": "TPEX",
    "foreign_ratio": 0.0,
    "trust_ratio": 3.8081292349328435,
    "dealer_ratio": 0.0,
    "three_inst_ratio": 3.8081292349328435,
    "three_inst_ratio_change_20": 0.45257211037235523
  },
  {
    "date": "2025-12-05",
    "code": "3491",
    "name": "昇達科",
    "market": "TPEX",
    "foreign_ratio": 0.0,
    "trust_ratio": 3.8006164426384563,
    "dealer_ratio": 0.0,
    "three_inst_ratio": 3.8006164426384563,
    "three_inst_ratio_change_20": 0.3098290567789954
  },
  {
    "date": "2025-12-08",
    "code": "3491",
    "name": "昇達科",
    "market": "TPEX",
    "foreign_ratio": 0.0,
    "trust_ratio": 3.8216522610627406,
    "dealer_ratio": 0.0,
    "three_inst_ratio": 3.8216522610627406,
    "three_inst_ratio_change_20": 0.27376765376593504
  },
  {
    "date": "2025-12-09",
    "code": "3491",
    "name": "昇達科",
    "market": "TPEX",
    "foreign_ratio": 0.0,
    "trust_ratio": 3.8216522610627406,
    "dealer_ratio": 0.0,
    "three_inst_ratio": 3.8216522610627406,
    "three_inst_ratio_change_20": 0.27376765376593504
  },
  {
    "date": "2025-12-10",
    "code": "3491",
    "name": "昇達科",
    "market": "TPEX",
    "foreign_ratio": 0.0,
    "trust_ratio": 3.820149702603863,
    "dealer_ratio": 0.0,
    "three_inst_ratio": 3.820149702603863,
    "three_inst_ratio_change_20": 0.11299389866604503
  },
  {
    "date": "2025-12-11",
    "code": "3491",
    "name": "昇達科",
    "market": "TPEX",
    "foreign_ratio": 0.0,
    "trust_ratio": 4.2213328111241495,
    "dealer_ratio": 0.0,
    "three_inst_ratio": 4.2213328111241495,
    "three_inst_ratio_change_20": 0.5036590979741891
  },
  {
    "date": "2025-12-12",
    "code": "3491",
    "name": "昇達科",
    "market": "TPEX",
    "foreign_ratio": 0.0,
    "trust_ratio": 4.1912816419466,
    "dealer_ratio": 0.0,
    "three_inst_ratio": 4.1912816419466,
    "three_inst_ratio_change_20": 0.43303885040694734
  },
  {
    "date": "2025-12-15",
    "code": "3491",
    "name": "昇達科",
    "market": "TPEX",
    "foreign_ratio": 0.0,
    "trust_ratio": 4.1912816419466,
    "dealer_ratio": 1.5206522678392793,
    "three_inst_ratio": 5.711933909785879,
    "three_inst_ratio_change_20": 1.9536911182462262
  },
  {
    "date": "2025-12-16",
    "code": "3491",
    "name": "昇達科",
    "market": "TPEX",
    "foreign_ratio": 0.0,
    "trust_ratio": 4.1912816419466,
    "dealer_ratio": 3.839099969887226,
    "three_inst_ratio": 8.030381611833826,
    "three_inst_ratio_change_20": 4.261620911082032
  },
  {
    "date": "2025-12-17",
    "code": "3491",
    "name": "昇達科",
    "market": "TPEX",
    "foreign_ratio": 0.0,
    "trust_ratio": 4.1912816419466,
    "dealer_ratio": 5.517608024299255,
    "three_inst_ratio": 9.708889666245856,
    "three_inst_ratio_change_20": 6.009246654602426
  },
  {
    "date": "2025-12-18",
    "code": "3491",
    "name": "昇達科",
    "market": "TPEX",
    "foreign_ratio": 0.0,
    "trust_ratio": 4.1912816419466,
    "dealer_ratio": 5.9263565146599895,
    "three_inst_ratio": 10.117638156606588,
    "three_inst_ratio_change_20": 6.418445912500822
  },
  {
    "date": "2025-12-19",
    "code": "3491",
    "name": "昇達科",
    "market": "TPEX",
    "foreign_ratio": 0.0,
    "trust_ratio": 4.1912816419466,
    "dealer_ratio": 6.196817037257936,
    "three_inst_ratio": 10.388098679204536,
    "three_inst_ratio_change_20": 6.688906435098769
  },
  {
    "date": "2025-12-22",
    "code": "3491",
    "name": "昇達科",
    "market": "TPEX",
    "foreign_ratio": 0.0,
    "trust_ratio": 4.1912816419466,
    "dealer_ratio": 6.384636844617619,
    "three_inst_ratio": 10.57591848656422,
    "three_inst_ratio_change_20": 6.834654605609883
  },
  {
    "date": "2025-12-23",
    "code": "3491",
    "name": "昇達科",
    "market": "TPEX",
    "foreign_ratio": 0.0,
    "trust_ratio": 4.1912816419466,
    "dealer_ratio": 6.781324298228945,
    "three_inst_ratio": 10.972605940175544,
    "three_inst_ratio_change_20": 7.228336942303452
  },
  {
    "date": "2025-12-24",
    "code": "3491",
    "name": "昇達科",
    "market": "TPEX",
    "foreign_ratio": 0.0,
    "trust_ratio": 4.1912816419466,
    "dealer_ratio": 6.934585261034447,
    "three_inst_ratio": 11.125866902981047,
    "three_inst_ratio_change_20": 7.357555467208456
  },
  {
    "date": "2025-12-26",
    "code": "3491",
    "name": "昇達科",
    "market": "TPEX",
    "foreign_ratio": 0.0,
    "trust_ratio": 4.1912816419466,
    "dealer_ratio": 6.991395493806146,
    "three_inst_ratio": 11.182677135752746,
    "three_inst_ratio_change_20": 7.423381050733421
  },
  {
    "date": "2025-12-29",
    "code": "3491",
    "name": "昇達科",
    "market": "TPEX",
    "foreign_ratio": 0.0,
    "trust_ratio": 4.132583540357828,
    "dealer_ratio": 6.9821095457978934,
    "three_inst_ratio": 11.114693086155722,
    "three_inst_ratio_change_20": 7.331356065794356
  },
  {
    "date": "2025-12-30",
    "code": "3491",
    "name": "昇達科",
    "market": "TPEX",
    "foreign_ratio": 0.0,
    "trust_ratio": 4.132583540357828,
    "dealer_ratio": 7.1672989725068375,
    "three_inst_ratio": 11.299882512864666,
    "three_inst_ratio_change_20": 7.497763511767333
  },
  {
    "date": "2025-12-31",
    "code": "3491",
    "name": "昇達科",
    "market": "TPEX",
    "foreign_ratio": 0.0,
    "trust_ratio": 4.132583540357828,
    "dealer_ratio": 7.192561773340763,
    "three_inst_ratio": 11.325145313698592,
    "three_inst_ratio_change_20": 7.503493052635851
  },
  {
    "date": "2026-01-02",
    "code": "3491",
    "name": "昇達科",
    "market": "TPEX",
    "foreign_ratio": 0.0,
    "trust_ratio": 4.132583540357828,
    "dealer_ratio": 7.24589632823294,
    "three_inst_ratio": 11.378479868590768,
    "three_inst_ratio_change_20": 7.562837841363537
  },
  {
    "date": "2026-01-05",
    "code": "3491",
    "name": "昇達科",
    "market": "TPEX",
    "foreign_ratio": 0.0,
    "trust_ratio": 4.132583540357828,
    "dealer_ratio": 8.294739609887953,
    "three_inst_ratio": 12.427323150245781,
    "three_inst_ratio_change_20": 8.619193915312938
  },
  {
    "date": "2026-01-06",
    "code": "3491",
    "name": "昇達科",
    "market": "TPEX",
    "foreign_ratio": 0.0,
    "trust_ratio": 4.132583540357828,
    "dealer_ratio": 8.984225031287384,
    "three_inst_ratio": 13.116808571645212,
    "three_inst_ratio_change_20": 9.316192129006755
  },
  {
    "date": "2026-01-07",
    "code": "3491",
    "name": "昇達科",
    "market": "TPEX",
    "foreign_ratio": 0.0,
    "trust_ratio": 4.132583540357828,
    "dealer_ratio": 9.677586097008978,
    "three_inst_ratio": 13.810169637366807,
    "three_inst_ratio_change_20": 9.988517376304067
  },
  {
    "date": "2026-01-08",
    "code": "3491",
    "name": "昇達科",
    "market": "TPEX",
    "foreign_ratio": 0.0,
    "trust_ratio": 4.132583540357828,
    "dealer_ratio": 10.462789266254898,
    "three_inst_ratio": 14.595372806612726,
    "three_inst_ratio_change_20": 10.773720545549985
  },
  {
    "date": "2026-01-09",
    "code": "3491",
    "name": "昇達科",
    "market": "TPEX",
    "foreign_ratio": 0.0,
    "trust_ratio": 4.132583540357828,
    "dealer_ratio": 11.50725763289334,
    "three_inst_ratio": 15.639841173251169,
    "three_inst_ratio_change_20": 11.819691470647307
  },
  {
    "date": "2026-01-12",
    "code": "3491",
    "name": "昇達科",
    "market": "TPEX",
    "foreign_ratio": 0.0,
    "trust_ratio": 4.132583540357828,
    "dealer_ratio": 13.172624664855286,
    "three_inst_ratio": 17.305208205213113,
    "three_inst_ratio_change_20": 13.083875394088963
  },
  {
    "date": "2026-01-13",
    "code": "3491",
    "name": "昇達科",
    "market": "TPEX",
    "foreign_ratio": 0.0,
    "trust_ratio": 4.132583540357828,
    "dealer_ratio": 14.484860645845309,
    "three_inst_ratio": 18.617444186203137,
    "three_inst_ratio_change_20": 14.426162544256538
  },
  {
    "date": "2026-01-14",
    "code": "3491",
    "name": "昇達科",
    "market": "TPEX",
    "foreign_ratio": 0.0,
    "trust_ratio": 4.132583540357828,
    "dealer_ratio": 16.542586293902374,
    "three_inst_ratio": 20.675169834260203,
    "three_inst_ratio_change_20": 14.963235924474324
  },
  {
    "date": "2026-01-15",
    "code": "3491",
    "name": "昇達科",
    "market": "TPEX",
    "foreign_ratio": 0.0,
    "trust_ratio": 4.132583540357828,
    "dealer_ratio": 18.301145089930504,
    "three_inst_ratio": 22.433728630288332,
    "three_inst_ratio_change_20": 14.403347018454506
  },
  {
    "date": "2026-01-16",
    "code": "3491",
    "name": "昇達科",
    "market": "TPEX",
    "foreign_ratio": 0.0,
    "trust_ratio": 4.132583540357828,
    "dealer_ratio": 19.788611751018774,
    "three_inst_ratio": 23.921195291376602,
    "three_inst_ratio_change_20": 14.212305625130746
  },
  {
    "date": "2026-01-19",
    "code": "3491",
    "name": "昇達科",
    "market": "TPEX",
    "foreign_ratio": 0.0,
    "trust_ratio": 4.132583540357828,
    "dealer_ratio": 21.13679077745988,
    "three_inst_ratio": 25.269374317817707,
    "three_inst_ratio_change_20": 15.151736161211119
  },
  {
    "date": "2026-01-20",
    "code": "3491",
    "name": "昇達科",
    "market": "TPEX",
    "foreign_ratio": 0.0,
    "trust_ratio": 4.132583540357828,
    "dealer_ratio": 22.587632896006774,
    "three_inst_ratio": 26.720216436364602,
    "three_inst_ratio_change_20": 16.332117757160066
  },
  {
    "date": "2026-01-21",
    "code": "3491",
    "name": "昇達科",
    "market": "TPEX",
    "foreign_ratio": 0.0,
    "trust_ratio": 4.132583540357828,
    "dealer_ratio": 23.76397094961612,
    "three_inst_ratio": 27.896554489973948,
    "three_inst_ratio_change_20": 17.320636003409728
  },
  {
    "date": "2026-01-22",
    "code": "3491",
    "name": "昇達科",
    "market": "TPEX",
    "foreign_ratio": 0.0,
    "trust_ratio": 4.132583540357828,
    "dealer_ratio": 26.06042354688598,
    "three_inst_ratio": 30.193007087243807,
    "three_inst_ratio_change_20": 19.220401147068262
  },
  {
    "date": "2026-01-23",
    "code": "3491",
    "name": "昇達科",
    "market": "TPEX",
    "foreign_ratio": 0.0,
    "trust_ratio": 4.132583540357828,
    "dealer_ratio": 26.64888146919632,
    "three_inst_ratio": 30.781465009554147,
    "three_inst_ratio_change_20": 19.655598106573102
  },
  {
    "date": "2026-01-26",
    "code": "3491",
    "name": "昇達科",
    "market": "TPEX",
    "foreign_ratio": 0.0,
    "trust_ratio": 4.132583540357828,
    "dealer_ratio": 27.296109626451592,
    "three_inst_ratio": 31.42869316680942,
    "three_inst_ratio_change_20": 20.246016031056676
  },
  {
    "date": "2026-01-27",
    "code": "3491",
    "name": "昇達科",
    "market": "TPEX",
    "foreign_ratio": 0.0,
    "trust_ratio": 4.132583540357828,
    "dealer_ratio": 27.805379068385772,
    "three_inst_ratio": 31.9379626087436,
    "three_inst_ratio_change_20": 20.82326952258788
  },
  {
    "date": "2026-01-28",
    "code": "3491",
    "name": "昇達科",
    "market": "TPEX",
    "foreign_ratio": 0.0,
    "trust_ratio": 4.132583540357828,
    "dealer_ratio": 28.0305753373255,
    "three_inst_ratio": 32.16315887768333,
    "three_inst_ratio_change_20": 20.863276364818663
  },
  {
    "date": "2026-01-29",
    "code": "3491",
    "name": "昇達科",
    "market": "TPEX",
    "foreign_ratio": 0.0,
    "trust_ratio": 4.132583540357828,
    "dealer_ratio": 28.276509859025804,
    "three_inst_ratio": 32.409093399383636,
    "three_inst_ratio_change_20": 21.083948085685044
  },
  {
    "date": "2026-01-30",
    "code": "3491",
    "name": "昇達科",
    "market": "TPEX",
    "foreign_ratio": 0.0,
    "trust_ratio": 4.132583540357828,
    "dealer_ratio": 28.725409029368286,
    "three_inst_ratio": 32.857992569726115,
    "three_inst_ratio_change_20": 21.47951270113535
  },
  {
    "date": "2026-02-02",
    "code": "3491",
    "name": "昇達科",
    "market": "TPEX",
    "foreign_ratio": 0.0,
    "trust_ratio": 4.132583540357828,
    "dealer_ratio": 29.448751522516353,
    "three_inst_ratio": 33.58133506287418,
    "three_inst_ratio_change_20": 21.1540119126284
  },
  {
    "date": "2026-02-03",
    "code": "3491",
    "name": "昇達科",
    "market": "TPEX",
    "foreign_ratio": 0.0,
    "trust_ratio": 4.132583540357828,
    "dealer_ratio": 30.010303643399006,
    "three_inst_ratio": 34.142887183756834,
    "three_inst_ratio_change_20": 21.026078612111622
  },
  {
    "date": "2026-02-04",
    "code": "3491",
    "name": "昇達科",
    "market": "TPEX",
    "foreign_ratio": 0.0,
    "trust_ratio": 4.132583540357828,
    "dealer_ratio": 30.732828340038722,
    "three_inst_ratio": 34.86541188039655,
    "three_inst_ratio_change_20": 21.055242243029745
  },
  {
    "date": "2026-02-05",
    "code": "3491",
    "name": "昇達科",
    "market": "TPEX",
    "foreign_ratio": 0.0,
    "trust_ratio": 4.132583540357828,
    "dealer_ratio": 31.014501458063027,
    "three_inst_ratio": 35.14708499842085,
    "three_inst_ratio_change_20": 20.551712191808125
  },
  {
    "date": "2026-02-06",
    "code": "3491",
    "name": "昇達科",
    "market": "TPEX",
    "foreign_ratio": 0.0,
    "trust_ratio": 4.132583540357828,
    "dealer_ratio": 31.4746482934261,
    "three_inst_ratio": 35.60723183378393,
    "three_inst_ratio_change_20": 19.967390660532757
  },
  {
    "date": "2026-02-09",
    "code": "3491",
    "name": "昇達科",
    "market": "TPEX",
    "foreign_ratio": 0.0,
    "trust_ratio": 4.132583540357828,
    "dealer_ratio": 31.975117533803072,
    "three_inst_ratio": 36.1077010741609,
    "three_inst_ratio_change_20": 18.802492868947787
  },
  {
    "date": "2026-02-10",
    "code": "3491",
    "name": "昇達科",
    "market": "TPEX",
    "foreign_ratio": 0.0,
    "trust_ratio": 4.132583540357828,
    "dealer_ratio": 32.26443675287734,
    "three_inst_ratio": 36.397020293235165,
    "three_inst_ratio_change_20": 17.779576107032028
  },
  {
    "date": "2026-02-11",
    "code": "3491",
    "name": "昇達科",
    "market": "TPEX",
    "foreign_ratio": 0.0,
    "trust_ratio": 4.132583540357828,
    "dealer_ratio": 32.73577347415987,
    "three_inst_ratio": 36.8683570145177,
    "three_inst_ratio_change_20": 16.193187180257496
  },
  {
    "date": "2026-02-23",
    "code": "3491",
    "name": "昇達科",
    "market": "TPEX",
    "foreign_ratio": 0.0,
    "trust_ratio": 4.132583540357828,
    "dealer_ratio": 33.533698416262986,
    "three_inst_ratio": 37.666281956620814,
    "three_inst_ratio_change_20": 15.232553326332482
  },
  {
    "date": "2026-02-24",
    "code": "3491",
    "name": "昇達科",
    "market": "TPEX",
    "foreign_ratio": 0.0,
    "trust_ratio": 4.132583540357828,
    "dealer_ratio": 33.79799039545409,
    "three_inst_ratio": 37.93057393581192,
    "three_inst_ratio_change_20": 14.00937864443532
  },
  {
    "date": "2026-02-25",
    "code": "3491",
    "name": "昇達科",
    "market": "TPEX",
    "foreign_ratio": 0.0,
    "trust_ratio": 4.132583540357828,
    "dealer_ratio": 34.16845369525056,
    "three_inst_ratio": 38.30103723560839,
    "three_inst_ratio_change_20": 13.031662917790683
  },
  {
    "date": "2026-03-04",
    "code": "3491",
    "name": "昇達科",
    "market": "TPEX",
    "foreign_ratio": 0.0,
    "trust_ratio": 4.132583540357828,
    "dealer_ratio": 34.184781476624636,
    "three_inst_ratio": 38.317365016982464,
    "three_inst_ratio_change_20": 11.597148580617862
  },
  {
    "date": "2026-03-05",
    "code": "3491",
    "name": "昇達科",
    "market": "TPEX",
    "foreign_ratio": 0.0,
    "trust_ratio": 4.132583540357828,
    "dealer_ratio": 34.34629332399228,
    "three_inst_ratio": 38.478876864350106,
    "three_inst_ratio_change_20": 10.582322374376158
  },
  {
    "date": "2026-03-06",
    "code": "3491",
    "name": "昇達科",
    "market": "TPEX",
    "foreign_ratio": 0.0,
    "trust_ratio": 4.132583540357828,
    "dealer_ratio": 34.55723593313708,
    "three_inst_ratio": 38.68981947349491,
    "three_inst_ratio_change_20": 8.4968123862511
  },
  {
    "date": "2026-03-09",
    "code": "3491",
    "name": "昇達科",
    "market": "TPEX",
    "foreign_ratio": 0.0,
    "trust_ratio": 4.132583540357828,
    "dealer_ratio": 34.64457867435008,
    "three_inst_ratio": 38.77716221470791,
    "three_inst_ratio_change_20": 7.9956972051537605
  },
  {
    "date": "2026-03-10",
    "code": "3491",
    "name": "昇達科",
    "market": "TPEX",
    "foreign_ratio": 0.0,
    "trust_ratio": 4.132583540357828,
    "dealer_ratio": 34.91576710779184,
    "three_inst_ratio": 39.048350648149665,
    "three_inst_ratio_change_20": 7.619657481340244
  },
  {
    "date": "2026-03-11",
    "code": "3491",
    "name": "昇達科",
    "market": "TPEX",
    "foreign_ratio": 0.0,
    "trust_ratio": 4.132583540357828,
    "dealer_ratio": 34.94836044689261,
    "three_inst_ratio": 39.080943987250436,
    "three_inst_ratio_change_20": 7.1429813785068355
  },
  {
    "date": "2026-03-12",
    "code": "3491",
    "name": "昇達科",
    "market": "TPEX",
    "foreign_ratio": 0.0,
    "trust_ratio": 4.132583540357828,
    "dealer_ratio": 35.49652263146649,
    "three_inst_ratio": 39.62910617182432,
    "three_inst_ratio_change_20": 7.465947294140989
  },
  {
    "date": "2026-03-13",
    "code": "3491",
    "name": "昇達科",
    "market": "TPEX",
    "foreign_ratio": 0.0,
    "trust_ratio": 4.132583540357828,
    "dealer_ratio": 35.54870901191307,
    "three_inst_ratio": 39.6812925522709,
    "three_inst_ratio_change_20": 7.272199152887261
  },
  {
    "date": "2026-03-16",
    "code": "3491",
    "name": "昇達科",
    "market": "TPEX",
    "foreign_ratio": 0.0,
    "trust_ratio": 4.132583540357828,
    "dealer_ratio": 35.74575056193139,
    "three_inst_ratio": 39.878334102289216,
    "three_inst_ratio_change_20": 7.020341532563101
  },
  {
    "date": "2026-03-17",
    "code": "3491",
    "name": "昇達科",
    "market": "TPEX",
    "foreign_ratio": 0.0,
    "trust_ratio": 4.132583540357828,
    "dealer_ratio": 35.89585770364459,
    "three_inst_ratio": 40.028441244002416,
    "three_inst_ratio_change_20": 6.447106181128234
  },
  {
    "date": "2026-03-18",
    "code": "3491",
    "name": "昇達科",
    "market": "TPEX",
    "foreign_ratio": 0.0,
    "trust_ratio": 4.132583540357828,
    "dealer_ratio": 36.03364011863146,
    "three_inst_ratio": 40.16622365898929,
    "three_inst_ratio_change_20": 6.023336475232455
  },
  {
    "date": "2026-03-19",
    "code": "3491",
    "name": "昇達科",
    "market": "TPEX",
    "foreign_ratio": 0.0,
    "trust_ratio": 4.132583540357828,
    "dealer_ratio": 36.16703576647844,
    "three_inst_ratio": 40.29961930683627,
    "three_inst_ratio_change_20": 5.43420742643972
  },
  {
    "date": "2026-03-20",
    "code": "3491",
    "name": "昇達科",
    "market": "TPEX",
    "foreign_ratio": 0.0,
    "trust_ratio": 4.132583540357828,
    "dealer_ratio": 36.30148625329996,
    "three_inst_ratio": 40.43406979365779,
    "three_inst_ratio_change_20": 5.28698479523694
  },
  {
    "date": "2026-03-23",
    "code": "3491",
    "name": "昇達科",
    "market": "TPEX",
    "foreign_ratio": 0.0,
    "trust_ratio": 4.132583540357828,
    "dealer_ratio": 36.51187625719546,
    "three_inst_ratio": 40.64445979755329,
    "three_inst_ratio_change_20": 5.037227963769361
  },
  {
    "date": "2026-03-24",
    "code": "3491",
    "name": "昇達科",
    "market": "TPEX",
    "foreign_ratio": 0.0,
    "trust_ratio": 4.132583540357828,
    "dealer_ratio": 36.69709531421268,
    "three_inst_ratio": 40.82967885457051,
    "three_inst_ratio_change_20": 4.72197778040961
  },
  {
    "date": "2026-03-25",
    "code": "3491",
    "name": "昇達科",
    "market": "TPEX",
    "foreign_ratio": 0.0,
    "trust_ratio": 4.132583540357828,
    "dealer_ratio": 36.96821263491457,
    "three_inst_ratio": 41.1007961752724,
    "three_inst_ratio_change_20": 4.703775882037235
  },
  {
    "date": "2026-03-26",
    "code": "3491",
    "name": "昇達科",
    "market": "TPEX",
    "foreign_ratio": 0.0,
    "trust_ratio": 4.132583540357828,
    "dealer_ratio": 37.880371304504244,
    "three_inst_ratio": 42.01295484486207,
    "three_inst_ratio_change_20": 5.144597830344374
  },
  {
    "date": "2026-03-27",
    "code": "3491",
    "name": "昇達科",
    "market": "TPEX",
    "foreign_ratio": 0.0,
    "trust_ratio": 4.132583540357828,
    "dealer_ratio": 40.04712463488423,
    "three_inst_ratio": 44.179708175242055,
    "three_inst_ratio_change_20": 6.513426218621241
  },
  {
    "date": "2026-03-30",
    "code": "3491",
    "name": "昇達科",
    "market": "TPEX",
    "foreign_ratio": 0.0,
    "trust_ratio": 4.132583540357828,
    "dealer_ratio": 41.260229456514665,
    "three_inst_ratio": 45.39281299687249,
    "three_inst_ratio_change_20": 7.462239061060572
  },
  {
    "date": "2026-03-31",
    "code": "3491",
    "name": "昇達科",
    "market": "TPEX",
    "foreign_ratio": 0.0,
    "trust_ratio": 4.054102074518432,
    "dealer_ratio": 42.03642388557539,
    "three_inst_ratio": 46.09052596009382,
    "three_inst_ratio_change_20": 7.78948872448543
  },
  {
    "date": "2026-04-01",
    "code": "3491",
    "name": "昇達科",
    "market": "TPEX",
    "foreign_ratio": 0.0,
    "trust_ratio": 4.054102074518432,
    "dealer_ratio": 43.82707247461581,
    "three_inst_ratio": 47.88117454913424,
    "three_inst_ratio_change_20": 9.56380953215178
  },
  {
    "date": "2026-04-02",
    "code": "3491",
    "name": "昇達科",
    "market": "TPEX",
    "foreign_ratio": 0.0,
    "trust_ratio": 4.054102074518432,
    "dealer_ratio": 45.212886394727136,
    "three_inst_ratio": 49.26698846924557,
    "three_inst_ratio_change_20": 10.788111604895462
  },
  {
    "date": "2026-04-07",
    "code": "3491",
    "name": "昇達科",
    "market": "TPEX",
    "foreign_ratio": 0.0,
    "trust_ratio": 4.054102074518432,
    "dealer_ratio": 46.135782763275266,
    "three_inst_ratio": 50.1898848377937,
    "three_inst_ratio_change_20": 11.500065364298791
  },
  {
    "date": "2026-04-08",
    "code": "3491",
    "name": "昇達科",
    "market": "TPEX",
    "foreign_ratio": 0.0,
    "trust_ratio": 4.054102074518432,
    "dealer_ratio": 47.83288744842771,
    "three_inst_ratio": 51.886989522946145,
    "three_inst_ratio_change_20": 13.109827308238238
  },
  {
    "date": "2026-04-09",
    "code": "3491",
    "name": "昇達科",
    "market": "TPEX",
    "foreign_ratio": 0.0,
    "trust_ratio": 4.054102074518432,
    "dealer_ratio": 49.093056658206784,
    "three_inst_ratio": 53.14715873272522,
    "three_inst_ratio_change_20": 14.098808084575552
  },
  {
    "date": "2026-04-10",
    "code": "3491",
    "name": "昇達科",
    "market": "TPEX",
    "foreign_ratio": 0.0,
    "trust_ratio": 4.054102074518432,
    "dealer_ratio": 50.48415652177073,
    "three_inst_ratio": 54.53825859628916,
    "three_inst_ratio_change_20": 15.457314609038725
  },
  {
    "date": "2026-04-13",
    "code": "3491",
    "name": "昇達科",
    "market": "TPEX",
    "foreign_ratio": 0.0,
    "trust_ratio": 4.054102074518432,
    "dealer_ratio": 51.363287255128164,
    "three_inst_ratio": 55.417389329646596,
    "three_inst_ratio_change_20": 15.788283157822278
  },
  {
    "date": "2026-04-14",
    "code": "3491",
    "name": "昇達科",
    "market": "TPEX",
    "foreign_ratio": 0.0,
    "trust_ratio": 4.054102074518432,
    "dealer_ratio": 52.35982784712622,
    "three_inst_ratio": 56.41392992164465,
    "three_inst_ratio_change_20": 16.732637369373755
  },
  {
    "date": "2026-04-15",
    "code": "3491",
    "name": "昇達科",
    "market": "TPEX",
    "foreign_ratio": 0.0,
    "trust_ratio": 4.054102074518432,
    "dealer_ratio": 53.060531464770975,
    "three_inst_ratio": 57.11463353928941,
    "three_inst_ratio_change_20": 17.23629943700019
  },
  {
    "date": "2026-04-16",
    "code": "3491",
    "name": "昇達科",
    "market": "TPEX",
    "foreign_ratio": 0.0,
    "trust_ratio": 4.054102074518432,
    "dealer_ratio": 53.62368718899937,
    "three_inst_ratio": 57.6777892635178,
    "three_inst_ratio_change_20": 17.649348019515386
  },
  {
    "date": "2026-04-17",
    "code": "3491",
    "name": "昇達科",
    "market": "TPEX",
    "foreign_ratio": 0.0,
    "trust_ratio": 4.054102074518432,
    "dealer_ratio": 54.55469051178964,
    "three_inst_ratio": 58.60879258630807,
    "three_inst_ratio_change_20": 18.44256892731878
  },
  {
    "date": "2026-04-20",
    "code": "3491",
    "name": "昇達科",
    "market": "TPEX",
    "foreign_ratio": 0.0,
    "trust_ratio": 4.054102074518432,
    "dealer_ratio": 55.22579168339568,
    "three_inst_ratio": 59.27989375791411,
    "three_inst_ratio_change_20": 18.98027445107784
  },
  {
    "date": "2026-04-21",
    "code": "3491",
    "name": "昇達科",
    "market": "TPEX",
    "foreign_ratio": 0.0,
    "trust_ratio": 4.054102074518432,
    "dealer_ratio": 55.93238149047763,
    "three_inst_ratio": 59.986483564996064,
    "three_inst_ratio_change_20": 19.552413771338273
  },
  {
    "date": "2026-04-22",
    "code": "3491",
    "name": "昇達科",
    "market": "TPEX",
    "foreign_ratio": 0.0,
    "trust_ratio": 4.054102074518432,
    "dealer_ratio": 56.513589649026876,
    "three_inst_ratio": 60.56769172354531,
    "three_inst_ratio_change_20": 19.92323192599202
  },
  {
    "date": "2026-04-23",
    "code": "3491",
    "name": "昇達科",
    "market": "TPEX",
    "foreign_ratio": 0.0,
    "trust_ratio": 4.054102074518432,
    "dealer_ratio": 57.68495297406988,
    "three_inst_ratio": 61.73905504858831,
    "three_inst_ratio_change_20": 20.909376194017803
  },
  {
    "date": "2026-04-24",
    "code": "3491",
    "name": "昇達科",
    "market": "TPEX",
    "foreign_ratio": 0.0,
    "trust_ratio": 4.054102074518432,
    "dealer_ratio": 59.368932183467436,
    "three_inst_ratio": 63.42303425798587,
    "three_inst_ratio_change_20": 22.32223808271347
  },
  {
    "date": "2026-04-27",
    "code": "3491",
    "name": "昇達科",
    "market": "TPEX",
    "foreign_ratio": 0.0,
    "trust_ratio": 4.054102074518432,
    "dealer_ratio": 60.772645932988276,
    "three_inst_ratio": 64.82674800750671,
    "three_inst_ratio_change_20": 22.813793162644636
  },
  {
    "date": "2026-04-28",
    "code": "3491",
    "name": "昇達科",
    "market": "TPEX",
    "foreign_ratio": 0.0,
    "trust_ratio": 4.054102074518432,
    "dealer_ratio": 61.59413270450421,
    "three_inst_ratio": 65.64823477902264,
    "three_inst_ratio_change_20": 21.46852660378059
  },
  {
    "date": "2026-04-29",
    "code": "3491",
    "name": "昇達科",
    "market": "TPEX",
    "foreign_ratio": 0.0,
    "trust_ratio": 4.054102074518432,
    "dealer_ratio": 62.701335111301674,
    "three_inst_ratio": 66.7554371858201,
    "three_inst_ratio_change_20": 21.362624188947606
  },
  {
    "date": "2026-04-30",
    "code": "3491",
    "name": "昇達科",
    "market": "TPEX",
    "foreign_ratio": 0.0,
    "trust_ratio": 4.054102074518432,
    "dealer_ratio": 63.23833435372729,
    "three_inst_ratio": 67.29243642824572,
    "three_inst_ratio_change_20": 21.2019104681519
  },
  {
    "date": "2026-05-04",
    "code": "3491",
    "name": "昇達科",
    "market": "TPEX",
    "foreign_ratio": 0.0,
    "trust_ratio": 4.054102074518432,
    "dealer_ratio": 63.77535830361474,
    "three_inst_ratio": 67.82946037813316,
    "three_inst_ratio_change_20": 19.94828582899892
  },
  {
    "date": "2026-05-05",
    "code": "3491",
    "name": "昇達科",
    "market": "TPEX",
    "foreign_ratio": 0.0,
    "trust_ratio": 4.054102074518432,
    "dealer_ratio": 65.13382251685466,
    "three_inst_ratio": 69.18792459137309,
    "three_inst_ratio_change_20": 19.92093612212752
  },
  {
    "date": "2026-05-06",
    "code": "3491",
    "name": "昇達科",
    "market": "TPEX",
    "foreign_ratio": 0.0,
    "trust_ratio": 4.054102074518432,
    "dealer_ratio": 65.94075368658949,
    "three_inst_ratio": 69.99485576110791,
    "three_inst_ratio_change_20": 19.804970923314215
  },
  {
    "date": "2026-05-07",
    "code": "3491",
    "name": "昇達科",
    "market": "TPEX",
    "foreign_ratio": 0.0,
    "trust_ratio": 4.054102074518432,
    "dealer_ratio": 66.56154901251905,
    "three_inst_ratio": 70.61565108703748,
    "three_inst_ratio_change_20": 18.728661564091333
  },
  {
    "date": "2026-05-08",
    "code": "3491",
    "name": "昇達科",
    "market": "TPEX",
    "foreign_ratio": 0.0,
    "trust_ratio": 4.054102074518432,
    "dealer_ratio": 67.64594352528246,
    "three_inst_ratio": 71.70004559980089,
    "three_inst_ratio_change_20": 18.55288686707567
  },
  {
    "date": "2026-05-11",
    "code": "3491",
    "name": "昇達科",
    "market": "TPEX",
    "foreign_ratio": 0.0,
    "trust_ratio": 4.054102074518432,
    "dealer_ratio": 69.89340256267248,
    "three_inst_ratio": 73.9475046371909,
    "three_inst_ratio_change_20": 19.409246040901742
  },
  {
    "date": "2026-05-12",
    "code": "3491",
    "name": "昇達科",
    "market": "TPEX",
    "foreign_ratio": 0.0,
    "trust_ratio": 4.054102074518432,
    "dealer_ratio": 71.0911854313178,
    "three_inst_ratio": 75.14528750583622,
    "three_inst_ratio_change_20": 19.727898176189626
  },
  {
    "date": "2026-05-13",
    "code": "3491",
    "name": "昇達科",
    "market": "TPEX",
    "foreign_ratio": 0.0,
    "trust_ratio": 4.054102074518432,
    "dealer_ratio": 71.90169627625849,
    "three_inst_ratio": 75.95579835077692,
    "three_inst_ratio_change_20": 19.541868429132265
  },
  {
    "date": "2026-05-14",
    "code": "3491",
    "name": "昇達科",
    "market": "TPEX",
    "foreign_ratio": 0.0,
    "trust_ratio": 4.054102074518432,
    "dealer_ratio": 72.26843058565768,
    "three_inst_ratio": 76.32253266017611,
    "three_inst_ratio_change_20": 19.2078991208867
  },
  {
    "date": "2026-05-15",
    "code": "3491",
    "name": "昇達科",
    "market": "TPEX",
    "foreign_ratio": 0.0,
    "trust_ratio": 4.054102074518432,
    "dealer_ratio": 73.8988905259601,
    "three_inst_ratio": 77.95299260047852,
    "three_inst_ratio_change_20": 20.275203336960722
  },
  {
    "date": "2026-05-18",
    "code": "3491",
    "name": "昇達科",
    "market": "TPEX",
    "foreign_ratio": 0.0,
    "trust_ratio": 4.054102074518432,
    "dealer_ratio": 74.74613845988944,
    "three_inst_ratio": 78.80024053440786,
    "three_inst_ratio_change_20": 20.191447948099793
  },
  {
    "date": "2026-05-19",
    "code": "3491",
    "name": "昇達科",
    "market": "TPEX",
    "foreign_ratio": 0.0,
    "trust_ratio": 4.054102074518432,
    "dealer_ratio": 77.62792379201404,
    "three_inst_ratio": 81.68202586653247,
    "three_inst_ratio_change_20": 22.40213210861836
  },
  {
    "date": "2026-05-20",
    "code": "3491",
    "name": "昇達科",
    "market": "TPEX",
    "foreign_ratio": 0.0,
    "trust_ratio": 4.054102074518432,
    "dealer_ratio": 78.820558788317,
    "three_inst_ratio": 82.87466086283543,
    "three_inst_ratio_change_20": 22.888177297839363
  },
  {
    "date": "2026-05-21",
    "code": "3491",
    "name": "昇達科",
    "market": "TPEX",
    "foreign_ratio": 0.0,
    "trust_ratio": 4.054102074518432,
    "dealer_ratio": 80.029417866765,
    "three_inst_ratio": 84.08351994128343,
    "three_inst_ratio_change_20": 23.515828217738118
  },
  {
    "date": "2026-05-22",
    "code": "3491",
    "name": "昇達科",
    "market": "TPEX",
    "foreign_ratio": 0.0,
    "trust_ratio": 4.054102074518432,
    "dealer_ratio": 81.64051878402954,
    "three_inst_ratio": 85.69462085854796,
    "three_inst_ratio_change_20": 23.95556580995965
  },
  {
    "date": "2026-05-25",
    "code": "3491",
    "name": "昇達科",
    "market": "TPEX",
    "foreign_ratio": 0.0,
    "trust_ratio": 4.054102074518432,
    "dealer_ratio": 83.4169518622341,
    "three_inst_ratio": 87.47105393675253,
    "three_inst_ratio_change_20": 24.048019678766657
  },
  {
    "date": "2026-05-26",
    "code": "3491",
    "name": "昇達科",
    "market": "TPEX",
    "foreign_ratio": 0.0,
    "trust_ratio": 4.054102074518432,
    "dealer_ratio": 83.67886403810762,
    "three_inst_ratio": 87.73296611262604,
    "three_inst_ratio_change_20": 22.906218105119336
  },
  {
    "date": "2026-05-27",
    "code": "3491",
    "name": "昇達科",
    "market": "TPEX",
    "foreign_ratio": 0.0,
    "trust_ratio": 4.054102074518432,
    "dealer_ratio": 83.91728377791625,
    "three_inst_ratio": 87.97138585243468,
    "three_inst_ratio_change_20": 22.323151073412035
  },
  {
    "date": "2026-05-28",
    "code": "3491",
    "name": "昇達科",
    "market": "TPEX",
    "foreign_ratio": 0.0,
    "trust_ratio": 4.054102074518432,
    "dealer_ratio": 84.67778962686282,
    "three_inst_ratio": 88.73189170138124,
    "three_inst_ratio_change_20": 21.976454515561144
  },
  {
    "date": "2026-05-29",
    "code": "3491",
    "name": "昇達科",
    "market": "TPEX",
    "foreign_ratio": 0.0,
    "trust_ratio": 4.054102074518432,
    "dealer_ratio": 85.45921542908323,
    "three_inst_ratio": 89.51331750360166,
    "three_inst_ratio_change_20": 22.220881075355933
  },
  {
    "date": "2026-06-01",
    "code": "3491",
    "name": "昇達科",
    "market": "TPEX",
    "foreign_ratio": 0.0,
    "trust_ratio": 4.054102074518432,
    "dealer_ratio": 86.22512494527116,
    "three_inst_ratio": 90.27922701978959,
    "three_inst_ratio_change_20": 22.449766641656424
  },
  {
    "date": "2026-06-02",
    "code": "3491",
    "name": "昇達科",
    "market": "TPEX",
    "foreign_ratio": 0.0,
    "trust_ratio": 4.054102074518432,
    "dealer_ratio": 86.52903689950422,
    "three_inst_ratio": 90.58313897402265,
    "three_inst_ratio_change_20": 21.395214382649556
  },
  {
    "date": "2026-06-03",
    "code": "3491",
    "name": "昇達科",
    "market": "TPEX",
    "foreign_ratio": 0.0,
    "trust_ratio": 4.054102074518432,
    "dealer_ratio": 86.71484863954538,
    "three_inst_ratio": 90.7689507140638,
    "three_inst_ratio_change_20": 20.774094952955892
  },
  {
    "date": "2026-06-04",
    "code": "3491",
    "name": "昇達科",
    "market": "TPEX",
    "foreign_ratio": 0.0,
    "trust_ratio": 4.054102074518432,
    "dealer_ratio": 86.8650176858192,
    "three_inst_ratio": 90.91911976033762,
    "three_inst_ratio_change_20": 20.303468673300145
  },
  {
    "date": "2026-06-05",
    "code": "3491",
    "name": "昇達科",
    "market": "TPEX",
    "foreign_ratio": 0.0,
    "trust_ratio": 4.054102074518432,
    "dealer_ratio": 87.37614240218298,
    "three_inst_ratio": 91.4302444767014,
    "three_inst_ratio_change_20": 19.730198876900516
  },
  {
    "date": "2026-06-08",
    "code": "3491",
    "name": "昇達科",
    "market": "TPEX",
    "foreign_ratio": 0.0,
    "trust_ratio": 4.054102074518432,
    "dealer_ratio": 87.55988888909074,
    "three_inst_ratio": 91.61399096360917,
    "three_inst_ratio_change_20": 17.666486326418266
  },
  {
    "date": "2026-06-09",
    "code": "3491",
    "name": "昇達科",
    "market": "TPEX",
    "foreign_ratio": 0.0,
    "trust_ratio": 4.054102074518432,
    "dealer_ratio": 89.89826411913356,
    "three_inst_ratio": 93.95236619365198,
    "three_inst_ratio_change_20": 18.80707868781576
  },
  {
    "date": "2026-06-10",
    "code": "3491",
    "name": "昇達科",
    "market": "TPEX",
    "foreign_ratio": 0.0,
    "trust_ratio": 4.054102074518432,
    "dealer_ratio": 91.1202893679795,
    "three_inst_ratio": 95.17439144249792,
    "three_inst_ratio_change_20": 19.218593091721004
  },
  {
    "date": "2026-06-11",
    "code": "3491",
    "name": "昇達科",
    "market": "TPEX",
    "foreign_ratio": 0.0,
    "trust_ratio": 4.054102074518432,
    "dealer_ratio": 92.67724170256213,
    "three_inst_ratio": 96.73134377708055,
    "three_inst_ratio_change_20": 20.408811116904445
  },
  {
    "date": "2026-06-12",
    "code": "3491",
    "name": "昇達科",
    "market": "TPEX",
    "foreign_ratio": 0.0,
    "trust_ratio": 4.054102074518432,
    "dealer_ratio": 93.44750699893358,
    "three_inst_ratio": 97.501609073452,
    "three_inst_ratio_change_20": 19.548616472973478
  },
  {
    "date": "2026-06-15",
    "code": "3491",
    "name": "昇達科",
    "market": "TPEX",
    "foreign_ratio": 0.0,
    "trust_ratio": 4.054102074518432,
    "dealer_ratio": 94.4857610534099,
    "three_inst_ratio": 98.53986312792833,
    "three_inst_ratio_change_20": 19.739622593520465
  },
  {
    "date": "2026-06-16",
    "code": "3491",
    "name": "昇達科",
    "market": "TPEX",
    "foreign_ratio": 0.0,
    "trust_ratio": 4.054102074518432,
    "dealer_ratio": 96.32441624079601,
    "three_inst_ratio": 100.37851831531444,
    "three_inst_ratio_change_20": 18.696492448781967
  },
  {
    "date": "2026-06-17",
    "code": "3491",
    "name": "昇達科",
    "market": "TPEX",
    "foreign_ratio": 0.0,
    "trust_ratio": 4.054102074518432,
    "dealer_ratio": 96.7786818205766,
    "three_inst_ratio": 100.83278389509502,
    "three_inst_ratio_change_20": 17.958123032259593
  },
  {
    "date": "2026-06-18",
    "code": "3491",
    "name": "昇達科",
    "market": "TPEX",
    "foreign_ratio": 0.0,
    "trust_ratio": 4.054102074518432,
    "dealer_ratio": 97.56269318600904,
    "three_inst_ratio": 101.61679526052747,
    "three_inst_ratio_change_20": 17.53327531924404
  },
  {
    "date": "2026-06-22",
    "code": "3491",
    "name": "昇達科",
    "market": "TPEX",
    "foreign_ratio": 0.0,
    "trust_ratio": 4.054102074518432,
    "dealer_ratio": 98.94679647773332,
    "three_inst_ratio": 103.00089855225174,
    "three_inst_ratio_change_20": 17.306277693703777
  },
  {
    "date": "2026-06-23",
    "code": "3491",
    "name": "昇達科",
    "market": "TPEX",
    "foreign_ratio": 0.0,
    "trust_ratio": 4.054102074518432,
    "dealer_ratio": 101.01747943921329,
    "three_inst_ratio": 105.07158151373172,
    "three_inst_ratio_change_20": 17.60052757697919
  },
  {
    "date": "2026-06-24",
    "code": "3491",
    "name": "昇達科",
    "market": "TPEX",
    "foreign_ratio": 0.0,
    "trust_ratio": 4.054102074518432,
    "dealer_ratio": 102.40142867264612,
    "three_inst_ratio": 106.45553074716454,
    "three_inst_ratio_change_20": 18.7225646345385
  },
  {
    "date": "2026-06-25",
    "code": "3491",
    "name": "昇達科",
    "market": "TPEX",
    "foreign_ratio": 0.0,
    "trust_ratio": 4.054102074518432,
    "dealer_ratio": 102.87165672615231,
    "three_inst_ratio": 106.92575880067074,
    "three_inst_ratio_change_20": 18.954372948236056
  },
  {
    "date": "2026-06-26",
    "code": "3491",
    "name": "昇達科",
    "market": "TPEX",
    "foreign_ratio": 0.0,
    "trust_ratio": 4.054102074518432,
    "dealer_ratio": 104.5189119269822,
    "three_inst_ratio": 108.57301400150062,
    "three_inst_ratio_change_20": 19.84112230011938
  }
]