[
  {
    "date": "2025-12-24",
    "code": "6620",
    "name": "漢達",
    "market": "TPEX",
    "foreign_ratio": 0.0,
    "trust_ratio": 0.0,
    "dealer_ratio": 0.05118155863729982,
    "three_inst_ratio": 0.05118155863729982,
    "three_inst_ratio_change_20": 0.0
  },
  {
    "date": "2025-12-26",
    "code": "6620",
    "name": "漢達",
    "market": "TPEX",
    "foreign_ratio": 0.0,
    "trust_ratio": 0.0,
    "dealer_ratio": 0.20649111588151997,
    "three_inst_ratio": 0.20649111588151997,
    "three_inst_ratio_change_20": 0.0
  },
  {
    "date": "2025-12-29",
    "code": "6620",
    "name": "漢達",
    "market": "TPEX",
    "foreign_ratio": 0.0,
    "trust_ratio": 0.0,
    "dealer_ratio": 0.23061116075656932,
    "three_inst_ratio": 0.23061116075656932,
    "three_inst_ratio_change_20": 0.0
  },
  {
    "date": "2025-12-30",
    "code": "6620",
    "name": "漢達",
    "market": "TPEX",
    "foreign_ratio": 0.0,
    "trust_ratio": 0.0,
    "dealer_ratio": 0.29414688872011396,
    "three_inst_ratio": 0.29414688872011396,
    "three_inst_ratio_change_20": 0.0
  },
  {
    "date": "2025-12-31",
    "code": "6620",
    "name": "漢達",
    "market": "TPEX",
    "foreign_ratio": 0.0,
    "trust_ratio": 0.0,
    "dealer_ratio": 0.32767963403420697,
    "three_inst_ratio": 0.32767963403420697,
    "three_inst_ratio_change_20": 0.0
  },
  {
    "date": "2026-01-02",
    "code": "6620",
    "name": "漢達",
    "market": "TPEX",
    "foreign_ratio": 0.0,
    "trust_ratio": 0.0,
    "dealer_ratio": 0.35121138513181605,
    "three_inst_ratio": 0.35121138513181605,
    "three_inst_ratio_change_20": 0.0
  },
  {
    "date": "2026-01-05",
    "code": "6620",
    "name": "漢達",
    "market": "TPEX",
    "foreign_ratio": 0.0,
    "trust_ratio": 0.0,
    "dealer_ratio": 0.43592568908320883,
    "three_inst_ratio": 0.43592568908320883,
    "three_inst_ratio_change_20": 0.0
  },
  {
    "date": "2026-01-06",
    "code": "6620",
    "name": "漢達",
    "market": "TPEX",
    "foreign_ratio": 0.0,
    "trust_ratio": 0.0,
    "dealer_ratio": 0.5159336428150798,
    "three_inst_ratio": 0.5159336428150798,
    "three_inst_ratio_change_20": 0.0
  },
  {
    "date": "2026-01-07",
    "code": "6620",
    "name": "漢達",
    "market": "TPEX",
    "foreign_ratio": 0.0,
    "trust_ratio": 0.0,
    "dealer_ratio": 0.580645958333505,
    "three_inst_ratio": 0.580645958333505,
    "three_inst_ratio_change_20": 0.0
  },
  {
    "date": "2026-01-08",
    "code": "6620",
    "name": "漢達",
    "market": "TPEX",
    "foreign_ratio": 0.0,
    "trust_ratio": 0.0,
    "dealer_ratio": 0.5977064778792716,
    "three_inst_ratio": 0.5977064778792716,
    "three_inst_ratio_change_20": 0.0
  },
  {
    "date": "2026-01-09",
    "code": "6620",
    "name": "漢達",
    "market": "TPEX",
    "foreign_ratio": 0.0,
    "trust_ratio": 0.0,
    "dealer_ratio": 0.7188949960319584,
    "three_inst_ratio": 0.7188949960319584,
    "three_inst_ratio_change_20": 0.0
  },
  {
    "date": "2026-01-12",
    "code": "6620",
    "name": "漢達",
    "market": "TPEX",
    "foreign_ratio": 0.0,
    "trust_ratio": 0.0,
    "dealer_ratio": 0.7771360799985411,
    "three_inst_ratio": 0.7771360799985411,
    "three_inst_ratio_change_20": 0.0
  },
  {
    "date": "2026-01-13",
    "code": "6620",
    "name": "漢達",
    "market": "TPEX",
    "foreign_ratio": 0.0,
    "trust_ratio": 0.0,
    "dealer_ratio": 0.8689099092792165,
    "three_inst_ratio": 0.8689099092792165,
    "three_inst_ratio_change_20": 0.0
  },
  {
    "date": "2026-01-14",
    "code": "6620",
    "name": "漢達",
    "market": "TPEX",
    "foreign_ratio": 0.0,
    "trust_ratio": 0.0,
    "dealer_ratio": 1.035397048294801,
    "three_inst_ratio": 1.035397048294801,
    "three_inst_ratio_change_20": 0.0
  },
  {
    "date": "2026-01-15",
    "code": "6620",
    "name": "漢達",
    "market": "TPEX",
    "foreign_ratio": 0.0,
    "trust_ratio": 0.0,
    "dealer_ratio": 1.1136401206943514,
    "three_inst_ratio": 1.1136401206943514,
    "three_inst_ratio_change_20": 0.0
  },
  {
    "date": "2026-01-16",
    "code": "6620",
    "name": "漢達",
    "market": "TPEX",
    "foreign_ratio": 0.0,
    "trust_ratio": 0.0,
    "dealer_ratio": 1.2230627632982338,
    "three_inst_ratio": 1.2230627632982338,
    "three_inst_ratio_change_20": 0.0
  },
  {
    "date": "2026-01-19",
    "code": "6620",
    "name": "漢達",
    "market": "TPEX",
    "foreign_ratio": 0.0,
    "trust_ratio": 0.0,
    "dealer_ratio": 1.3142482988014692,
    "three_inst_ratio": 1.3142482988014692,
    "three_inst_ratio_change_20": 0.0
  },
  {
    "date": "2026-01-20",
    "code": "6620",
    "name": "漢達",
    "market": "TPEX",
    "foreign_ratio": 0.0,
    "trust_ratio": 0.0,
    "dealer_ratio": 1.3930796649784596,
    "three_inst_ratio": 1.3930796649784596,
    "three_inst_ratio_change_20": 0.0
  },
  {
    "date": "2026-01-21",
    "code": "6620",
    "name": "漢達",
    "market": "TPEX",
    "foreign_ratio": 0.0,
    "trust_ratio": 0.0,
    "dealer_ratio": 1.4366134045090364,
    "three_inst_ratio": 1.4366134045090364,
    "three_inst_ratio_change_20": 0.0
  },
  {
    "date": "2026-01-22",
    "code": "6620",
    "name": "漢達",
    "market": "TPEX",
    "foreign_ratio": 0.0,
    "trust_ratio": 0.0,
    "dealer_ratio": 1.4854417880365753,
    "three_inst_ratio": 1.4854417880365753,
    "three_inst_ratio_change_20": 0.0
  },
  {
    "date": "2026-01-23",
    "code": "6620",
    "name": "漢達",
    "market": "TPEX",
    "foreign_ratio": 0.0,
    "trust_ratio": 0.0,
    "dealer_ratio": 1.5789804986495717,
    "three_inst_ratio": 1.5789804986495717,
    "three_inst_ratio_change_20": 1.5277989400122718
  },
  {
    "date": "2026-01-26",
    "code": "6620",
    "name": "漢達",
    "market": "TPEX",
    "foreign_ratio": 0.0,
    "trust_ratio": 0.0,
    "dealer_ratio": 1.6378098763935942,
    "three_inst_ratio": 1.6378098763935942,
    "three_inst_ratio_change_20": 1.4313187605120743
  },
  {
    "date": "2026-01-27",
    "code": "6620",
    "name": "漢達",
    "market": "TPEX",
    "foreign_ratio": 0.0,
    "trust_ratio": 0.0,
    "dealer_ratio": 1.7145345625535717,
    "three_inst_ratio": 1.7145345625535717,
    "three_inst_ratio_change_20": 1.4839234017970024
  },
  {
    "date": "2026-01-28",
    "code": "6620",
    "name": "漢達",
    "market": "TPEX",
    "foreign_ratio": 0.0,
    "trust_ratio": 0.0,
    "dealer_ratio": 1.7227706754377348,
    "three_inst_ratio": 1.7227706754377348,
    "three_inst_ratio_change_20": 1.4286237867176208
  },
  {
    "date": "2026-01-29",
    "code": "6620",
    "name": "漢達",
    "market": "TPEX",
    "foreign_ratio": 0.0,
    "trust_ratio": 0.0,
    "dealer_ratio": 1.756891714529268,
    "three_inst_ratio": 1.756891714529268,
    "three_inst_ratio_change_20": 1.429212080495061
  },
  {
    "date": "2026-01-30",
    "code": "6620",
    "name": "漢達",
    "market": "TPEX",
    "foreign_ratio": 0.0,
    "trust_ratio": 0.0,
    "dealer_ratio": 1.7874829909561598,
    "three_inst_ratio": 1.7874829909561598,
    "three_inst_ratio_change_20": 1.4362716058243437
  },
  {
    "date": "2026-02-02",
    "code": "6620",
    "name": "漢達",
    "market": "TPEX",
    "foreign_ratio": 0.0,
    "trust_ratio": 0.0,
    "dealer_ratio": 1.8521953064745849,
    "three_inst_ratio": 1.8521953064745849,
    "three_inst_ratio_change_20": 1.416269617391376
  },
  {
    "date": "2026-02-03",
    "code": "6620",
    "name": "漢達",
    "market": "TPEX",
    "foreign_ratio": 0.0,
    "trust_ratio": 0.0,
    "dealer_ratio": 1.881021701569156,
    "three_inst_ratio": 1.881021701569156,
    "three_inst_ratio_change_20": 1.3650880587540761
  },
  {
    "date": "2026-02-04",
    "code": "6620",
    "name": "漢達",
    "market": "TPEX",
    "foreign_ratio": 0.0,
    "trust_ratio": 0.0,
    "dealer_ratio": 1.896905633560042,
    "three_inst_ratio": 1.896905633560042,
    "three_inst_ratio_change_20": 1.316259675226537
  },
  {
    "date": "2026-02-05",
    "code": "6620",
    "name": "漢達",
    "market": "TPEX",
    "foreign_ratio": 0.0,
    "trust_ratio": 0.0,
    "dealer_ratio": 1.91690762199301,
    "three_inst_ratio": 1.91690762199301,
    "three_inst_ratio_change_20": 1.3192011441137383
  },
  {
    "date": "2026-02-06",
    "code": "6620",
    "name": "漢達",
    "market": "TPEX",
    "foreign_ratio": 0.0,
    "trust_ratio": 0.0,
    "dealer_ratio": 1.9539701299717442,
    "three_inst_ratio": 1.9539701299717442,
    "three_inst_ratio_change_20": 1.2350751339397859
  },
  {
    "date": "2026-02-09",
    "code": "6620",
    "name": "漢達",
    "market": "TPEX",
    "foreign_ratio": 0.0,
    "trust_ratio": 0.0,
    "dealer_ratio": 2.0086814512736852,
    "three_inst_ratio": 2.0086814512736852,
    "three_inst_ratio_change_20": 1.231545371275144
  },
  {
    "date": "2026-02-10",
    "code": "6620",
    "name": "漢達",
    "market": "TPEX",
    "foreign_ratio": 0.0,
    "trust_ratio": 0.0,
    "dealer_ratio": 2.0398610214780173,
    "three_inst_ratio": 2.0398610214780173,
    "three_inst_ratio_change_20": 1.1709511121988008
  },
  {
    "date": "2026-02-11",
    "code": "6620",
    "name": "漢達",
    "market": "TPEX",
    "foreign_ratio": 0.0,
    "trust_ratio": 0.0,
    "dealer_ratio": 2.076335235679312,
    "three_inst_ratio": 2.076335235679312,
    "three_inst_ratio_change_20": 1.040938187384511
  },
  {
    "date": "2026-02-23",
    "code": "6620",
    "name": "漢達",
    "market": "TPEX",
    "foreign_ratio": 0.0,
    "trust_ratio": 0.0,
    "dealer_ratio": 2.12398703165197,
    "three_inst_ratio": 2.12398703165197,
    "three_inst_ratio_change_20": 1.0103469109576186
  },
  {
    "date": "2026-02-24",
    "code": "6620",
    "name": "漢達",
    "market": "TPEX",
    "foreign_ratio": 0.0,
    "trust_ratio": 0.0,
    "dealer_ratio": 2.1492836640819,
    "three_inst_ratio": 2.1492836640819,
    "three_inst_ratio_change_20": 0.9262209007836664
  },
  {
    "date": "2026-02-25",
    "code": "6620",
    "name": "漢達",
    "market": "TPEX",
    "foreign_ratio": 0.0,
    "trust_ratio": 0.0,
    "dealer_ratio": 2.190464228502716,
    "three_inst_ratio": 2.190464228502716,
    "three_inst_ratio_change_20": 0.8762159297012466
  },
  {
    "date": "2026-02-26",
    "code": "6620",
    "name": "漢達",
    "market": "TPEX",
    "foreign_ratio": 0.0,
    "trust_ratio": 0.0,
    "dealer_ratio": 2.205171572938722,
    "three_inst_ratio": 2.205171572938722,
    "three_inst_ratio_change_20": 0.8120919079602622
  },
  {
    "date": "2026-03-02",
    "code": "6620",
    "name": "漢達",
    "market": "TPEX",
    "foreign_ratio": 0.0,
    "trust_ratio": 0.0,
    "dealer_ratio": 2.2563531315760215,
    "three_inst_ratio": 2.2563531315760215,
    "three_inst_ratio_change_20": 0.8197397270669851
  },
  {
    "date": "2026-03-03",
    "code": "6620",
    "name": "漢達",
    "market": "TPEX",
    "foreign_ratio": 0.0,
    "trust_ratio": 0.0,
    "dealer_ratio": 2.3134176279877234,
    "three_inst_ratio": 2.3134176279877234,
    "three_inst_ratio_change_20": 0.8279758399511481
  },
  {
    "date": "2026-03-04",
    "code": "6620",
    "name": "漢達",
    "market": "TPEX",
    "foreign_ratio": 0.0,
    "trust_ratio": 0.0,
    "dealer_ratio": 2.3199494537986425,
    "three_inst_ratio": 2.3199494537986425,
    "three_inst_ratio_change_20": 0.7409689551490708
  },
  {
    "date": "2026-03-05",
    "code": "6620",
    "name": "漢達",
    "market": "TPEX",
    "foreign_ratio": 0.0,
    "trust_ratio": 0.0,
    "dealer_ratio": 2.3287738604602457,
    "three_inst_ratio": 2.3287738604602457,
    "three_inst_ratio_change_20": 0.6909639840666515
  },
  {
    "date": "2026-03-06",
    "code": "6620",
    "name": "漢達",
    "market": "TPEX",
    "foreign_ratio": 0.0,
    "trust_ratio": 0.0,
    "dealer_ratio": 2.3611300182194586,
    "three_inst_ratio": 2.3611300182194586,
    "three_inst_ratio_change_20": 0.6465954556658868
  },
  {
    "date": "2026-03-09",
    "code": "6620",
    "name": "漢達",
    "market": "TPEX",
    "foreign_ratio": 0.0,
    "trust_ratio": 0.0,
    "dealer_ratio": 2.3663405362062466,
    "three_inst_ratio": 2.3663405362062466,
    "three_inst_ratio_change_20": 0.6435698607685119
  },
  {
    "date": "2026-03-10",
    "code": "6620",
    "name": "漢達",
    "market": "TPEX",
    "foreign_ratio": 0.0,
    "trust_ratio": 0.0,
    "dealer_ratio": 2.4092859819593833,
    "three_inst_ratio": 2.4092859819593833,
    "three_inst_ratio_change_20": 0.6523942674301153
  },
  {
    "date": "2026-03-11",
    "code": "6620",
    "name": "漢達",
    "market": "TPEX",
    "foreign_ratio": 0.0,
    "trust_ratio": 0.0,
    "dealer_ratio": 2.435923335908099,
    "three_inst_ratio": 2.435923335908099,
    "three_inst_ratio_change_20": 0.6484403449519391
  },
  {
    "date": "2026-03-12",
    "code": "6620",
    "name": "漢達",
    "market": "TPEX",
    "foreign_ratio": 0.0,
    "trust_ratio": 0.0,
    "dealer_ratio": 2.445924330124583,
    "three_inst_ratio": 2.445924330124583,
    "three_inst_ratio_change_20": 0.5937290236499981
  },
  {
    "date": "2026-03-13",
    "code": "6620",
    "name": "漢達",
    "market": "TPEX",
    "foreign_ratio": 0.0,
    "trust_ratio": 0.0,
    "dealer_ratio": 2.4965175949844425,
    "three_inst_ratio": 2.4965175949844425,
    "three_inst_ratio_change_20": 0.6154958934152865
  },
  {
    "date": "2026-03-16",
    "code": "6620",
    "name": "漢達",
    "market": "TPEX",
    "foreign_ratio": 0.0,
    "trust_ratio": 0.0,
    "dealer_ratio": 2.504754296162383,
    "three_inst_ratio": 2.504754296162383,
    "three_inst_ratio_change_20": 0.6078486626023412
  },
  {
    "date": "2026-03-17",
    "code": "6620",
    "name": "漢達",
    "market": "TPEX",
    "foreign_ratio": 0.0,
    "trust_ratio": 0.0,
    "dealer_ratio": 2.5147552903788672,
    "three_inst_ratio": 2.5147552903788672,
    "three_inst_ratio_change_20": 0.5978476683858573
  },
  {
    "date": "2026-03-18",
    "code": "6620",
    "name": "漢達",
    "market": "TPEX",
    "foreign_ratio": 0.0,
    "trust_ratio": 0.0,
    "dealer_ratio": 2.5294626348148728,
    "three_inst_ratio": 2.5294626348148728,
    "three_inst_ratio_change_20": 0.5754925048431285
  },
  {
    "date": "2026-03-19",
    "code": "6620",
    "name": "漢達",
    "market": "TPEX",
    "foreign_ratio": 0.0,
    "trust_ratio": 0.0,
    "dealer_ratio": 2.556031746685406,
    "three_inst_ratio": 2.556031746685406,
    "three_inst_ratio_change_20": 0.5473502954117206
  },
  {
    "date": "2026-03-20",
    "code": "6620",
    "name": "漢達",
    "market": "TPEX",
    "foreign_ratio": 0.0,
    "trust_ratio": 0.0,
    "dealer_ratio": 2.561914684459808,
    "three_inst_ratio": 2.561914684459808,
    "three_inst_ratio_change_20": 0.5220536629817909
  },
  {
    "date": "2026-03-23",
    "code": "6620",
    "name": "漢達",
    "market": "TPEX",
    "foreign_ratio": 0.0,
    "trust_ratio": 0.0,
    "dealer_ratio": 2.5666210346793297,
    "three_inst_ratio": 2.5666210346793297,
    "three_inst_ratio_change_20": 0.4902857990000178
  },
  {
    "date": "2026-03-24",
    "code": "6620",
    "name": "漢達",
    "market": "TPEX",
    "foreign_ratio": 0.0,
    "trust_ratio": 0.0,
    "dealer_ratio": 2.573092266231172,
    "three_inst_ratio": 2.573092266231172,
    "three_inst_ratio_change_20": 0.44910523457920215
  },
  {
    "date": "2026-03-25",
    "code": "6620",
    "name": "漢達",
    "market": "TPEX",
    "foreign_ratio": 0.0,
    "trust_ratio": 0.0,
    "dealer_ratio": 2.587799610667178,
    "three_inst_ratio": 2.587799610667178,
    "three_inst_ratio_change_20": 0.4385159465852779
  },
  {
    "date": "2026-03-26",
    "code": "6620",
    "name": "漢達",
    "market": "TPEX",
    "foreign_ratio": 0.0,
    "trust_ratio": 0.0,
    "dealer_ratio": 2.5989771924385425,
    "three_inst_ratio": 2.5989771924385425,
    "three_inst_ratio_change_20": 0.4085129639358267
  },
  {
    "date": "2026-03-27",
    "code": "6620",
    "name": "漢達",
    "market": "TPEX",
    "foreign_ratio": 0.0,
    "trust_ratio": 0.0,
    "dealer_ratio": 2.627215293755673,
    "three_inst_ratio": 2.627215293755673,
    "three_inst_ratio_change_20": 0.4220437208169514
  },
  {
    "date": "2026-03-30",
    "code": "6620",
    "name": "漢達",
    "market": "TPEX",
    "foreign_ratio": 0.0,
    "trust_ratio": 0.0,
    "dealer_ratio": 2.6583948639600052,
    "three_inst_ratio": 2.6583948639600052,
    "three_inst_ratio_change_20": 0.4020417323839838
  },
  {
    "date": "2026-03-31",
    "code": "6620",
    "name": "漢達",
    "market": "TPEX",
    "foreign_ratio": 0.0,
    "trust_ratio": 0.0,
    "dealer_ratio": 2.7025168972680227,
    "three_inst_ratio": 2.7025168972680227,
    "three_inst_ratio_change_20": 0.38909926928029925
  },
  {
    "date": "2026-04-01",
    "code": "6620",
    "name": "漢達",
    "market": "TPEX",
    "foreign_ratio": 0.0,
    "trust_ratio": 0.0,
    "dealer_ratio": 2.7425214624277356,
    "three_inst_ratio": 2.7425214624277356,
    "three_inst_ratio_change_20": 0.42257200862909317
  },
  {
    "date": "2026-04-02",
    "code": "6620",
    "name": "漢達",
    "market": "TPEX",
    "foreign_ratio": 0.0,
    "trust_ratio": 0.0,
    "dealer_ratio": 2.756640513086301,
    "three_inst_ratio": 2.756640513086301,
    "three_inst_ratio_change_20": 0.4278666526260553
  },
  {
    "date": "2026-04-07",
    "code": "6620",
    "name": "漢達",
    "market": "TPEX",
    "foreign_ratio": 0.0,
    "trust_ratio": 0.0,
    "dealer_ratio": 2.804292309058959,
    "three_inst_ratio": 2.804292309058959,
    "three_inst_ratio_change_20": 0.44316229083950054
  },
  {
    "date": "2026-04-08",
    "code": "6620",
    "name": "漢達",
    "market": "TPEX",
    "foreign_ratio": 0.0,
    "trust_ratio": 0.0,
    "dealer_ratio": 2.8413848200203433,
    "three_inst_ratio": 2.8413848200203433,
    "three_inst_ratio_change_20": 0.4750442838140967
  },
  {
    "date": "2026-04-09",
    "code": "6620",
    "name": "漢達",
    "market": "TPEX",
    "foreign_ratio": 0.0,
    "trust_ratio": 0.0,
    "dealer_ratio": 2.8590336333435498,
    "three_inst_ratio": 2.8590336333435498,
    "three_inst_ratio_change_20": 0.4497476513841665
  },
  {
    "date": "2026-04-10",
    "code": "6620",
    "name": "漢達",
    "market": "TPEX",
    "foreign_ratio": 0.0,
    "trust_ratio": 0.0,
    "dealer_ratio": 2.9478659937370244,
    "three_inst_ratio": 2.9478659937370244,
    "three_inst_ratio_change_20": 0.5119426578289255
  },
  {
    "date": "2026-04-13",
    "code": "6620",
    "name": "漢達",
    "market": "TPEX",
    "foreign_ratio": 0.0,
    "trust_ratio": 0.0,
    "dealer_ratio": 2.9913997332676012,
    "three_inst_ratio": 2.9913997332676012,
    "three_inst_ratio_change_20": 0.5454754031430182
  },
  {
    "date": "2026-04-14",
    "code": "6620",
    "name": "漢達",
    "market": "TPEX",
    "foreign_ratio": 0.0,
    "trust_ratio": 0.0,
    "dealer_ratio": 3.027285653691455,
    "three_inst_ratio": 3.027285653691455,
    "three_inst_ratio_change_20": 0.5307680587070127
  },
  {
    "date": "2026-04-15",
    "code": "6620",
    "name": "漢達",
    "market": "TPEX",
    "foreign_ratio": 0.0,
    "trust_ratio": 0.0,
    "dealer_ratio": 3.1090590770494244,
    "three_inst_ratio": 3.1090590770494244,
    "three_inst_ratio_change_20": 0.6043047808870412
  },
  {
    "date": "2026-04-16",
    "code": "6620",
    "name": "漢達",
    "market": "TPEX",
    "foreign_ratio": 0.0,
    "trust_ratio": 0.0,
    "dealer_ratio": 3.202597787662421,
    "three_inst_ratio": 3.202597787662421,
    "three_inst_ratio_change_20": 0.6878424972835537
  },
  {
    "date": "2026-04-17",
    "code": "6620",
    "name": "漢達",
    "market": "TPEX",
    "foreign_ratio": 0.0,
    "trust_ratio": 0.0,
    "dealer_ratio": 3.2378954143088343,
    "three_inst_ratio": 3.2378954143088343,
    "three_inst_ratio_change_20": 0.7084327794939616
  },
  {
    "date": "2026-04-20",
    "code": "6620",
    "name": "漢達",
    "market": "TPEX",
    "foreign_ratio": 0.0,
    "trust_ratio": 0.0,
    "dealer_ratio": 3.379085920894489,
    "three_inst_ratio": 3.379085920894489,
    "three_inst_ratio_change_20": 0.8230541742090831
  },
  {
    "date": "2026-04-21",
    "code": "6620",
    "name": "漢達",
    "market": "TPEX",
    "foreign_ratio": 0.0,
    "trust_ratio": 0.0,
    "dealer_ratio": 3.440856767525713,
    "three_inst_ratio": 3.440856767525713,
    "three_inst_ratio_change_20": 0.8789420830659047
  },
  {
    "date": "2026-04-22",
    "code": "6620",
    "name": "漢達",
    "market": "TPEX",
    "foreign_ratio": 0.0,
    "trust_ratio": 0.0,
    "dealer_ratio": 3.5514559976844757,
    "three_inst_ratio": 3.5514559976844757,
    "three_inst_ratio_change_20": 0.9848349630051461
  },
  {
    "date": "2026-04-23",
    "code": "6620",
    "name": "漢達",
    "market": "TPEX",
    "foreign_ratio": 0.0,
    "trust_ratio": 0.0,
    "dealer_ratio": 3.6144034318705804,
    "three_inst_ratio": 3.6144034318705804,
    "three_inst_ratio_change_20": 1.0413111656394083
  },
  {
    "date": "2026-04-24",
    "code": "6620",
    "name": "漢達",
    "market": "TPEX",
    "foreign_ratio": 0.0,
    "trust_ratio": 0.0,
    "dealer_ratio": 3.6855869789408477,
    "three_inst_ratio": 3.6855869789408477,
    "three_inst_ratio_change_20": 1.0977873682736696
  },
  {
    "date": "2026-04-27",
    "code": "6620",
    "name": "漢達",
    "market": "TPEX",
    "foreign_ratio": 0.0,
    "trust_ratio": 0.0,
    "dealer_ratio": 3.7326504811360657,
    "three_inst_ratio": 3.7326504811360657,
    "three_inst_ratio_change_20": 1.1336732886975232
  },
  {
    "date": "2026-04-28",
    "code": "6620",
    "name": "漢達",
    "market": "TPEX",
    "foreign_ratio": 0.0,
    "trust_ratio": 0.0,
    "dealer_ratio": 3.780890570886165,
    "three_inst_ratio": 3.780890570886165,
    "three_inst_ratio_change_20": 1.1536752771304917
  },
  {
    "date": "2026-04-29",
    "code": "6620",
    "name": "漢達",
    "market": "TPEX",
    "foreign_ratio": 0.0,
    "trust_ratio": 0.0,
    "dealer_ratio": 3.7914369134343353,
    "three_inst_ratio": 3.7914369134343353,
    "three_inst_ratio_change_20": 1.13304204947433
  },
  {
    "date": "2026-04-30",
    "code": "6620",
    "name": "漢達",
    "market": "TPEX",
    "foreign_ratio": 0.0,
    "trust_ratio": 0.0,
    "dealer_ratio": 3.8249584811666573,
    "three_inst_ratio": 3.8249584811666573,
    "three_inst_ratio_change_20": 1.1224415838986346
  },
  {
    "date": "2026-05-04",
    "code": "6620",
    "name": "漢達",
    "market": "TPEX",
    "foreign_ratio": 0.0,
    "trust_ratio": 0.0,
    "dealer_ratio": 3.851431701151468,
    "three_inst_ratio": 3.851431701151468,
    "three_inst_ratio_change_20": 1.1089102387237322
  },
  {
    "date": "2026-05-05",
    "code": "6620",
    "name": "漢達",
    "market": "TPEX",
    "foreign_ratio": 0.0,
    "trust_ratio": 0.0,
    "dealer_ratio": 3.900260084679006,
    "three_inst_ratio": 3.900260084679006,
    "three_inst_ratio_change_20": 1.1436195715927049
  },
  {
    "date": "2026-05-06",
    "code": "6620",
    "name": "漢達",
    "market": "TPEX",
    "foreign_ratio": 0.0,
    "trust_ratio": 0.0,
    "dealer_ratio": 3.9190854855570936,
    "three_inst_ratio": 3.9190854855570936,
    "three_inst_ratio_change_20": 1.1147931764981345
  },
  {
    "date": "2026-05-07",
    "code": "6620",
    "name": "漢達",
    "market": "TPEX",
    "foreign_ratio": 0.0,
    "trust_ratio": 0.0,
    "dealer_ratio": 3.952029937093746,
    "three_inst_ratio": 3.952029937093746,
    "three_inst_ratio_change_20": 1.1106451170734029
  },
  {
    "date": "2026-05-08",
    "code": "6620",
    "name": "漢達",
    "market": "TPEX",
    "foreign_ratio": 0.0,
    "trust_ratio": 0.0,
    "dealer_ratio": 3.970264102725506,
    "three_inst_ratio": 3.970264102725506,
    "three_inst_ratio_change_20": 1.1112304693819564
  },
  {
    "date": "2026-05-11",
    "code": "6620",
    "name": "漢達",
    "market": "TPEX",
    "foreign_ratio": 0.0,
    "trust_ratio": 0.0,
    "dealer_ratio": 4.000855379152398,
    "three_inst_ratio": 4.000855379152398,
    "three_inst_ratio_change_20": 1.0529893854153736
  },
  {
    "date": "2026-05-12",
    "code": "6620",
    "name": "漢達",
    "market": "TPEX",
    "foreign_ratio": 0.0,
    "trust_ratio": 0.0,
    "dealer_ratio": 4.067332576003143,
    "three_inst_ratio": 4.067332576003143,
    "three_inst_ratio_change_20": 1.0759328427355421
  },
  {
    "date": "2026-05-13",
    "code": "6620",
    "name": "漢達",
    "market": "TPEX",
    "foreign_ratio": 0.0,
    "trust_ratio": 0.0,
    "dealer_ratio": 4.125573659969726,
    "three_inst_ratio": 4.125573659969726,
    "three_inst_ratio_change_20": 1.098288006278271
  },
  {
    "date": "2026-05-14",
    "code": "6620",
    "name": "漢達",
    "market": "TPEX",
    "foreign_ratio": 0.0,
    "trust_ratio": 0.0,
    "dealer_ratio": 4.129691716411808,
    "three_inst_ratio": 4.129691716411808,
    "three_inst_ratio_change_20": 1.020632639362384
  },
  {
    "date": "2026-05-15",
    "code": "6620",
    "name": "漢達",
    "market": "TPEX",
    "foreign_ratio": 0.0,
    "trust_ratio": 0.0,
    "dealer_ratio": 4.140869298183173,
    "three_inst_ratio": 4.140869298183173,
    "three_inst_ratio_change_20": 0.9382715105207518
  },
  {
    "date": "2026-05-18",
    "code": "6620",
    "name": "漢達",
    "market": "TPEX",
    "foreign_ratio": 0.0,
    "trust_ratio": 0.0,
    "dealer_ratio": 4.224995308357125,
    "three_inst_ratio": 4.224995308357125,
    "three_inst_ratio_change_20": 0.9870998940482902
  },
  {
    "date": "2026-05-19",
    "code": "6620",
    "name": "漢達",
    "market": "TPEX",
    "foreign_ratio": 0.0,
    "trust_ratio": 0.0,
    "dealer_ratio": 4.386788451322514,
    "three_inst_ratio": 4.386788451322514,
    "three_inst_ratio_change_20": 1.0077025304280247
  },
  {
    "date": "2026-05-20",
    "code": "6620",
    "name": "漢達",
    "market": "TPEX",
    "foreign_ratio": 0.0,
    "trust_ratio": 0.0,
    "dealer_ratio": 4.417968021526846,
    "three_inst_ratio": 4.417968021526846,
    "three_inst_ratio_change_20": 0.9771112540011333
  },
  {
    "date": "2026-05-21",
    "code": "6620",
    "name": "漢達",
    "market": "TPEX",
    "foreign_ratio": 0.0,
    "trust_ratio": 0.0,
    "dealer_ratio": 4.45267735439582,
    "three_inst_ratio": 4.45267735439582,
    "three_inst_ratio_change_20": 0.9012213567113441
  },
  {
    "date": "2026-05-22",
    "code": "6620",
    "name": "漢達",
    "market": "TPEX",
    "foreign_ratio": 0.0,
    "trust_ratio": 0.0,
    "dealer_ratio": 4.502125814572022,
    "three_inst_ratio": 4.502125814572022,
    "three_inst_ratio_change_20": 0.8877223827014413
  },
  {
    "date": "2026-05-25",
    "code": "6620",
    "name": "漢達",
    "market": "TPEX",
    "foreign_ratio": 0.0,
    "trust_ratio": 0.0,
    "dealer_ratio": 4.519186454557809,
    "three_inst_ratio": 4.519186454557809,
    "three_inst_ratio_change_20": 0.8335994756169609
  },
  {
    "date": "2026-05-26",
    "code": "6620",
    "name": "漢達",
    "market": "TPEX",
    "foreign_ratio": 0.0,
    "trust_ratio": 0.0,
    "dealer_ratio": 4.556413359304726,
    "three_inst_ratio": 4.556413359304726,
    "three_inst_ratio_change_20": 0.8237628781686599
  },
  {
    "date": "2026-05-27",
    "code": "6620",
    "name": "漢達",
    "market": "TPEX",
    "foreign_ratio": 0.0,
    "trust_ratio": 0.0,
    "dealer_ratio": 4.591254715943285,
    "three_inst_ratio": 4.591254715943285,
    "three_inst_ratio_change_20": 0.8103641450571204
  },
  {
    "date": "2026-05-28",
    "code": "6620",
    "name": "漢達",
    "market": "TPEX",
    "foreign_ratio": 0.0,
    "trust_ratio": 0.0,
    "dealer_ratio": 4.613610037303972,
    "three_inst_ratio": 4.613610037303972,
    "three_inst_ratio_change_20": 0.8221731238696366
  },
  {
    "date": "2026-05-29",
    "code": "6620",
    "name": "漢達",
    "market": "TPEX",
    "foreign_ratio": 0.0,
    "trust_ratio": 0.0,
    "dealer_ratio": 4.632759134943191,
    "three_inst_ratio": 4.632759134943191,
    "three_inst_ratio_change_20": 0.8078006537765337
  },
  {
    "date": "2026-06-01",
    "code": "6620",
    "name": "漢達",
    "market": "TPEX",
    "foreign_ratio": 0.0,
    "trust_ratio": 0.0,
    "dealer_ratio": 4.747756672916352,
    "three_inst_ratio": 4.747756672916352,
    "three_inst_ratio_change_20": 0.896324971764884
  },
  {
    "date": "2026-06-02",
    "code": "6620",
    "name": "漢達",
    "market": "TPEX",
    "foreign_ratio": 0.0,
    "trust_ratio": 0.0,
    "dealer_ratio": 4.766582206693772,
    "three_inst_ratio": 4.766582206693772,
    "three_inst_ratio_change_20": 0.8663221220147661
  },
  {
    "date": "2026-06-03",
    "code": "6620",
    "name": "漢達",
    "market": "TPEX",
    "foreign_ratio": 0.0,
    "trust_ratio": 0.0,
    "dealer_ratio": 4.860945194753088,
    "three_inst_ratio": 4.860945194753088,
    "three_inst_ratio_change_20": 0.9418597091959948
  },
  {
    "date": "2026-06-04",
    "code": "6620",
    "name": "漢達",
    "market": "TPEX",
    "foreign_ratio": 0.0,
    "trust_ratio": 0.0,
    "dealer_ratio": 4.889411755016269,
    "three_inst_ratio": 4.889411755016269,
    "three_inst_ratio_change_20": 0.9373818179225228
  },
  {
    "date": "2026-06-05",
    "code": "6620",
    "name": "漢達",
    "market": "TPEX",
    "foreign_ratio": 0.0,
    "trust_ratio": 0.0,
    "dealer_ratio": 4.944389961519432,
    "three_inst_ratio": 4.944389961519432,
    "three_inst_ratio_change_20": 0.9741258587939261
  },
  {
    "date": "2026-06-08",
    "code": "6620",
    "name": "漢達",
    "market": "TPEX",
    "foreign_ratio": 0.0,
    "trust_ratio": 0.0,
    "dealer_ratio": 5.032664065997615,
    "three_inst_ratio": 5.032664065997615,
    "three_inst_ratio_change_20": 1.031808686845217
  },
  {
    "date": "2026-06-09",
    "code": "6620",
    "name": "漢達",
    "market": "TPEX",
    "foreign_ratio": 0.0,
    "trust_ratio": 0.0,
    "dealer_ratio": 5.048630471832589,
    "three_inst_ratio": 5.048630471832589,
    "three_inst_ratio_change_20": 0.9812978958294458
  },
  {
    "date": "2026-06-10",
    "code": "6620",
    "name": "漢達",
    "market": "TPEX",
    "foreign_ratio": 0.0,
    "trust_ratio": 0.0,
    "dealer_ratio": 5.19175865195059,
    "three_inst_ratio": 5.19175865195059,
    "three_inst_ratio_change_20": 1.0661849919808635
  },
  {
    "date": "2026-06-11",
    "code": "6620",
    "name": "漢達",
    "market": "TPEX",
    "foreign_ratio": 0.0,
    "trust_ratio": 0.0,
    "dealer_ratio": 5.231174613297062,
    "three_inst_ratio": 5.231174613297062,
    "three_inst_ratio_change_20": 1.101482896885254
  },
  {
    "date": "2026-06-12",
    "code": "6620",
    "name": "漢達",
    "market": "TPEX",
    "foreign_ratio": 0.0,
    "trust_ratio": 0.0,
    "dealer_ratio": 5.2494118491439385,
    "three_inst_ratio": 5.2494118491439385,
    "three_inst_ratio_change_20": 1.1085425509607658
  },
  {
    "date": "2026-06-15",
    "code": "6620",
    "name": "漢達",
    "market": "TPEX",
    "foreign_ratio": 0.0,
    "trust_ratio": 0.0,
    "dealer_ratio": 5.3788373938637,
    "three_inst_ratio": 5.3788373938637,
    "three_inst_ratio_change_20": 1.1538420855065752
  },
  {
    "date": "2026-06-16",
    "code": "6620",
    "name": "漢達",
    "market": "TPEX",
    "foreign_ratio": 0.0,
    "trust_ratio": 0.0,
    "dealer_ratio": 5.43201952678491,
    "three_inst_ratio": 5.43201952678491,
    "three_inst_ratio_change_20": 1.0452310754623966
  },
  {
    "date": "2026-06-17",
    "code": "6620",
    "name": "漢達",
    "market": "TPEX",
    "foreign_ratio": 0.0,
    "trust_ratio": 0.0,
    "dealer_ratio": 5.587918478379168,
    "three_inst_ratio": 5.587918478379168,
    "three_inst_ratio_change_20": 1.1699504568523222
  },
  {
    "date": "2026-06-18",
    "code": "6620",
    "name": "漢達",
    "market": "TPEX",
    "foreign_ratio": 0.0,
    "trust_ratio": 0.0,
    "dealer_ratio": 5.845592971957602,
    "three_inst_ratio": 5.845592971957602,
    "three_inst_ratio_change_20": 1.3929156175617825
  },
  {
    "date": "2026-06-22",
    "code": "6620",
    "name": "漢達",
    "market": "TPEX",
    "foreign_ratio": 0.0,
    "trust_ratio": 0.0,
    "dealer_ratio": 5.845592971957602,
    "three_inst_ratio": 5.845592971957602,
    "three_inst_ratio_change_20": 1.3434671573855805
  },
  {
    "date": "2026-06-23",
    "code": "6620",
    "name": "漢達",
    "market": "TPEX",
    "foreign_ratio": 0.0,
    "trust_ratio": 0.0,
    "dealer_ratio": 6.173863217201361,
    "three_inst_ratio": 6.173863217201361,
    "three_inst_ratio_change_20": 1.6546767626435521
  },
  {
    "date": "2026-06-24",
    "code": "6620",
    "name": "漢達",
    "market": "TPEX",
    "foreign_ratio": 0.0,
    "trust_ratio": 0.0,
    "dealer_ratio": 6.572818047097956,
    "three_inst_ratio": 6.572818047097956,
    "three_inst_ratio_change_20": 2.01640468779323
  },
  {
    "date": "2026-06-25",
    "code": "6620",
    "name": "漢達",
    "market": "TPEX",
    "foreign_ratio": 0.0,
    "trust_ratio": 0.0,
    "dealer_ratio": 6.861731160788295,
    "three_inst_ratio": 6.861731160788295,
    "three_inst_ratio_change_20": 2.27047644484501
  },
  {
    "date": "2026-06-26",
    "code": "6620",
    "name": "漢達",
    "market": "TPEX",
    "foreign_ratio": 0.0,
    "trust_ratio": 0.0,
    "dealer_ratio": 6.912324782815111,
    "three_inst_ratio": 6.912324782815111,
    "three_inst_ratio_change_20": 2.2987147455111394
  }
]