[
  {
    "date": "2025-09-11",
    "code": "8155",
    "name": "博智",
    "market": "TPEX",
    "foreign_ratio": 0.0,
    "trust_ratio": 0.0,
    "dealer_ratio": 0.0,
    "three_inst_ratio": 0.0,
    "three_inst_ratio_change_20": 0.0
  },
  {
    "date": "2025-09-12",
    "code": "8155",
    "name": "博智",
    "market": "TPEX",
    "foreign_ratio": 0.0,
    "trust_ratio": 0.0,
    "dealer_ratio": 0.0,
    "three_inst_ratio": 0.0,
    "three_inst_ratio_change_20": 0.0
  },
  {
    "date": "2025-09-15",
    "code": "8155",
    "name": "博智",
    "market": "TPEX",
    "foreign_ratio": 0.0,
    "trust_ratio": 0.0,
    "dealer_ratio": 0.0,
    "three_inst_ratio": 0.0,
    "three_inst_ratio_change_20": 0.0
  },
  {
    "date": "2025-09-16",
    "code": "8155",
    "name": "博智",
    "market": "TPEX",
    "foreign_ratio": 0.0,
    "trust_ratio": 0.0,
    "dealer_ratio": 0.0,
    "three_inst_ratio": 0.0,
    "three_inst_ratio_change_20": 0.0
  },
  {
    "date": "2025-09-17",
    "code": "8155",
    "name": "博智",
    "market": "TPEX",
    "foreign_ratio": 0.0,
    "trust_ratio": 0.0,
    "dealer_ratio": 0.0,
    "three_inst_ratio": 0.0,
    "three_inst_ratio_change_20": 0.0
  },
  {
    "date": "2025-09-18",
    "code": "8155",
    "name": "博智",
    "market": "TPEX",
    "foreign_ratio": 0.0,
    "trust_ratio": 0.0,
    "dealer_ratio": 0.0,
    "three_inst_ratio": 0.0,
    "three_inst_ratio_change_20": 0.0
  },
  {
    "date": "2025-09-19",
    "code": "8155",
    "name": "博智",
    "market": "TPEX",
    "foreign_ratio": 0.0,
    "trust_ratio": 0.0,
    "dealer_ratio": 0.0,
    "three_inst_ratio": 0.0,
    "three_inst_ratio_change_20": 0.0
  },
  {
    "date": "2025-09-22",
    "code": "8155",
    "name": "博智",
    "market": "TPEX",
    "foreign_ratio": 0.0,
    "trust_ratio": 0.0,
    "dealer_ratio": 0.0,
    "three_inst_ratio": 0.0,
    "three_inst_ratio_change_20": 0.0
  },
  {
    "date": "2025-09-23",
    "code": "8155",
    "name": "博智",
    "market": "TPEX",
    "foreign_ratio": 0.0,
    "trust_ratio": 0.0,
    "dealer_ratio": 0.0,
    "three_inst_ratio": 0.0,
    "three_inst_ratio_change_20": 0.0
  },
  {
    "date": "2025-09-24",
    "code": "8155",
    "name": "博智",
    "market": "TPEX",
    "foreign_ratio": 0.0,
    "trust_ratio": 0.0,
    "dealer_ratio": 0.0,
    "three_inst_ratio": 0.0,
    "three_inst_ratio_change_20": 0.0
  },
  {
    "date": "2025-09-25",
    "code": "8155",
    "name": "博智",
    "market": "TPEX",
    "foreign_ratio": 0.0,
    "trust_ratio": 0.0,
    "dealer_ratio": 0.0,
    "three_inst_ratio": 0.0,
    "three_inst_ratio_change_20": 0.0
  },
  {
    "date": "2025-09-26",
    "code": "8155",
    "name": "博智",
    "market": "TPEX",
    "foreign_ratio": 0.0,
    "trust_ratio": 0.0,
    "dealer_ratio": 0.0,
    "three_inst_ratio": 0.0,
    "three_inst_ratio_change_20": 0.0
  },
  {
    "date": "2025-09-30",
    "code": "8155",
    "name": "博智",
    "market": "TPEX",
    "foreign_ratio": 0.0,
    "trust_ratio": 0.0,
    "dealer_ratio": 0.0,
    "three_inst_ratio": 0.0,
    "three_inst_ratio_change_20": 0.0
  },
  {
    "date": "2025-10-01",
    "code": "8155",
    "name": "博智",
    "market": "TPEX",
    "foreign_ratio": 0.0,
    "trust_ratio": 0.0,
    "dealer_ratio": 0.0,
    "three_inst_ratio": 0.0,
    "three_inst_ratio_change_20": 0.0
  },
  {
    "date": "2025-10-02",
    "code": "8155",
    "name": "博智",
    "market": "TPEX",
    "foreign_ratio": 0.0,
    "trust_ratio": 0.0,
    "dealer_ratio": 0.0,
    "three_inst_ratio": 0.0,
    "three_inst_ratio_change_20": 0.0
  },
  {
    "date": "2025-10-03",
    "code": "8155",
    "name": "博智",
    "market": "TPEX",
    "foreign_ratio": 0.0,
    "trust_ratio": 0.0,
    "dealer_ratio": 0.0,
    "three_inst_ratio": 0.0,
    "three_inst_ratio_change_20": 0.0
  },
  {
    "date": "2025-10-07",
    "code": "8155",
    "name": "博智",
    "market": "TPEX",
    "foreign_ratio": 0.0,
    "trust_ratio": 0.0,
    "dealer_ratio": 0.0,
    "three_inst_ratio": 0.0,
    "three_inst_ratio_change_20": 0.0
  },
  {
    "date": "2025-10-08",
    "code": "8155",
    "name": "博智",
    "market": "TPEX",
    "foreign_ratio": 0.0,
    "trust_ratio": 0.0,
    "dealer_ratio": 0.0,
    "three_inst_ratio": 0.0,
    "three_inst_ratio_change_20": 0.0
  },
  {
    "date": "2025-10-09",
    "code": "8155",
    "name": "博智",
    "market": "TPEX",
    "foreign_ratio": 0.0,
    "trust_ratio": 0.023311047374324316,
    "dealer_ratio": 0.0,
    "three_inst_ratio": 0.023311047374324316,
    "three_inst_ratio_change_20": 0.0
  },
  {
    "date": "2025-10-13",
    "code": "8155",
    "name": "博智",
    "market": "TPEX",
    "foreign_ratio": 0.0,
    "trust_ratio": 0.023311047374324316,
    "dealer_ratio": 0.0,
    "three_inst_ratio": 0.023311047374324316,
    "three_inst_ratio_change_20": 0.0
  },
  {
    "date": "2025-10-14",
    "code": "8155",
    "name": "博智",
    "market": "TPEX",
    "foreign_ratio": 0.0,
    "trust_ratio": 0.18828153648492715,
    "dealer_ratio": 0.0,
    "three_inst_ratio": 0.18828153648492715,
    "three_inst_ratio_change_20": 0.18828153648492715
  },
  {
    "date": "2025-10-15",
    "code": "8155",
    "name": "博智",
    "market": "TPEX",
    "foreign_ratio": 0.0,
    "trust_ratio": 0.2384899462142411,
    "dealer_ratio": 0.0,
    "three_inst_ratio": 0.2384899462142411,
    "three_inst_ratio_change_20": 0.2384899462142411
  },
  {
    "date": "2025-10-16",
    "code": "8155",
    "name": "博智",
    "market": "TPEX",
    "foreign_ratio": 0.0,
    "trust_ratio": 0.2922846709242202,
    "dealer_ratio": 0.0,
    "three_inst_ratio": 0.2922846709242202,
    "three_inst_ratio_change_20": 0.2922846709242202
  },
  {
    "date": "2025-10-17",
    "code": "8155",
    "name": "博智",
    "market": "TPEX",
    "foreign_ratio": 0.0,
    "trust_ratio": 0.3855288604215175,
    "dealer_ratio": 0.0,
    "three_inst_ratio": 0.3855288604215175,
    "three_inst_ratio_change_20": 0.3855288604215175
  },
  {
    "date": "2025-10-20",
    "code": "8155",
    "name": "博智",
    "market": "TPEX",
    "foreign_ratio": 0.0,
    "trust_ratio": 0.5343609321191266,
    "dealer_ratio": 0.0,
    "three_inst_ratio": 0.5343609321191266,
    "three_inst_ratio_change_20": 0.5343609321191266
  },
  {
    "date": "2025-10-21",
    "code": "8155",
    "name": "博智",
    "market": "TPEX",
    "foreign_ratio": 0.0,
    "trust_ratio": 0.5343609321191266,
    "dealer_ratio": 0.0,
    "three_inst_ratio": 0.5343609321191266,
    "three_inst_ratio_change_20": 0.5343609321191266
  },
  {
    "date": "2025-10-22",
    "code": "8155",
    "name": "博智",
    "market": "TPEX",
    "foreign_ratio": 0.0,
    "trust_ratio": 0.5343609321191266,
    "dealer_ratio": 0.0,
    "three_inst_ratio": 0.5343609321191266,
    "three_inst_ratio_change_20": 0.5343609321191266
  },
  {
    "date": "2025-10-23",
    "code": "8155",
    "name": "博智",
    "market": "TPEX",
    "foreign_ratio": 0.0,
    "trust_ratio": 0.552292507022453,
    "dealer_ratio": 0.0,
    "three_inst_ratio": 0.552292507022453,
    "three_inst_ratio_change_20": 0.552292507022453
  },
  {
    "date": "2025-10-27",
    "code": "8155",
    "name": "博智",
    "market": "TPEX",
    "foreign_ratio": 0.0,
    "trust_ratio": 0.5612582944741162,
    "dealer_ratio": 0.0,
    "three_inst_ratio": 0.5612582944741162,
    "three_inst_ratio_change_20": 0.5612582944741162
  },
  {
    "date": "2025-10-28",
    "code": "8155",
    "name": "博智",
    "market": "TPEX",
    "foreign_ratio": 0.0,
    "trust_ratio": 0.5612582944741162,
    "dealer_ratio": 0.0,
    "three_inst_ratio": 0.5612582944741162,
    "three_inst_ratio_change_20": 0.5612582944741162
  },
  {
    "date": "2025-10-29",
    "code": "8155",
    "name": "博智",
    "market": "TPEX",
    "foreign_ratio": 0.0,
    "trust_ratio": 0.6240188066357586,
    "dealer_ratio": 0.0,
    "three_inst_ratio": 0.6240188066357586,
    "three_inst_ratio_change_20": 0.6240188066357586
  },
  {
    "date": "2025-10-30",
    "code": "8155",
    "name": "博智",
    "market": "TPEX",
    "foreign_ratio": 0.0,
    "trust_ratio": 0.6240188066357586,
    "dealer_ratio": 0.0,
    "three_inst_ratio": 0.6240188066357586,
    "three_inst_ratio_change_20": 0.6240188066357586
  },
  {
    "date": "2025-10-31",
    "code": "8155",
    "name": "博智",
    "market": "TPEX",
    "foreign_ratio": 0.0,
    "trust_ratio": 0.6240188066357586,
    "dealer_ratio": 0.0,
    "three_inst_ratio": 0.6240188066357586,
    "three_inst_ratio_change_20": 0.6240188066357586
  },
  {
    "date": "2025-11-03",
    "code": "8155",
    "name": "博智",
    "market": "TPEX",
    "foreign_ratio": 0.0,
    "trust_ratio": 0.6240188066357586,
    "dealer_ratio": 0.0,
    "three_inst_ratio": 0.6240188066357586,
    "three_inst_ratio_change_20": 0.6240188066357586
  },
  {
    "date": "2025-11-04",
    "code": "8155",
    "name": "博智",
    "market": "TPEX",
    "foreign_ratio": 0.0,
    "trust_ratio": 0.6240188066357586,
    "dealer_ratio": 0.0,
    "three_inst_ratio": 0.6240188066357586,
    "three_inst_ratio_change_20": 0.6240188066357586
  },
  {
    "date": "2025-11-05",
    "code": "8155",
    "name": "博智",
    "market": "TPEX",
    "foreign_ratio": 0.0,
    "trust_ratio": 0.6240188066357586,
    "dealer_ratio": 0.0,
    "three_inst_ratio": 0.6240188066357586,
    "three_inst_ratio_change_20": 0.6240188066357586
  },
  {
    "date": "2025-11-06",
    "code": "8155",
    "name": "博智",
    "market": "TPEX",
    "foreign_ratio": 0.0,
    "trust_ratio": 0.6240188066357586,
    "dealer_ratio": 0.0,
    "three_inst_ratio": 0.6240188066357586,
    "three_inst_ratio_change_20": 0.6240188066357586
  },
  {
    "date": "2025-11-07",
    "code": "8155",
    "name": "博智",
    "market": "TPEX",
    "foreign_ratio": 0.0,
    "trust_ratio": 0.6240188066357586,
    "dealer_ratio": 0.0,
    "three_inst_ratio": 0.6240188066357586,
    "three_inst_ratio_change_20": 0.6240188066357586
  },
  {
    "date": "2025-11-10",
    "code": "8155",
    "name": "博智",
    "market": "TPEX",
    "foreign_ratio": 0.0,
    "trust_ratio": 0.6240188066357586,
    "dealer_ratio": 0.0,
    "three_inst_ratio": 0.6240188066357586,
    "three_inst_ratio_change_20": 0.6007077592614343
  },
  {
    "date": "2025-11-11",
    "code": "8155",
    "name": "博智",
    "market": "TPEX",
    "foreign_ratio": 0.0,
    "trust_ratio": 0.6240188066357586,
    "dealer_ratio": 0.0,
    "three_inst_ratio": 0.6240188066357586,
    "three_inst_ratio_change_20": 0.6007077592614343
  },
  {
    "date": "2025-11-12",
    "code": "8155",
    "name": "博智",
    "market": "TPEX",
    "foreign_ratio": 0.0,
    "trust_ratio": 0.681399846326403,
    "dealer_ratio": 0.0,
    "three_inst_ratio": 0.681399846326403,
    "three_inst_ratio_change_20": 0.49311830984147587
  },
  {
    "date": "2025-11-13",
    "code": "8155",
    "name": "博智",
    "market": "TPEX",
    "foreign_ratio": 0.0,
    "trust_ratio": 0.681399846326403,
    "dealer_ratio": 0.0,
    "three_inst_ratio": 0.681399846326403,
    "three_inst_ratio_change_20": 0.4429099001121619
  },
  {
    "date": "2025-11-14",
    "code": "8155",
    "name": "博智",
    "market": "TPEX",
    "foreign_ratio": 0.0,
    "trust_ratio": 0.681399846326403,
    "dealer_ratio": 0.0,
    "three_inst_ratio": 0.681399846326403,
    "three_inst_ratio_change_20": 0.3891151754021828
  },
  {
    "date": "2025-11-17",
    "code": "8155",
    "name": "博智",
    "market": "TPEX",
    "foreign_ratio": 0.0,
    "trust_ratio": 0.681399846326403,
    "dealer_ratio": 0.0,
    "three_inst_ratio": 0.681399846326403,
    "three_inst_ratio_change_20": 0.29587098590488553
  },
  {
    "date": "2025-11-18",
    "code": "8155",
    "name": "博智",
    "market": "TPEX",
    "foreign_ratio": 0.0,
    "trust_ratio": 0.681399846326403,
    "dealer_ratio": 0.0,
    "three_inst_ratio": 0.681399846326403,
    "three_inst_ratio_change_20": 0.14703891420727644
  },
  {
    "date": "2025-11-19",
    "code": "8155",
    "name": "博智",
    "market": "TPEX",
    "foreign_ratio": 0.0,
    "trust_ratio": 0.681399846326403,
    "dealer_ratio": 0.0,
    "three_inst_ratio": 0.681399846326403,
    "three_inst_ratio_change_20": 0.14703891420727644
  },
  {
    "date": "2025-11-20",
    "code": "8155",
    "name": "博智",
    "market": "TPEX",
    "foreign_ratio": 0.0,
    "trust_ratio": 0.681399846326403,
    "dealer_ratio": 0.0,
    "three_inst_ratio": 0.681399846326403,
    "three_inst_ratio_change_20": 0.14703891420727644
  },
  {
    "date": "2025-11-21",
    "code": "8155",
    "name": "博智",
    "market": "TPEX",
    "foreign_ratio": 0.0,
    "trust_ratio": 0.681399846326403,
    "dealer_ratio": 0.0,
    "three_inst_ratio": 0.681399846326403,
    "three_inst_ratio_change_20": 0.12910733930395002
  },
  {
    "date": "2025-11-24",
    "code": "8155",
    "name": "博智",
    "market": "TPEX",
    "foreign_ratio": 0.0,
    "trust_ratio": 0.681399846326403,
    "dealer_ratio": 0.0,
    "three_inst_ratio": 0.681399846326403,
    "three_inst_ratio_change_20": 0.12014155185228681
  },
  {
    "date": "2025-11-25",
    "code": "8155",
    "name": "博智",
    "market": "TPEX",
    "foreign_ratio": 0.0,
    "trust_ratio": 0.681399846326403,
    "dealer_ratio": 0.0,
    "three_inst_ratio": 0.681399846326403,
    "three_inst_ratio_change_20": 0.12014155185228681
  },
  {
    "date": "2025-11-26",
    "code": "8155",
    "name": "博智",
    "market": "TPEX",
    "foreign_ratio": 0.0,
    "trust_ratio": 0.681399846326403,
    "dealer_ratio": 0.0,
    "three_inst_ratio": 0.681399846326403,
    "three_inst_ratio_change_20": 0.05738103969064445
  },
  {
    "date": "2025-11-27",
    "code": "8155",
    "name": "博智",
    "market": "TPEX",
    "foreign_ratio": 0.0,
    "trust_ratio": 0.681399846326403,
    "dealer_ratio": 0.0,
    "three_inst_ratio": 0.681399846326403,
    "three_inst_ratio_change_20": 0.05738103969064445
  },
  {
    "date": "2025-11-28",
    "code": "8155",
    "name": "博智",
    "market": "TPEX",
    "foreign_ratio": 0.0,
    "trust_ratio": 0.7441603584880454,
    "dealer_ratio": 0.0,
    "three_inst_ratio": 0.7441603584880454,
    "three_inst_ratio_change_20": 0.12014155185228681
  },
  {
    "date": "2025-12-01",
    "code": "8155",
    "name": "博智",
    "market": "TPEX",
    "foreign_ratio": 0.0,
    "trust_ratio": 0.7943687682173594,
    "dealer_ratio": 0.0,
    "three_inst_ratio": 0.7943687682173594,
    "three_inst_ratio_change_20": 0.17034996158160076
  },
  {
    "date": "2025-12-02",
    "code": "8155",
    "name": "博智",
    "market": "TPEX",
    "foreign_ratio": 0.0,
    "trust_ratio": 0.7943687682173594,
    "dealer_ratio": 0.0,
    "three_inst_ratio": 0.7943687682173594,
    "three_inst_ratio_change_20": 0.17034996158160076
  },
  {
    "date": "2025-12-03",
    "code": "8155",
    "name": "博智",
    "market": "TPEX",
    "foreign_ratio": 0.0,
    "trust_ratio": 0.8391977054756753,
    "dealer_ratio": 0.0,
    "three_inst_ratio": 0.8391977054756753,
    "three_inst_ratio_change_20": 0.2151788988399167
  },
  {
    "date": "2025-12-04",
    "code": "8155",
    "name": "博智",
    "market": "TPEX",
    "foreign_ratio": 0.0,
    "trust_ratio": 0.8391977054756753,
    "dealer_ratio": 0.0,
    "three_inst_ratio": 0.8391977054756753,
    "three_inst_ratio_change_20": 0.2151788988399167
  },
  {
    "date": "2025-12-05",
    "code": "8155",
    "name": "博智",
    "market": "TPEX",
    "foreign_ratio": 0.0,
    "trust_ratio": 0.8481634929273386,
    "dealer_ratio": 0.0,
    "three_inst_ratio": 0.8481634929273386,
    "three_inst_ratio_change_20": 0.22414468629158002
  },
  {
    "date": "2025-12-08",
    "code": "8155",
    "name": "博智",
    "market": "TPEX",
    "foreign_ratio": 0.0,
    "trust_ratio": 0.8517498079080038,
    "dealer_ratio": 0.0,
    "three_inst_ratio": 0.8517498079080038,
    "three_inst_ratio_change_20": 0.22773100127224521
  },
  {
    "date": "2025-12-09",
    "code": "8155",
    "name": "博智",
    "market": "TPEX",
    "foreign_ratio": 0.0,
    "trust_ratio": 0.8553361228886691,
    "dealer_ratio": 0.0,
    "three_inst_ratio": 0.8553361228886691,
    "three_inst_ratio_change_20": 0.23131731625291052
  },
  {
    "date": "2025-12-10",
    "code": "8155",
    "name": "博智",
    "market": "TPEX",
    "foreign_ratio": 0.0,
    "trust_ratio": 0.8696813828113303,
    "dealer_ratio": 0.0,
    "three_inst_ratio": 0.8696813828113303,
    "three_inst_ratio_change_20": 0.1882815364849273
  },
  {
    "date": "2025-12-11",
    "code": "8155",
    "name": "博智",
    "market": "TPEX",
    "foreign_ratio": 0.0,
    "trust_ratio": 0.8876129577146566,
    "dealer_ratio": 0.0,
    "three_inst_ratio": 0.8876129577146566,
    "three_inst_ratio_change_20": 0.2062131113882536
  },
  {
    "date": "2025-12-12",
    "code": "8155",
    "name": "博智",
    "market": "TPEX",
    "foreign_ratio": 0.0,
    "trust_ratio": 0.8876129577146566,
    "dealer_ratio": 0.0,
    "three_inst_ratio": 0.8876129577146566,
    "three_inst_ratio_change_20": 0.2062131113882536
  },
  {
    "date": "2025-12-15",
    "code": "8155",
    "name": "博智",
    "market": "TPEX",
    "foreign_ratio": 0.0,
    "trust_ratio": 0.8876129577146566,
    "dealer_ratio": 0.4070467503055092,
    "three_inst_ratio": 1.2946597080201658,
    "three_inst_ratio_change_20": 0.6132598616937628
  },
  {
    "date": "2025-12-16",
    "code": "8155",
    "name": "博智",
    "market": "TPEX",
    "foreign_ratio": 0.0,
    "trust_ratio": 0.8876129577146566,
    "dealer_ratio": 1.2212801172007735,
    "three_inst_ratio": 2.10889307491543,
    "three_inst_ratio_change_20": 1.427493228589027
  },
  {
    "date": "2025-12-17",
    "code": "8155",
    "name": "博智",
    "market": "TPEX",
    "foreign_ratio": 0.0,
    "trust_ratio": 0.8876129577146566,
    "dealer_ratio": 1.4956332132216674,
    "three_inst_ratio": 2.383246170936324,
    "three_inst_ratio_change_20": 1.701846324609921
  },
  {
    "date": "2025-12-18",
    "code": "8155",
    "name": "博智",
    "market": "TPEX",
    "foreign_ratio": 0.0,
    "trust_ratio": 0.8876129577146566,
    "dealer_ratio": 1.7215710570035803,
    "three_inst_ratio": 2.609184014718237,
    "three_inst_ratio_change_20": 1.9277841683918338
  },
  {
    "date": "2025-12-19",
    "code": "8155",
    "name": "博智",
    "market": "TPEX",
    "foreign_ratio": 0.0,
    "trust_ratio": 0.8876129577146566,
    "dealer_ratio": 1.9170252234498377,
    "three_inst_ratio": 2.8046381811644943,
    "three_inst_ratio_change_20": 2.123238334838091
  },
  {
    "date": "2025-12-22",
    "code": "8155",
    "name": "博智",
    "market": "TPEX",
    "foreign_ratio": 0.0,
    "trust_ratio": 0.8876129577146566,
    "dealer_ratio": 2.159101484644744,
    "three_inst_ratio": 3.046714442359401,
    "three_inst_ratio_change_20": 2.3653145960329978
  },
  {
    "date": "2025-12-23",
    "code": "8155",
    "name": "博智",
    "market": "TPEX",
    "foreign_ratio": 0.0,
    "trust_ratio": 0.8876129577146566,
    "dealer_ratio": 4.707178278407425,
    "three_inst_ratio": 5.594791236122082,
    "three_inst_ratio_change_20": 4.913391389795679
  },
  {
    "date": "2025-12-24",
    "code": "8155",
    "name": "博智",
    "market": "TPEX",
    "foreign_ratio": 0.0,
    "trust_ratio": 0.8876129577146566,
    "dealer_ratio": 5.6611380632643895,
    "three_inst_ratio": 6.548751020979046,
    "three_inst_ratio_change_20": 5.867351174652644
  },
  {
    "date": "2025-12-26",
    "code": "8155",
    "name": "博智",
    "market": "TPEX",
    "foreign_ratio": 0.0,
    "trust_ratio": 0.8876129577146566,
    "dealer_ratio": 5.861971702181645,
    "three_inst_ratio": 6.749584659896302,
    "three_inst_ratio_change_20": 6.068184813569898
  },
  {
    "date": "2025-12-29",
    "code": "8155",
    "name": "博智",
    "market": "TPEX",
    "foreign_ratio": 0.0,
    "trust_ratio": 0.8876129577146566,
    "dealer_ratio": 5.95342273418861,
    "three_inst_ratio": 6.841035691903267,
    "three_inst_ratio_change_20": 6.0968753334152215
  },
  {
    "date": "2025-12-30",
    "code": "8155",
    "name": "博智",
    "market": "TPEX",
    "foreign_ratio": 0.0,
    "trust_ratio": 0.8876129577146566,
    "dealer_ratio": 6.125565853260543,
    "three_inst_ratio": 7.0131788109752,
    "three_inst_ratio_change_20": 6.21881004275784
  },
  {
    "date": "2025-12-31",
    "code": "8155",
    "name": "博智",
    "market": "TPEX",
    "foreign_ratio": 0.0,
    "trust_ratio": 0.8876129577146566,
    "dealer_ratio": 6.236741617661166,
    "three_inst_ratio": 7.124354575375823,
    "three_inst_ratio_change_20": 6.329985807158463
  },
  {
    "date": "2026-01-02",
    "code": "8155",
    "name": "博智",
    "market": "TPEX",
    "foreign_ratio": 0.0,
    "trust_ratio": 0.8876129577146566,
    "dealer_ratio": 6.371228429436114,
    "three_inst_ratio": 7.25884138715077,
    "three_inst_ratio_change_20": 6.419643681675095
  },
  {
    "date": "2026-01-05",
    "code": "8155",
    "name": "博智",
    "market": "TPEX",
    "foreign_ratio": 0.0,
    "trust_ratio": 0.8876129577146566,
    "dealer_ratio": 6.72089414005098,
    "three_inst_ratio": 7.608507097765637,
    "three_inst_ratio_change_20": 6.769309392289961
  },
  {
    "date": "2026-01-06",
    "code": "8155",
    "name": "博智",
    "market": "TPEX",
    "foreign_ratio": 0.0,
    "trust_ratio": 0.8876129577146566,
    "dealer_ratio": 6.891244101632581,
    "three_inst_ratio": 7.778857059347238,
    "three_inst_ratio_change_20": 6.930693566419899
  },
  {
    "date": "2026-01-07",
    "code": "8155",
    "name": "博智",
    "market": "TPEX",
    "foreign_ratio": 0.0,
    "trust_ratio": 0.8876129577146566,
    "dealer_ratio": 7.178149300085803,
    "three_inst_ratio": 8.06576225780046,
    "three_inst_ratio_change_20": 7.214012449892456
  },
  {
    "date": "2026-01-08",
    "code": "8155",
    "name": "博智",
    "market": "TPEX",
    "foreign_ratio": 0.0,
    "trust_ratio": 0.8876129577146566,
    "dealer_ratio": 7.9079643986511865,
    "three_inst_ratio": 8.795577356365843,
    "three_inst_ratio_change_20": 7.940241233477174
  },
  {
    "date": "2026-01-09",
    "code": "8155",
    "name": "博智",
    "market": "TPEX",
    "foreign_ratio": 0.0,
    "trust_ratio": 0.8876129577146566,
    "dealer_ratio": 10.21934440368996,
    "three_inst_ratio": 11.106957361404616,
    "three_inst_ratio_change_20": 10.237275978593285
  },
  {
    "date": "2026-01-12",
    "code": "8155",
    "name": "博智",
    "market": "TPEX",
    "foreign_ratio": 0.0,
    "trust_ratio": 0.8876129577146566,
    "dealer_ratio": 14.341813473964699,
    "three_inst_ratio": 15.229426431679356,
    "three_inst_ratio_change_20": 14.341813473964699
  },
  {
    "date": "2026-01-13",
    "code": "8155",
    "name": "博智",
    "market": "TPEX",
    "foreign_ratio": 0.0,
    "trust_ratio": 0.8876129577146566,
    "dealer_ratio": 15.962827845225405,
    "three_inst_ratio": 16.85044080294006,
    "three_inst_ratio_change_20": 15.962827845225403
  },
  {
    "date": "2026-01-14",
    "code": "8155",
    "name": "博智",
    "market": "TPEX",
    "foreign_ratio": 0.0,
    "trust_ratio": 0.8876129577146566,
    "dealer_ratio": 16.360908808079248,
    "three_inst_ratio": 17.248521765793903,
    "three_inst_ratio_change_20": 15.953862057773737
  },
  {
    "date": "2026-01-15",
    "code": "8155",
    "name": "博智",
    "market": "TPEX",
    "foreign_ratio": 0.0,
    "trust_ratio": 0.8876129577146566,
    "dealer_ratio": 16.771541873365425,
    "three_inst_ratio": 17.65915483108008,
    "three_inst_ratio_change_20": 15.55026175616465
  },
  {
    "date": "2026-01-16",
    "code": "8155",
    "name": "博智",
    "market": "TPEX",
    "foreign_ratio": 0.0,
    "trust_ratio": 0.8876129577146566,
    "dealer_ratio": 17.207279143516256,
    "three_inst_ratio": 18.09489210123091,
    "three_inst_ratio_change_20": 15.711645930294587
  },
  {
    "date": "2026-01-19",
    "code": "8155",
    "name": "博智",
    "market": "TPEX",
    "foreign_ratio": 0.0,
    "trust_ratio": 0.8876129577146566,
    "dealer_ratio": 17.375835947607523,
    "three_inst_ratio": 18.26344890532218,
    "three_inst_ratio_change_20": 15.654264890603942
  },
  {
    "date": "2026-01-20",
    "code": "8155",
    "name": "博智",
    "market": "TPEX",
    "foreign_ratio": 0.0,
    "trust_ratio": 0.8876129577146566,
    "dealer_ratio": 17.94964634451397,
    "three_inst_ratio": 18.837259302228624,
    "three_inst_ratio_change_20": 16.03262112106413
  },
  {
    "date": "2026-01-21",
    "code": "8155",
    "name": "博智",
    "market": "TPEX",
    "foreign_ratio": 0.0,
    "trust_ratio": 0.8876129577146566,
    "dealer_ratio": 18.60235567099505,
    "three_inst_ratio": 19.489968628709704,
    "three_inst_ratio_change_20": 16.443254186350302
  },
  {
    "date": "2026-01-22",
    "code": "8155",
    "name": "博智",
    "market": "TPEX",
    "foreign_ratio": 0.0,
    "trust_ratio": 0.8876129577146566,
    "dealer_ratio": 19.572453873265008,
    "three_inst_ratio": 20.460066830979663,
    "three_inst_ratio_change_20": 14.865275594857582
  },
  {
    "date": "2026-01-23",
    "code": "8155",
    "name": "博智",
    "market": "TPEX",
    "foreign_ratio": 0.0,
    "trust_ratio": 0.8876129577146566,
    "dealer_ratio": 22.480058743839386,
    "three_inst_ratio": 23.36767170155404,
    "three_inst_ratio_change_20": 16.818920680574994
  },
  {
    "date": "2026-01-26",
    "code": "8155",
    "name": "博智",
    "market": "TPEX",
    "foreign_ratio": 0.0,
    "trust_ratio": 0.8876129577146566,
    "dealer_ratio": 23.59898901780695,
    "three_inst_ratio": 24.486601975521605,
    "three_inst_ratio_change_20": 17.7370173156253
  },
  {
    "date": "2026-01-27",
    "code": "8155",
    "name": "博智",
    "market": "TPEX",
    "foreign_ratio": 0.0,
    "trust_ratio": 0.8876129577146566,
    "dealer_ratio": 29.021708861156714,
    "three_inst_ratio": 29.90932181887137,
    "three_inst_ratio_change_20": 23.068286126968104
  },
  {
    "date": "2026-01-28",
    "code": "8155",
    "name": "博智",
    "market": "TPEX",
    "foreign_ratio": 0.0,
    "trust_ratio": 0.8876129577146566,
    "dealer_ratio": 31.245224149169186,
    "three_inst_ratio": 32.13283710688384,
    "three_inst_ratio_change_20": 25.119658295908643
  },
  {
    "date": "2026-01-29",
    "code": "8155",
    "name": "博智",
    "market": "TPEX",
    "foreign_ratio": 0.0,
    "trust_ratio": 0.8876129577146566,
    "dealer_ratio": 34.30623902251399,
    "three_inst_ratio": 35.19385198022865,
    "three_inst_ratio_change_20": 28.06949740485283
  },
  {
    "date": "2026-01-30",
    "code": "8155",
    "name": "博智",
    "market": "TPEX",
    "foreign_ratio": 0.0,
    "trust_ratio": 0.8876129577146566,
    "dealer_ratio": 37.73834245901066,
    "three_inst_ratio": 38.62595541672532,
    "three_inst_ratio_change_20": 31.367114029574548
  },
  {
    "date": "2026-02-02",
    "code": "8155",
    "name": "博智",
    "market": "TPEX",
    "foreign_ratio": 0.0,
    "trust_ratio": 0.8876129577146566,
    "dealer_ratio": 40.010272999262114,
    "three_inst_ratio": 40.89788595697677,
    "three_inst_ratio_change_20": 33.28937885921113
  },
  {
    "date": "2026-02-03",
    "code": "8155",
    "name": "博智",
    "market": "TPEX",
    "foreign_ratio": 0.0,
    "trust_ratio": 0.8876129577146566,
    "dealer_ratio": 41.36052058948259,
    "three_inst_ratio": 42.24813354719725,
    "three_inst_ratio_change_20": 34.46927648785001
  },
  {
    "date": "2026-02-04",
    "code": "8155",
    "name": "博智",
    "market": "TPEX",
    "foreign_ratio": 0.0,
    "trust_ratio": 0.8876129577146566,
    "dealer_ratio": 42.06164516820265,
    "three_inst_ratio": 42.94925812591731,
    "three_inst_ratio_change_20": 34.88349586811685
  },
  {
    "date": "2026-02-05",
    "code": "8155",
    "name": "博智",
    "market": "TPEX",
    "foreign_ratio": 0.0,
    "trust_ratio": 0.8876129577146566,
    "dealer_ratio": 42.96898285831097,
    "three_inst_ratio": 43.85659581602563,
    "three_inst_ratio_change_20": 35.06101845965979
  },
  {
    "date": "2026-02-06",
    "code": "8155",
    "name": "博智",
    "market": "TPEX",
    "foreign_ratio": 0.0,
    "trust_ratio": 0.8876129577146566,
    "dealer_ratio": 44.712200912537845,
    "three_inst_ratio": 45.599813870252504,
    "three_inst_ratio_change_20": 34.492856508847886
  },
  {
    "date": "2026-02-09",
    "code": "8155",
    "name": "博智",
    "market": "TPEX",
    "foreign_ratio": 0.0,
    "trust_ratio": 0.8876129577146566,
    "dealer_ratio": 45.707403319672466,
    "three_inst_ratio": 46.595016277387124,
    "three_inst_ratio_change_20": 31.365589845707767
  },
  {
    "date": "2026-02-10",
    "code": "8155",
    "name": "博智",
    "market": "TPEX",
    "foreign_ratio": 0.0,
    "trust_ratio": 0.8876129577146566,
    "dealer_ratio": 46.88909410580167,
    "three_inst_ratio": 47.77670706351633,
    "three_inst_ratio_change_20": 30.926266260576266
  },
  {
    "date": "2026-02-11",
    "code": "8155",
    "name": "博智",
    "market": "TPEX",
    "foreign_ratio": 0.0,
    "trust_ratio": 0.8876129577146566,
    "dealer_ratio": 47.27910585994902,
    "three_inst_ratio": 48.16671881766368,
    "three_inst_ratio_change_20": 30.918197051869775
  },
  {
    "date": "2026-02-23",
    "code": "8155",
    "name": "博智",
    "market": "TPEX",
    "foreign_ratio": 0.0,
    "trust_ratio": 0.8876129577146566,
    "dealer_ratio": 48.12009672291503,
    "three_inst_ratio": 49.00770968062969,
    "three_inst_ratio_change_20": 31.348554849549608
  },
  {
    "date": "2026-02-24",
    "code": "8155",
    "name": "博智",
    "market": "TPEX",
    "foreign_ratio": 0.0,
    "trust_ratio": 0.8876129577146566,
    "dealer_ratio": 48.77997867935744,
    "three_inst_ratio": 49.6675916370721,
    "three_inst_ratio_change_20": 31.57269953584119
  },
  {
    "date": "2026-02-25",
    "code": "8155",
    "name": "博智",
    "market": "TPEX",
    "foreign_ratio": 0.0,
    "trust_ratio": 0.8876129577146566,
    "dealer_ratio": 49.30716698151524,
    "three_inst_ratio": 50.194779939229896,
    "three_inst_ratio_change_20": 31.931331033907718
  },
  {
    "date": "2026-03-04",
    "code": "8155",
    "name": "博智",
    "market": "TPEX",
    "foreign_ratio": 0.0,
    "trust_ratio": 0.8876129577146566,
    "dealer_ratio": 50.98199400906083,
    "three_inst_ratio": 51.869606966775486,
    "three_inst_ratio_change_20": 33.03234766454686
  },
  {
    "date": "2026-03-05",
    "code": "8155",
    "name": "博智",
    "market": "TPEX",
    "foreign_ratio": 0.0,
    "trust_ratio": 0.8876129577146566,
    "dealer_ratio": 51.487664421334635,
    "three_inst_ratio": 52.375277379049294,
    "three_inst_ratio_change_20": 32.88530875033959
  },
  {
    "date": "2026-03-06",
    "code": "8155",
    "name": "博智",
    "market": "TPEX",
    "foreign_ratio": 0.0,
    "trust_ratio": 0.8876129577146566,
    "dealer_ratio": 51.77815593476852,
    "three_inst_ratio": 52.66576889248318,
    "three_inst_ratio_change_20": 32.205702061503516
  },
  {
    "date": "2026-03-09",
    "code": "8155",
    "name": "博智",
    "market": "TPEX",
    "foreign_ratio": 0.0,
    "trust_ratio": 0.8876129577146566,
    "dealer_ratio": 52.897095174523535,
    "three_inst_ratio": 53.784708132238194,
    "three_inst_ratio_change_20": 30.417036430684153
  },
  {
    "date": "2026-03-10",
    "code": "8155",
    "name": "博智",
    "market": "TPEX",
    "foreign_ratio": 0.0,
    "trust_ratio": 0.8876129577146566,
    "dealer_ratio": 54.01423229100077,
    "three_inst_ratio": 54.90184524871543,
    "three_inst_ratio_change_20": 30.415243273193827
  },
  {
    "date": "2026-03-11",
    "code": "8155",
    "name": "博智",
    "market": "TPEX",
    "foreign_ratio": 0.0,
    "trust_ratio": 0.8876129577146566,
    "dealer_ratio": 55.10985151759401,
    "three_inst_ratio": 55.99746447530867,
    "three_inst_ratio_change_20": 26.0881426564373
  },
  {
    "date": "2026-03-12",
    "code": "8155",
    "name": "博智",
    "market": "TPEX",
    "foreign_ratio": 0.0,
    "trust_ratio": 0.8876129577146566,
    "dealer_ratio": 55.95980816801168,
    "three_inst_ratio": 56.84742112572634,
    "three_inst_ratio_change_20": 24.7145840188425
  },
  {
    "date": "2026-03-13",
    "code": "8155",
    "name": "博智",
    "market": "TPEX",
    "foreign_ratio": 0.0,
    "trust_ratio": 0.8876129577146566,
    "dealer_ratio": 56.901215850436316,
    "three_inst_ratio": 57.788828808150974,
    "three_inst_ratio_change_20": 22.594976827922324
  },
  {
    "date": "2026-03-16",
    "code": "8155",
    "name": "博智",
    "market": "TPEX",
    "foreign_ratio": 0.0,
    "trust_ratio": 0.8876129577146566,
    "dealer_ratio": 58.782955320791395,
    "three_inst_ratio": 59.67056827850605,
    "three_inst_ratio_change_20": 21.044612861780735
  },
  {
    "date": "2026-03-17",
    "code": "8155",
    "name": "博智",
    "market": "TPEX",
    "foreign_ratio": 0.0,
    "trust_ratio": 0.8876129577146566,
    "dealer_ratio": 61.09899753530503,
    "three_inst_ratio": 61.98661049301969,
    "three_inst_ratio_change_20": 21.088724536042918
  },
  {
    "date": "2026-03-18",
    "code": "8155",
    "name": "博智",
    "market": "TPEX",
    "foreign_ratio": 0.0,
    "trust_ratio": 0.8876129577146566,
    "dealer_ratio": 61.10079069279536,
    "three_inst_ratio": 61.988403650510016,
    "three_inst_ratio_change_20": 19.740270103312767
  },
  {
    "date": "2026-03-19",
    "code": "8155",
    "name": "博智",
    "market": "TPEX",
    "foreign_ratio": 0.0,
    "trust_ratio": 0.8876129577146566,
    "dealer_ratio": 61.4325248285069,
    "three_inst_ratio": 62.32013778622156,
    "three_inst_ratio_change_20": 19.370879660304247
  },
  {
    "date": "2026-03-20",
    "code": "8155",
    "name": "博智",
    "market": "TPEX",
    "foreign_ratio": 0.0,
    "trust_ratio": 0.8876129577146566,
    "dealer_ratio": 67.59919343776085,
    "three_inst_ratio": 68.4868063954755,
    "three_inst_ratio_change_20": 24.630210579449866
  },
  {
    "date": "2026-03-23",
    "code": "8155",
    "name": "博智",
    "market": "TPEX",
    "foreign_ratio": 0.0,
    "trust_ratio": 0.8876129577146566,
    "dealer_ratio": 70.14190510431246,
    "three_inst_ratio": 71.02951806202711,
    "three_inst_ratio_change_20": 25.429704191774604
  },
  {
    "date": "2026-03-24",
    "code": "8155",
    "name": "博智",
    "market": "TPEX",
    "foreign_ratio": 0.0,
    "trust_ratio": 0.8876129577146566,
    "dealer_ratio": 70.62067815423127,
    "three_inst_ratio": 71.50829111194592,
    "three_inst_ratio_change_20": 24.9132748345588
  },
  {
    "date": "2026-03-25",
    "code": "8155",
    "name": "博智",
    "market": "TPEX",
    "foreign_ratio": 0.0,
    "trust_ratio": 0.8876129577146566,
    "dealer_ratio": 70.84661599801319,
    "three_inst_ratio": 71.73422895572784,
    "three_inst_ratio_change_20": 23.957521892211517
  },
  {
    "date": "2026-03-26",
    "code": "8155",
    "name": "博智",
    "market": "TPEX",
    "foreign_ratio": 0.0,
    "trust_ratio": 0.8876129577146566,
    "dealer_ratio": 70.92551492758781,
    "three_inst_ratio": 71.81312788530246,
    "three_inst_ratio_change_20": 23.646409067638785
  },
  {
    "date": "2026-03-27",
    "code": "8155",
    "name": "博智",
    "market": "TPEX",
    "foreign_ratio": 0.0,
    "trust_ratio": 0.8876129577146566,
    "dealer_ratio": 70.99025867193377,
    "three_inst_ratio": 71.87787162964842,
    "three_inst_ratio_change_20": 22.870161949018737
  },
  {
    "date": "2026-03-30",
    "code": "8155",
    "name": "博智",
    "market": "TPEX",
    "foreign_ratio": 0.0,
    "trust_ratio": 0.8876129577146566,
    "dealer_ratio": 71.02074234926943,
    "three_inst_ratio": 71.90835530698408,
    "three_inst_ratio_change_20": 22.240763669911978
  },
  {
    "date": "2026-03-31",
    "code": "8155",
    "name": "博智",
    "market": "TPEX",
    "foreign_ratio": 0.0,
    "trust_ratio": 0.8876129577146566,
    "dealer_ratio": 71.16957442096702,
    "three_inst_ratio": 72.05718737868168,
    "three_inst_ratio_change_20": 21.86240743945178
  },
  {
    "date": "2026-04-01",
    "code": "8155",
    "name": "博智",
    "market": "TPEX",
    "foreign_ratio": 0.0,
    "trust_ratio": 0.8876129577146566,
    "dealer_ratio": 71.23771440559968,
    "three_inst_ratio": 72.12532736331433,
    "three_inst_ratio_change_20": 20.25572039653884
  },
  {
    "date": "2026-04-02",
    "code": "8155",
    "name": "博智",
    "market": "TPEX",
    "foreign_ratio": 0.0,
    "trust_ratio": 0.8876129577146566,
    "dealer_ratio": 71.32916543760663,
    "three_inst_ratio": 72.21677839532128,
    "three_inst_ratio_change_20": 19.84150101627199
  },
  {
    "date": "2026-04-07",
    "code": "8155",
    "name": "博智",
    "market": "TPEX",
    "foreign_ratio": 0.0,
    "trust_ratio": 0.8876129577146566,
    "dealer_ratio": 71.36323542992295,
    "three_inst_ratio": 72.2508483876376,
    "three_inst_ratio_change_20": 19.585079495154424
  },
  {
    "date": "2026-04-08",
    "code": "8155",
    "name": "博智",
    "market": "TPEX",
    "foreign_ratio": 0.0,
    "trust_ratio": 0.8876129577146566,
    "dealer_ratio": 71.4044780522006,
    "three_inst_ratio": 72.29209100991525,
    "three_inst_ratio_change_20": 18.50738287767706
  },
  {
    "date": "2026-04-09",
    "code": "8155",
    "name": "博智",
    "market": "TPEX",
    "foreign_ratio": 0.0,
    "trust_ratio": 0.8876129577146566,
    "dealer_ratio": 73.50964494585112,
    "three_inst_ratio": 74.39725790356577,
    "three_inst_ratio_change_20": 19.49541265485034
  },
  {
    "date": "2026-04-10",
    "code": "8155",
    "name": "博智",
    "market": "TPEX",
    "foreign_ratio": 0.0,
    "trust_ratio": 0.8876129577146566,
    "dealer_ratio": 76.37331745791235,
    "three_inst_ratio": 77.260930415627,
    "three_inst_ratio_change_20": 21.263465940318333
  },
  {
    "date": "2026-04-13",
    "code": "8155",
    "name": "博智",
    "market": "TPEX",
    "foreign_ratio": 0.0,
    "trust_ratio": 0.8876129577146566,
    "dealer_ratio": 77.98363385158574,
    "three_inst_ratio": 78.87124680930039,
    "three_inst_ratio_change_20": 22.023825683574046
  },
  {
    "date": "2026-04-14",
    "code": "8155",
    "name": "博智",
    "market": "TPEX",
    "foreign_ratio": 0.0,
    "trust_ratio": 0.8876129577146566,
    "dealer_ratio": 81.51615410754104,
    "three_inst_ratio": 82.40376706525569,
    "three_inst_ratio_change_20": 24.61493825710472
  },
  {
    "date": "2026-04-15",
    "code": "8155",
    "name": "博智",
    "market": "TPEX",
    "foreign_ratio": 0.0,
    "trust_ratio": 0.8876129577146566,
    "dealer_ratio": 83.1876279305797,
    "three_inst_ratio": 84.07524088829435,
    "three_inst_ratio_change_20": 24.404672609788292
  },
  {
    "date": "2026-04-16",
    "code": "8155",
    "name": "博智",
    "market": "TPEX",
    "foreign_ratio": 0.0,
    "trust_ratio": 0.8876129577146566,
    "dealer_ratio": 87.27782016602845,
    "three_inst_ratio": 88.1654331237431,
    "three_inst_ratio_change_20": 26.17882263072341
  },
  {
    "date": "2026-04-17",
    "code": "8155",
    "name": "博智",
    "market": "TPEX",
    "foreign_ratio": 0.0,
    "trust_ratio": 0.8876129577146566,
    "dealer_ratio": 89.37590946706463,
    "three_inst_ratio": 90.26352242477928,
    "three_inst_ratio_change_20": 28.275118774269266
  },
  {
    "date": "2026-04-20",
    "code": "8155",
    "name": "博智",
    "market": "TPEX",
    "foreign_ratio": 0.0,
    "trust_ratio": 0.8876129577146566,
    "dealer_ratio": 91.75190590226754,
    "three_inst_ratio": 92.63951885998219,
    "three_inst_ratio_change_20": 30.31938107376063
  },
  {
    "date": "2026-04-21",
    "code": "8155",
    "name": "博智",
    "market": "TPEX",
    "foreign_ratio": 0.0,
    "trust_ratio": 0.8876129577146566,
    "dealer_ratio": 93.45719867557388,
    "three_inst_ratio": 94.34481163328853,
    "three_inst_ratio_change_20": 25.858005237813032
  },
  {
    "date": "2026-04-22",
    "code": "8155",
    "name": "博智",
    "market": "TPEX",
    "foreign_ratio": 0.0,
    "trust_ratio": 0.8876129577146566,
    "dealer_ratio": 95.45842160898228,
    "three_inst_ratio": 96.34603456669693,
    "three_inst_ratio_change_20": 25.31651650466982
  },
  {
    "date": "2026-04-23",
    "code": "8155",
    "name": "博智",
    "market": "TPEX",
    "foreign_ratio": 0.0,
    "trust_ratio": 0.8876129577146566,
    "dealer_ratio": 100.6982591130505,
    "three_inst_ratio": 101.58587207076515,
    "three_inst_ratio_change_20": 30.077580958819226
  },
  {
    "date": "2026-04-24",
    "code": "8155",
    "name": "博智",
    "market": "TPEX",
    "foreign_ratio": 0.0,
    "trust_ratio": 0.8167694954710875,
    "dealer_ratio": 94.97800282994955,
    "three_inst_ratio": 95.79477232542064,
    "three_inst_ratio_change_20": 24.060543369692795
  },
  {
    "date": "2026-04-27",
    "code": "8155",
    "name": "博智",
    "market": "TPEX",
    "foreign_ratio": 0.0,
    "trust_ratio": 0.8167694954710875,
    "dealer_ratio": 97.68905053994735,
    "three_inst_ratio": 98.50582003541844,
    "three_inst_ratio_change_20": 26.692692150115974
  },
  {
    "date": "2026-04-28",
    "code": "8155",
    "name": "博智",
    "market": "TPEX",
    "foreign_ratio": 0.0,
    "trust_ratio": 0.8167694954710875,
    "dealer_ratio": 99.9133861326136,
    "three_inst_ratio": 100.73015562808469,
    "three_inst_ratio_change_20": 28.852283998436263
  },
  {
    "date": "2026-04-29",
    "code": "8155",
    "name": "博智",
    "market": "TPEX",
    "foreign_ratio": 0.0,
    "trust_ratio": 0.8167694954710875,
    "dealer_ratio": 101.17566626197801,
    "three_inst_ratio": 101.9924357574491,
    "three_inst_ratio_change_20": 30.084080450465024
  },
  {
    "date": "2026-04-30",
    "code": "8155",
    "name": "博智",
    "market": "TPEX",
    "foreign_ratio": 0.0,
    "trust_ratio": 0.8167694954710875,
    "dealer_ratio": 103.22676421963514,
    "three_inst_ratio": 104.04353371510624,
    "three_inst_ratio_change_20": 31.98634633642456
  },
  {
    "date": "2026-05-04",
    "code": "8155",
    "name": "博智",
    "market": "TPEX",
    "foreign_ratio": 0.0,
    "trust_ratio": 0.8167694954710875,
    "dealer_ratio": 104.34879100129241,
    "three_inst_ratio": 105.1655604967635,
    "three_inst_ratio_change_20": 33.04023313344918
  },
  {
    "date": "2026-05-05",
    "code": "8155",
    "name": "博智",
    "market": "TPEX",
    "foreign_ratio": 0.0,
    "trust_ratio": 0.8167694954710875,
    "dealer_ratio": 106.28304967011258,
    "three_inst_ratio": 107.09981916558367,
    "three_inst_ratio_change_20": 34.88304077026238
  },
  {
    "date": "2026-05-06",
    "code": "8155",
    "name": "博智",
    "market": "TPEX",
    "foreign_ratio": 0.0,
    "trust_ratio": 0.8167694954710875,
    "dealer_ratio": 109.26989981323865,
    "three_inst_ratio": 110.08666930870974,
    "three_inst_ratio_change_20": 37.83582092107214
  },
  {
    "date": "2026-05-07",
    "code": "8155",
    "name": "博智",
    "market": "TPEX",
    "foreign_ratio": 0.0,
    "trust_ratio": 0.8167694954710875,
    "dealer_ratio": 111.24338156827464,
    "three_inst_ratio": 112.06015106374574,
    "three_inst_ratio_change_20": 39.76806005383048
  },
  {
    "date": "2026-05-08",
    "code": "8155",
    "name": "博智",
    "market": "TPEX",
    "foreign_ratio": 0.0,
    "trust_ratio": 0.8167694954710875,
    "dealer_ratio": 112.56187853947885,
    "three_inst_ratio": 113.37864803494995,
    "three_inst_ratio_change_20": 38.981390131384174
  },
  {
    "date": "2026-05-11",
    "code": "8155",
    "name": "博智",
    "market": "TPEX",
    "foreign_ratio": 0.0,
    "trust_ratio": 0.8167694954710875,
    "dealer_ratio": 113.40868370187127,
    "three_inst_ratio": 114.22545319734236,
    "three_inst_ratio_change_20": 36.96452278171536
  },
  {
    "date": "2026-05-12",
    "code": "8155",
    "name": "博智",
    "market": "TPEX",
    "foreign_ratio": 0.0,
    "trust_ratio": 0.8167694954710875,
    "dealer_ratio": 114.30135500904271,
    "three_inst_ratio": 115.1181245045138,
    "three_inst_ratio_change_20": 36.24687769521341
  },
  {
    "date": "2026-05-13",
    "code": "8155",
    "name": "博智",
    "market": "TPEX",
    "foreign_ratio": 0.0,
    "trust_ratio": 0.8167694954710875,
    "dealer_ratio": 115.20069742544685,
    "three_inst_ratio": 116.01746692091794,
    "three_inst_ratio_change_20": 33.61369985566225
  },
  {
    "date": "2026-05-14",
    "code": "8155",
    "name": "博智",
    "market": "TPEX",
    "foreign_ratio": 0.0,
    "trust_ratio": 0.8167694954710875,
    "dealer_ratio": 116.32289416116073,
    "three_inst_ratio": 117.13966365663183,
    "three_inst_ratio_change_20": 33.06442276833748
  },
  {
    "date": "2026-05-15",
    "code": "8155",
    "name": "博智",
    "market": "TPEX",
    "foreign_ratio": 0.0,
    "trust_ratio": 0.8167694954710875,
    "dealer_ratio": 117.5455733452902,
    "three_inst_ratio": 118.36234284076129,
    "three_inst_ratio_change_20": 30.196909717018187
  },
  {
    "date": "2026-05-18",
    "code": "8155",
    "name": "博智",
    "market": "TPEX",
    "foreign_ratio": 0.0,
    "trust_ratio": 0.8167694954710875,
    "dealer_ratio": 118.8509195025976,
    "three_inst_ratio": 119.6676889980687,
    "three_inst_ratio_change_20": 29.404166573289416
  },
  {
    "date": "2026-05-19",
    "code": "8155",
    "name": "博智",
    "market": "TPEX",
    "foreign_ratio": 0.0,
    "trust_ratio": 0.8167694954710875,
    "dealer_ratio": 119.69578091859474,
    "three_inst_ratio": 120.51255041406583,
    "three_inst_ratio_change_20": 27.87303155408364
  },
  {
    "date": "2026-05-20",
    "code": "8155",
    "name": "博智",
    "market": "TPEX",
    "foreign_ratio": 0.0,
    "trust_ratio": 0.8167694954710875,
    "dealer_ratio": 120.1710335123989,
    "three_inst_ratio": 120.98780300787,
    "three_inst_ratio_change_20": 26.64299137458147
  },
  {
    "date": "2026-05-21",
    "code": "8155",
    "name": "博智",
    "market": "TPEX",
    "foreign_ratio": 0.0,
    "trust_ratio": 0.8167694954710875,
    "dealer_ratio": 120.9269099544137,
    "three_inst_ratio": 121.7436794498848,
    "three_inst_ratio_change_20": 25.397644883187866
  },
  {
    "date": "2026-05-22",
    "code": "8155",
    "name": "博智",
    "market": "TPEX",
    "foreign_ratio": 0.0,
    "trust_ratio": 0.8167694954710875,
    "dealer_ratio": 121.62185869214512,
    "three_inst_ratio": 122.43862818761622,
    "three_inst_ratio_change_20": 20.85275611685107
  },
  {
    "date": "2026-05-25",
    "code": "8155",
    "name": "博智",
    "market": "TPEX",
    "foreign_ratio": 0.0,
    "trust_ratio": 0.8167694954710875,
    "dealer_ratio": 122.79668673411565,
    "three_inst_ratio": 123.61345622958675,
    "three_inst_ratio_change_20": 27.818683904166107
  },
  {
    "date": "2026-05-26",
    "code": "8155",
    "name": "博智",
    "market": "TPEX",
    "foreign_ratio": 0.0,
    "trust_ratio": 0.8167694954710875,
    "dealer_ratio": 124.04097153394954,
    "three_inst_ratio": 124.85774102942064,
    "three_inst_ratio_change_20": 26.3519209940022
  },
  {
    "date": "2026-05-27",
    "code": "8155",
    "name": "博智",
    "market": "TPEX",
    "foreign_ratio": 0.0,
    "trust_ratio": 0.8167694954710875,
    "dealer_ratio": 124.5443110981616,
    "three_inst_ratio": 125.36108059363269,
    "three_inst_ratio_change_20": 24.630924965548004
  },
  {
    "date": "2026-05-28",
    "code": "8155",
    "name": "博智",
    "market": "TPEX",
    "foreign_ratio": 0.0,
    "trust_ratio": 0.8167694954710875,
    "dealer_ratio": 125.48648688695549,
    "three_inst_ratio": 126.30325638242658,
    "three_inst_ratio_change_20": 24.31082062497748
  },
  {
    "date": "2026-05-29",
    "code": "8155",
    "name": "博智",
    "market": "TPEX",
    "foreign_ratio": 0.0,
    "trust_ratio": 0.8167694954710875,
    "dealer_ratio": 126.25705527965248,
    "three_inst_ratio": 127.07382477512357,
    "three_inst_ratio_change_20": 23.030291060017333
  },
  {
    "date": "2026-06-01",
    "code": "8155",
    "name": "博智",
    "market": "TPEX",
    "foreign_ratio": 0.0,
    "trust_ratio": 0.8167694954710875,
    "dealer_ratio": 126.73061658308723,
    "three_inst_ratio": 127.54738607855832,
    "three_inst_ratio_change_20": 22.381825581794814
  },
  {
    "date": "2026-06-02",
    "code": "8155",
    "name": "博智",
    "market": "TPEX",
    "foreign_ratio": 0.0,
    "trust_ratio": 0.8167694954710875,
    "dealer_ratio": 127.35637421929624,
    "three_inst_ratio": 128.17314371476732,
    "three_inst_ratio_change_20": 21.073324549183653
  },
  {
    "date": "2026-06-03",
    "code": "8155",
    "name": "博智",
    "market": "TPEX",
    "foreign_ratio": 0.0,
    "trust_ratio": 0.8167694954710875,
    "dealer_ratio": 128.3942489923292,
    "three_inst_ratio": 129.2110184878003,
    "three_inst_ratio_change_20": 19.124349179090544
  },
  {
    "date": "2026-06-04",
    "code": "8155",
    "name": "博智",
    "market": "TPEX",
    "foreign_ratio": 0.0,
    "trust_ratio": 0.8167694954710875,
    "dealer_ratio": 128.64018736263216,
    "three_inst_ratio": 129.45695685810324,
    "three_inst_ratio_change_20": 17.396805794357505
  },
  {
    "date": "2026-06-05",
    "code": "8155",
    "name": "博智",
    "market": "TPEX",
    "foreign_ratio": 0.0,
    "trust_ratio": 0.8167694954710875,
    "dealer_ratio": 129.4855685410355,
    "three_inst_ratio": 130.30233803650657,
    "three_inst_ratio_change_20": 16.923690001556622
  },
  {
    "date": "2026-06-08",
    "code": "8155",
    "name": "博智",
    "market": "TPEX",
    "foreign_ratio": 0.0,
    "trust_ratio": 0.8167694954710875,
    "dealer_ratio": 130.45097358428848,
    "three_inst_ratio": 131.26774307975955,
    "three_inst_ratio_change_20": 17.042289882417194
  },
  {
    "date": "2026-06-09",
    "code": "8155",
    "name": "博智",
    "market": "TPEX",
    "foreign_ratio": 0.0,
    "trust_ratio": 0.8167694954710875,
    "dealer_ratio": 130.87833378494912,
    "three_inst_ratio": 131.6951032804202,
    "three_inst_ratio_change_20": 16.576978775906397
  },
  {
    "date": "2026-06-10",
    "code": "8155",
    "name": "博智",
    "market": "TPEX",
    "foreign_ratio": 0.0,
    "trust_ratio": 0.8167694954710875,
    "dealer_ratio": 131.74111462866506,
    "three_inst_ratio": 132.55788412413614,
    "three_inst_ratio_change_20": 16.540417203218198
  },
  {
    "date": "2026-06-11",
    "code": "8155",
    "name": "博智",
    "market": "TPEX",
    "foreign_ratio": 0.0,
    "trust_ratio": 0.8167694954710875,
    "dealer_ratio": 132.36743162822552,
    "three_inst_ratio": 133.1842011236966,
    "three_inst_ratio_change_20": 16.04453746706477
  },
  {
    "date": "2026-06-12",
    "code": "8155",
    "name": "博智",
    "market": "TPEX",
    "foreign_ratio": 0.0,
    "trust_ratio": 0.8167694954710875,
    "dealer_ratio": 132.9073179147713,
    "three_inst_ratio": 133.7240874102424,
    "three_inst_ratio_change_20": 15.361744569481104
  },
  {
    "date": "2026-06-15",
    "code": "8155",
    "name": "博智",
    "market": "TPEX",
    "foreign_ratio": 0.0,
    "trust_ratio": 0.8167694954710875,
    "dealer_ratio": 133.894059617309,
    "three_inst_ratio": 134.7108291127801,
    "three_inst_ratio_change_20": 15.043140114711392
  },
  {
    "date": "2026-06-16",
    "code": "8155",
    "name": "博智",
    "market": "TPEX",
    "foreign_ratio": 0.0,
    "trust_ratio": 0.8167694954710875,
    "dealer_ratio": 134.82001221887165,
    "three_inst_ratio": 135.63678171434273,
    "three_inst_ratio_change_20": 15.124231300276904
  },
  {
    "date": "2026-06-17",
    "code": "8155",
    "name": "博智",
    "market": "TPEX",
    "foreign_ratio": 0.0,
    "trust_ratio": 0.8167694954710875,
    "dealer_ratio": 135.55190533842853,
    "three_inst_ratio": 136.3686748338996,
    "three_inst_ratio_change_20": 15.380871826029605
  },
  {
    "date": "2026-06-18",
    "code": "8155",
    "name": "博智",
    "market": "TPEX",
    "foreign_ratio": 0.0,
    "trust_ratio": 0.8167694954710875,
    "dealer_ratio": 135.81426160061014,
    "three_inst_ratio": 136.63103109608122,
    "three_inst_ratio_change_20": 14.887351646196421
  },
  {
    "date": "2026-06-22",
    "code": "8155",
    "name": "博智",
    "market": "TPEX",
    "foreign_ratio": 0.0,
    "trust_ratio": 0.8167694954710875,
    "dealer_ratio": 136.1946237294738,
    "three_inst_ratio": 137.01139322494487,
    "three_inst_ratio_change_20": 14.57276503732865
  },
  {
    "date": "2026-06-23",
    "code": "8155",
    "name": "博智",
    "market": "TPEX",
    "foreign_ratio": 0.0,
    "trust_ratio": 0.8167694954710875,
    "dealer_ratio": 136.60734808079133,
    "three_inst_ratio": 137.4241175762624,
    "three_inst_ratio_change_20": 13.810661346675658
  },
  {
    "date": "2026-06-24",
    "code": "8155",
    "name": "博智",
    "market": "TPEX",
    "foreign_ratio": 0.0,
    "trust_ratio": 0.8167694954710875,
    "dealer_ratio": 136.95313528438612,
    "three_inst_ratio": 137.7699047798572,
    "three_inst_ratio_change_20": 12.912163750436562
  },
  {
    "date": "2026-06-25",
    "code": "8155",
    "name": "博智",
    "market": "TPEX",
    "foreign_ratio": 0.0,
    "trust_ratio": 0.8167694954710875,
    "dealer_ratio": 137.36235330201097,
    "three_inst_ratio": 138.17912279748205,
    "three_inst_ratio_change_20": 12.818042203849359
  },
  {
    "date": "2026-06-26",
    "code": "8155",
    "name": "博智",
    "market": "TPEX",
    "foreign_ratio": 0.0,
    "trust_ratio": 0.8167694954710875,
    "dealer_ratio": 137.755062675591,
    "three_inst_ratio": 138.57183217106208,
    "three_inst_ratio_change_20": 12.268575788635502
  }
]