[
  {
    "code": "00943",
    "name": "兆豐電子高息等權",
    "market": "TWSE",
    "three_inst_ratio": 30.45,
    "change": 26.08
  },
  {
    "code": "2492",
    "name": "華新科",
    "market": "TWSE",
    "three_inst_ratio": 33.18076818766008,
    "change": 15.714869655506089
  },
  {
    "code": "00689R",
    "name": "國泰20年美債反1",
    "market": "TWSE",
    "three_inst_ratio": 36.71,
    "change": 14.93
  },
  {
    "code": "6165",
    "name": "浪凡",
    "market": "TWSE",
    "three_inst_ratio": 17.89,
    "change": 13.370000000000001
  },
  {
    "code": "4916",
    "name": "事欣科",
    "market": "TWSE",
    "three_inst_ratio": 17.738191729149957,
    "change": 13.24948111667958
  },
  {
    "code": "3033",
    "name": "威健",
    "market": "TWSE",
    "three_inst_ratio": 22.13401384804365,
    "change": 12.92971972272007
  },
  {
    "code": "00922",
    "name": "國泰台灣領袖50",
    "market": "TWSE",
    "three_inst_ratio": 20.48,
    "change": 12.58
  },
  {
    "code": "8028",
    "name": "昇陽半導體",
    "market": "TWSE",
    "three_inst_ratio": 28.25353803432821,
    "change": 11.63391979984366
  },
  {
    "code": "6414",
    "name": "樺漢",
    "market": "TWSE",
    "three_inst_ratio": 38.71141060718635,
    "change": 11.304945298110546
  },
  {
    "code": "3583",
    "name": "辛耘",
    "market": "TWSE",
    "three_inst_ratio": 26.90435778820821,
    "change": 10.755262578567734
  },
  {
    "code": "2376",
    "name": "技嘉",
    "market": "TWSE",
    "three_inst_ratio": 27.132554235419875,
    "change": 10.337366670268956
  },
  {
    "code": "3550",
    "name": "聯穎",
    "market": "TWSE",
    "three_inst_ratio": 13.827201301720129,
    "change": 10.279999999999998
  },
  {
    "code": "00983A",
    "name": "主動中信ARK創新",
    "market": "TWSE",
    "three_inst_ratio": 11.41,
    "change": 10.25
  },
  {
    "code": "00683L",
    "name": "期元大美元指正2",
    "market": "TWSE",
    "three_inst_ratio": 18.99,
    "change": 10.069999999999999
  },
  {
    "code": "2406",
    "name": "國碩",
    "market": "TWSE",
    "three_inst_ratio": 23.228549305679678,
    "change": 9.978549305679678
  },
  {
    "code": "3450",
    "name": "聯鈞",
    "market": "TWSE",
    "three_inst_ratio": 27.78252935546699,
    "change": 9.764049562901597
  },
  {
    "code": "3661",
    "name": "世芯-KY",
    "market": "TWSE",
    "three_inst_ratio": 58.62263692857249,
    "change": 8.71784459638117
  },
  {
    "code": "3090",
    "name": "日電貿",
    "market": "TWSE",
    "three_inst_ratio": 15.456560730250308,
    "change": 8.548266371871751
  },
  {
    "code": "00731",
    "name": "復華富時高息低波",
    "market": "TWSE",
    "three_inst_ratio": 10.47149377593361,
    "change": 8.298271184571483
  },
  {
    "code": "3533",
    "name": "嘉澤",
    "market": "TWSE",
    "three_inst_ratio": 53.774453671001766,
    "change": 8.049430230896533
  },
  {
    "code": "2455",
    "name": "全新",
    "market": "TWSE",
    "three_inst_ratio": 42.981317559127554,
    "change": 8.019139385143959
  },
  {
    "code": "3026",
    "name": "禾伸堂",
    "market": "TWSE",
    "three_inst_ratio": 27.545580699049598,
    "change": 7.898680648258207
  },
  {
    "code": "6285",
    "name": "啟碁",
    "market": "TWSE",
    "three_inst_ratio": 26.34378956185465,
    "change": 7.80303221626226
  },
  {
    "code": "2458",
    "name": "義隆",
    "market": "TWSE",
    "three_inst_ratio": 24.126981339947722,
    "change": 7.6339424303493715
  },
  {
    "code": "3189",
    "name": "景碩",
    "market": "TWSE",
    "three_inst_ratio": 30.731346950791526,
    "change": 7.435704508730026
  },
  {
    "code": "00936",
    "name": "台新永續高息中小",
    "market": "TWSE",
    "three_inst_ratio": 9.02,
    "change": 7.22
  },
  {
    "code": "3702",
    "name": "大聯大",
    "market": "TWSE",
    "three_inst_ratio": 31.340516221716285,
    "change": 7.095210865617002
  },
  {
    "code": "3209",
    "name": "全科",
    "market": "TWSE",
    "three_inst_ratio": 19.849654061860402,
    "change": 7.086649655465797
  },
  {
    "code": "6831",
    "name": "邁科",
    "market": "TWSE",
    "three_inst_ratio": 18.040514074074075,
    "change": 7.060164444444446
  },
  {
    "code": "2049",
    "name": "上銀",
    "market": "TWSE",
    "three_inst_ratio": 36.776027668667915,
    "change": 7.016314037865836
  },
  {
    "code": "8021",
    "name": "尖點",
    "market": "TWSE",
    "three_inst_ratio": 22.063999347584183,
    "change": 6.963622433490464
  },
  {
    "code": "00947",
    "name": "台新臺灣IC設計",
    "market": "TWSE",
    "three_inst_ratio": 9.396113683657973,
    "change": 6.946113683657972
  },
  {
    "code": "3231",
    "name": "緯創",
    "market": "TWSE",
    "three_inst_ratio": 33.05396469671503,
    "change": 6.753854362748104
  },
  {
    "code": "8016",
    "name": "矽創",
    "market": "TWSE",
    "three_inst_ratio": 36.35442250654162,
    "change": 6.703462293459335
  },
  {
    "code": "3305",
    "name": "昇貿",
    "market": "TWSE",
    "three_inst_ratio": 8.71019470943611,
    "change": 6.643780687670473
  },
  {
    "code": "3406",
    "name": "玉晶光",
    "market": "TWSE",
    "three_inst_ratio": 44.84543809342842,
    "change": 6.637108948068942
  },
  {
    "code": "2301",
    "name": "光寶科",
    "market": "TWSE",
    "three_inst_ratio": 35.694289747000866,
    "change": 6.604008563901317
  },
  {
    "code": "6415",
    "name": "矽力*-KY",
    "market": "TWSE",
    "three_inst_ratio": 84.31234043193325,
    "change": 6.505705651641634
  },
  {
    "code": "6166",
    "name": "凌華",
    "market": "TWSE",
    "three_inst_ratio": 21.228552662892042,
    "change": 6.388552662892042
  },
  {
    "code": "2481",
    "name": "強茂",
    "market": "TWSE",
    "three_inst_ratio": 37.286395257780654,
    "change": 6.260529086763473
  },
  {
    "code": "2356",
    "name": "英業達",
    "market": "TWSE",
    "three_inst_ratio": 19.203083117762915,
    "change": 6.2509342972252995
  },
  {
    "code": "2379",
    "name": "瑞昱",
    "market": "TWSE",
    "three_inst_ratio": 50.70690083068205,
    "change": 6.0836795815837235
  },
  {
    "code": "2344",
    "name": "華邦電",
    "market": "TWSE",
    "three_inst_ratio": 32.672854887406444,
    "change": 6.075340065099859
  },
  {
    "code": "2243",
    "name": "宏旭-KY",
    "market": "TWSE",
    "three_inst_ratio": 30.69252500216365,
    "change": 6.012525002163649
  },
  {
    "code": "6206",
    "name": "飛捷",
    "market": "TWSE",
    "three_inst_ratio": 13.658418866731118,
    "change": 5.966141379333387
  },
  {
    "code": "6715",
    "name": "嘉基",
    "market": "TWSE",
    "three_inst_ratio": 9.769507325445863,
    "change": 5.959507325445863
  },
  {
    "code": "4571",
    "name": "鈞興-KY",
    "market": "TWSE",
    "three_inst_ratio": 66.53726895361999,
    "change": 5.946227633284089
  },
  {
    "code": "00992A",
    "name": "主動群益科技創新",
    "market": "TWSE",
    "three_inst_ratio": 6.768316767051644,
    "change": 5.928316767051644
  },
  {
    "code": "00674R",
    "name": "期元大S&P黃金反1",
    "market": "TWSE",
    "three_inst_ratio": 7.85,
    "change": 5.859999999999999
  },
  {
    "code": "2351",
    "name": "順德",
    "market": "TWSE",
    "three_inst_ratio": 18.657215206947477,
    "change": 5.858031731635547
  },
  {
    "code": "3023",
    "name": "信邦",
    "market": "TWSE",
    "three_inst_ratio": 46.95615006882979,
    "change": 5.8198036474628125
  },
  {
    "code": "2316",
    "name": "楠梓電",
    "market": "TWSE",
    "three_inst_ratio": 35.03697667473187,
    "change": 5.755556825552919
  },
  {
    "code": "9933",
    "name": "中鼎",
    "market": "TWSE",
    "three_inst_ratio": 18.645833269022805,
    "change": 5.619269500894918
  },
  {
    "code": "00661",
    "name": "元大日經225",
    "market": "TWSE",
    "three_inst_ratio": 6.698537886872999,
    "change": 5.61067161352
  },
  {
    "code": "6271",
    "name": "同欣電",
    "market": "TWSE",
    "three_inst_ratio": 34.208029094544585,
    "change": 5.599067442060967
  },
  {
    "code": "4576",
    "name": "大銀微系統",
    "market": "TWSE",
    "three_inst_ratio": 7.427728539212517,
    "change": 5.434174672831425
  },
  {
    "code": "8996",
    "name": "高力",
    "market": "TWSE",
    "three_inst_ratio": 48.09109020551363,
    "change": 5.414303164291418
  },
  {
    "code": "7788",
    "name": "松川精密",
    "market": "TWSE",
    "three_inst_ratio": 9.51,
    "change": 5.24
  },
  {
    "code": "00907",
    "name": "永豐優息存股",
    "market": "TWSE",
    "three_inst_ratio": 5.56,
    "change": 5.2299999999999995
  },
  {
    "code": "2727",
    "name": "王品",
    "market": "TWSE",
    "three_inst_ratio": 31.571250828474312,
    "change": 5.219347900592098
  },
  {
    "code": "00910",
    "name": "第一金太空衛星",
    "market": "TWSE",
    "three_inst_ratio": 6.9,
    "change": 5.12
  },
  {
    "code": "6491",
    "name": "晶碩",
    "market": "TWSE",
    "three_inst_ratio": 13.346785897435897,
    "change": 5.057915384615384
  },
  {
    "code": "3048",
    "name": "益登",
    "market": "TWSE",
    "three_inst_ratio": 6.540344291112641,
    "change": 4.960344291112641
  },
  {
    "code": "3704",
    "name": "合勤控",
    "market": "TWSE",
    "three_inst_ratio": 13.191962714821171,
    "change": 4.928450454460911
  },
  {
    "code": "00930",
    "name": "永豐ESG低碳高息",
    "market": "TWSE",
    "three_inst_ratio": 5.19,
    "change": 4.83
  },
  {
    "code": "2327",
    "name": "國巨*",
    "market": "TWSE",
    "three_inst_ratio": 55.938058268413805,
    "change": 4.827421646436122
  },
  {
    "code": "00714",
    "name": "群益道瓊美國地產",
    "market": "TWSE",
    "three_inst_ratio": 7.01,
    "change": 4.82
  },
  {
    "code": "4764",
    "name": "雙鍵",
    "market": "TWSE",
    "three_inst_ratio": 29.41814362365967,
    "change": 4.810073053885471
  },
  {
    "code": "00634R",
    "name": "富邦上証反1",
    "market": "TWSE",
    "three_inst_ratio": 8.71,
    "change": 4.700000000000001
  },
  {
    "code": "3008",
    "name": "大立光",
    "market": "TWSE",
    "three_inst_ratio": 35.43674396008685,
    "change": 4.689103487577881
  },
  {
    "code": "00875",
    "name": "國泰網路資安",
    "market": "TWSE",
    "three_inst_ratio": 6.53,
    "change": 4.68
  },
  {
    "code": "6196",
    "name": "帆宣",
    "market": "TWSE",
    "three_inst_ratio": 13.366774123998603,
    "change": 4.611612066263781
  },
  {
    "code": "2464",
    "name": "盟立",
    "market": "TWSE",
    "three_inst_ratio": 11.272734845394135,
    "change": 4.542762642274353
  },
  {
    "code": "00908",
    "name": "富邦入息REITs+",
    "market": "TWSE",
    "three_inst_ratio": 6.41,
    "change": 4.51
  },
  {
    "code": "2476",
    "name": "鉅祥",
    "market": "TWSE",
    "three_inst_ratio": 11.83022734437346,
    "change": 4.43022734437346
  },
  {
    "code": "5285",
    "name": "界霖",
    "market": "TWSE",
    "three_inst_ratio": 7.347530293678441,
    "change": 4.3075302936784405
  },
  {
    "code": "6443",
    "name": "元晶",
    "market": "TWSE",
    "three_inst_ratio": 15.9,
    "change": 4.290000000000001
  },
  {
    "code": "5871",
    "name": "中租-KY",
    "market": "TWSE",
    "three_inst_ratio": 41.78799117380435,
    "change": 4.265671104869547
  },
  {
    "code": "6890",
    "name": "來億-KY",
    "market": "TWSE",
    "three_inst_ratio": 91.53510465116278,
    "change": 4.227526463512419
  },
  {
    "code": "2401",
    "name": "凌陽",
    "market": "TWSE",
    "three_inst_ratio": 14.522328071467788,
    "change": 4.216381731174959
  },
  {
    "code": "3042",
    "name": "晶技",
    "market": "TWSE",
    "three_inst_ratio": 16.820997016233314,
    "change": 4.1861509521721345
  },
  {
    "code": "00988A",
    "name": "主動統一全球創新",
    "market": "TWSE",
    "three_inst_ratio": 5.917065271375685,
    "change": 4.169705911103075
  },
  {
    "code": "6282",
    "name": "康舒",
    "market": "TWSE",
    "three_inst_ratio": 18.642632538454837,
    "change": 4.1515756439245255
  },
  {
    "code": "00830",
    "name": "國泰費城半導體",
    "market": "TWSE",
    "three_inst_ratio": 5.351336404865422,
    "change": 4.1480255582965295
  },
  {
    "code": "2027",
    "name": "大成鋼",
    "market": "TWSE",
    "three_inst_ratio": 23.448859725240986,
    "change": 4.124793081289134
  },
  {
    "code": "2305",
    "name": "全友",
    "market": "TWSE",
    "three_inst_ratio": 6.718898997522751,
    "change": 4.098898997522751
  },
  {
    "code": "2413",
    "name": "環科",
    "market": "TWSE",
    "three_inst_ratio": 10.189214819188562,
    "change": 4.059986243632182
  },
  {
    "code": "3034",
    "name": "聯詠",
    "market": "TWSE",
    "three_inst_ratio": 34.230919241720976,
    "change": 4.041019644923068
  },
  {
    "code": "2317",
    "name": "鴻海",
    "market": "TWSE",
    "three_inst_ratio": 41.26275782087294,
    "change": 4.009112870893745
  },
  {
    "code": "2637",
    "name": "慧洋-KY",
    "market": "TWSE",
    "three_inst_ratio": 19.083887273232815,
    "change": 3.9961605106638007
  },
  {
    "code": "00730",
    "name": "富邦臺灣優質高息",
    "market": "TWSE",
    "three_inst_ratio": 4.7580049700178275,
    "change": 3.962168799585557
  },
  {
    "code": "00733",
    "name": "富邦臺灣中小",
    "market": "TWSE",
    "three_inst_ratio": 7.042008912099452,
    "change": 3.951311843196651
  },
  {
    "code": "7769",
    "name": "鴻勁",
    "market": "TWSE",
    "three_inst_ratio": 23.992303117879178,
    "change": 3.9306991607847515
  },
  {
    "code": "00962",
    "name": "台新AI優息動能",
    "market": "TWSE",
    "three_inst_ratio": 4.28,
    "change": 3.87
  },
  {
    "code": "6834",
    "name": "天二科技",
    "market": "TWSE",
    "three_inst_ratio": 14.14,
    "change": 3.84
  },
  {
    "code": "00897",
    "name": "富邦基因免疫生技",
    "market": "TWSE",
    "three_inst_ratio": 4.11,
    "change": 3.8200000000000003
  },
  {
    "code": "6153",
    "name": "嘉聯益",
    "market": "TWSE",
    "three_inst_ratio": 13.323930143140165,
    "change": 3.8082434153059133
  },
  {
    "code": "2484",
    "name": "希華",
    "market": "TWSE",
    "three_inst_ratio": 8.92,
    "change": 3.8
  },
  {
    "code": "00954",
    "name": "中信日本半導體",
    "market": "TWSE",
    "three_inst_ratio": 5.96,
    "change": 3.77
  },
  {
    "code": "2444",
    "name": "兆勁",
    "market": "TWSE",
    "three_inst_ratio": 4.41,
    "change": 3.72
  },
  {
    "code": "6202",
    "name": "盛群",
    "market": "TWSE",
    "three_inst_ratio": 13.149089640875705,
    "change": 3.7139821397102804
  },
  {
    "code": "3528",
    "name": "安馳",
    "market": "TWSE",
    "three_inst_ratio": 6.52,
    "change": 3.7099999999999995
  },
  {
    "code": "1560",
    "name": "中砂",
    "market": "TWSE",
    "three_inst_ratio": 39.746825913656615,
    "change": 3.6825509930630247
  },
  {
    "code": "1714",
    "name": "和桐",
    "market": "TWSE",
    "three_inst_ratio": 23.369037386207424,
    "change": 3.6690373862074246
  },
  {
    "code": "3591",
    "name": "艾笛森",
    "market": "TWSE",
    "three_inst_ratio": 6.11,
    "change": 3.6300000000000003
  },
  {
    "code": "9136",
    "name": "巨騰-DR",
    "market": "TWSE",
    "three_inst_ratio": 3.57,
    "change": 3.57
  },
  {
    "code": "6226",
    "name": "光鼎",
    "market": "TWSE",
    "three_inst_ratio": 4.63,
    "change": 3.5599999999999996
  },
  {
    "code": "2495",
    "name": "普安",
    "market": "TWSE",
    "three_inst_ratio": 8.653006464909732,
    "change": 3.5499282094330615
  },
  {
    "code": "3045",
    "name": "台灣大",
    "market": "TWSE",
    "three_inst_ratio": 18.952711767977252,
    "change": 3.5010472461722877
  },
  {
    "code": "7795",
    "name": "長廣",
    "market": "TWSE",
    "three_inst_ratio": 8.325849787830544,
    "change": 3.4624459427745045
  },
  {
    "code": "6164",
    "name": "華興",
    "market": "TWSE",
    "three_inst_ratio": 6.82125,
    "change": 3.42125
  },
  {
    "code": "3022",
    "name": "威強電",
    "market": "TWSE",
    "three_inst_ratio": 17.568352190590833,
    "change": 3.399462013652604
  },
  {
    "code": "3706",
    "name": "神達",
    "market": "TWSE",
    "three_inst_ratio": 13.310500616816086,
    "change": 3.383150108351755
  },
  {
    "code": "2382",
    "name": "廣達",
    "market": "TWSE",
    "three_inst_ratio": 27.88747347629773,
    "change": 3.3807381232309375
  },
  {
    "code": "1342",
    "name": "八貫",
    "market": "TWSE",
    "three_inst_ratio": 31.567946775794976,
    "change": 3.379999999999999
  },
  {
    "code": "2233",
    "name": "宇隆",
    "market": "TWSE",
    "three_inst_ratio": 7.91851129300184,
    "change": 3.36680573852656
  },
  {
    "code": "3011",
    "name": "今皓",
    "market": "TWSE",
    "three_inst_ratio": 5.847715998716706,
    "change": 3.3400027377135517
  },
  {
    "code": "8454",
    "name": "富邦媒",
    "market": "TWSE",
    "three_inst_ratio": 16.554503848519452,
    "change": 3.3217760308013666
  },
  {
    "code": "3413",
    "name": "京鼎",
    "market": "TWSE",
    "three_inst_ratio": 17.30861389996667,
    "change": 3.298462683151147
  },
  {
    "code": "00980A",
    "name": "主動野村臺灣優選",
    "market": "TWSE",
    "three_inst_ratio": 4.085464354580638,
    "change": 3.285464354580638
  },
  {
    "code": "2867",
    "name": "三商壽",
    "market": "TWSE",
    "three_inst_ratio": 19.620577998033152,
    "change": 3.240577692922603
  },
  {
    "code": "3443",
    "name": "創意",
    "market": "TWSE",
    "three_inst_ratio": 34.638479854749626,
    "change": 3.2382339304153334
  },
  {
    "code": "00898",
    "name": "國泰基因免疫革命",
    "market": "TWSE",
    "three_inst_ratio": 3.89,
    "change": 3.23
  },
  {
    "code": "3016",
    "name": "嘉晶",
    "market": "TWSE",
    "three_inst_ratio": 5.719569559794034,
    "change": 3.199569559794034
  },
  {
    "code": "1303",
    "name": "南亞",
    "market": "TWSE",
    "three_inst_ratio": 35.826480511096264,
    "change": 3.1846719966682144
  },
  {
    "code": "2597",
    "name": "潤弘",
    "market": "TWSE",
    "three_inst_ratio": 6.617432124512416,
    "change": 3.1810825963259055
  },
  {
    "code": "2465",
    "name": "麗臺",
    "market": "TWSE",
    "three_inst_ratio": 4.15,
    "change": 3.1700000000000004
  },
  {
    "code": "00932",
    "name": "兆豐永續高息等權",
    "market": "TWSE",
    "three_inst_ratio": 3.79,
    "change": 3.17
  },
  {
    "code": "2375",
    "name": "凱美",
    "market": "TWSE",
    "three_inst_ratio": 15.518987810794306,
    "change": 3.154836914878956
  },
  {
    "code": "2363",
    "name": "矽統",
    "market": "TWSE",
    "three_inst_ratio": 8.681675081458815,
    "change": 3.147493304724728
  },
  {
    "code": "1326",
    "name": "台化",
    "market": "TWSE",
    "three_inst_ratio": 37.71080188184723,
    "change": 3.1402421653159465
  },
  {
    "code": "8046",
    "name": "南電",
    "market": "TWSE",
    "three_inst_ratio": 22.662799910172236,
    "change": 3.136991598376717
  },
  {
    "code": "0050",
    "name": "元大台灣50",
    "market": "TWSE",
    "three_inst_ratio": 7.662782962798827,
    "change": 3.1173704362832533
  },
  {
    "code": "00920",
    "name": "富邦ESG綠色電力",
    "market": "TWSE",
    "three_inst_ratio": 4.94,
    "change": 3.0700000000000003
  },
  {
    "code": "2461",
    "name": "光群雷",
    "market": "TWSE",
    "three_inst_ratio": 8.36,
    "change": 3.0699999999999994
  },
  {
    "code": "3312",
    "name": "弘憶股",
    "market": "TWSE",
    "three_inst_ratio": 4.41,
    "change": 3.06
  },
  {
    "code": "6214",
    "name": "精誠",
    "market": "TWSE",
    "three_inst_ratio": 13.684179490323547,
    "change": 3.059919165617977
  },
  {
    "code": "00986A",
    "name": "主動台新龍頭成長",
    "market": "TWSE",
    "three_inst_ratio": 3.64,
    "change": 3.0
  },
  {
    "code": "2349",
    "name": "錸德",
    "market": "TWSE",
    "three_inst_ratio": 14.63,
    "change": 3.0
  },
  {
    "code": "3014",
    "name": "聯陽",
    "market": "TWSE",
    "three_inst_ratio": 22.13696784504803,
    "change": 2.9802652350311227
  },
  {
    "code": "2501",
    "name": "國建",
    "market": "TWSE",
    "three_inst_ratio": 12.57718355396238,
    "change": 2.9725698111598966
  },
  {
    "code": "2337",
    "name": "旺宏",
    "market": "TWSE",
    "three_inst_ratio": 33.086985897433195,
    "change": 2.9572427285675467
  },
  {
    "code": "4551",
    "name": "智伸科",
    "market": "TWSE",
    "three_inst_ratio": 53.09697582359306,
    "change": 2.9532725558510293
  },
  {
    "code": "5388",
    "name": "中磊",
    "market": "TWSE",
    "three_inst_ratio": 18.22162291349988,
    "change": 2.9260256757289014
  },
  {
    "code": "6944",
    "name": "兆聯實業",
    "market": "TWSE",
    "three_inst_ratio": 17.538365189027445,
    "change": 2.899720818018425
  },
  {
    "code": "2851",
    "name": "中再保",
    "market": "TWSE",
    "three_inst_ratio": 9.089110853944412,
    "change": 2.8807787778126572
  },
  {
    "code": "2032",
    "name": "新鋼",
    "market": "TWSE",
    "three_inst_ratio": 4.13,
    "change": 2.8099999999999996
  },
  {
    "code": "1597",
    "name": "直得",
    "market": "TWSE",
    "three_inst_ratio": 7.365639001425515,
    "change": 2.805639001425515
  },
  {
    "code": "00989A",
    "name": "主動摩根美國科技",
    "market": "TWSE",
    "three_inst_ratio": 5.91,
    "change": 2.77
  },
  {
    "code": "4958",
    "name": "臻鼎-KY",
    "market": "TWSE",
    "three_inst_ratio": 68.74153715303055,
    "change": 2.7553712843222087
  },
  {
    "code": "2342",
    "name": "茂矽",
    "market": "TWSE",
    "three_inst_ratio": 5.868257197103302,
    "change": 2.7482571971033023
  },
  {
    "code": "6116",
    "name": "彩晶",
    "market": "TWSE",
    "three_inst_ratio": 8.33970758974288,
    "change": 2.7397022375752353
  },
  {
    "code": "2395",
    "name": "研華",
    "market": "TWSE",
    "three_inst_ratio": 35.80869214178907,
    "change": 2.73961060417561
  },
  {
    "code": "6449",
    "name": "鈺邦",
    "market": "TWSE",
    "three_inst_ratio": 12.005032914584802,
    "change": 2.7168175668040497
  },
  {
    "code": "2369",
    "name": "菱生",
    "market": "TWSE",
    "three_inst_ratio": 17.658254154412685,
    "change": 2.6985172414511585
  },
  {
    "code": "00982A",
    "name": "主動群益台灣強棒",
    "market": "TWSE",
    "three_inst_ratio": 3.4978106205409025,
    "change": 2.6478106205409024
  },
  {
    "code": "00951",
    "name": "台新日本半導體",
    "market": "TWSE",
    "three_inst_ratio": 3.76,
    "change": 2.62
  },
  {
    "code": "00900",
    "name": "富邦特選高股息30",
    "market": "TWSE",
    "three_inst_ratio": 3.0536049128206617,
    "change": 2.583604912820662
  },
  {
    "code": "00971",
    "name": "野村美國研發龍頭",
    "market": "TWSE",
    "three_inst_ratio": 3.16,
    "change": 2.5300000000000002
  },
  {
    "code": "2006",
    "name": "東和鋼鐵",
    "market": "TWSE",
    "three_inst_ratio": 18.47147694704402,
    "change": 2.514468145630186
  },
  {
    "code": "8105",
    "name": "凌巨",
    "market": "TWSE",
    "three_inst_ratio": 41.401773070681784,
    "change": 2.490000000000002
  },
  {
    "code": "6706",
    "name": "惠特",
    "market": "TWSE",
    "three_inst_ratio": 11.142918836573894,
    "change": 2.4709708676248834
  },
  {
    "code": "00913",
    "name": "兆豐台灣晶圓製造",
    "market": "TWSE",
    "three_inst_ratio": 4.25,
    "change": 2.46
  },
  {
    "code": "4526",
    "name": "東台",
    "market": "TWSE",
    "three_inst_ratio": 6.81,
    "change": 2.4499999999999993
  },
  {
    "code": "2493",
    "name": "揚博",
    "market": "TWSE",
    "three_inst_ratio": 6.420967931962924,
    "change": 2.447265018457234
  },
  {
    "code": "1563",
    "name": "巧新",
    "market": "TWSE",
    "three_inst_ratio": 4.18,
    "change": 2.4399999999999995
  },
  {
    "code": "7721",
    "name": "微程式",
    "market": "TWSE",
    "three_inst_ratio": 2.82,
    "change": 2.42
  },
  {
    "code": "00981A",
    "name": "主動統一台股增長",
    "market": "TWSE",
    "three_inst_ratio": 3.1335967723470577,
    "change": 2.3890779559626383
  },
  {
    "code": "8473",
    "name": "山林水",
    "market": "TWSE",
    "three_inst_ratio": 4.29,
    "change": 2.37
  },
  {
    "code": "3149",
    "name": "正達",
    "market": "TWSE",
    "three_inst_ratio": 7.53,
    "change": 2.3600000000000003
  },
  {
    "code": "00912",
    "name": "中信臺灣智慧50",
    "market": "TWSE",
    "three_inst_ratio": 2.96,
    "change": 2.36
  },
  {
    "code": "6277",
    "name": "宏正",
    "market": "TWSE",
    "three_inst_ratio": 9.3520129966757,
    "change": 2.359940571434617
  },
  {
    "code": "1723",
    "name": "中碳",
    "market": "TWSE",
    "three_inst_ratio": 8.74888147999565,
    "change": 2.3504443985187606
  },
  {
    "code": "3062",
    "name": "建漢",
    "market": "TWSE",
    "three_inst_ratio": 11.246345920273614,
    "change": 2.340279571099922
  },
  {
    "code": "8926",
    "name": "台汽電",
    "market": "TWSE",
    "three_inst_ratio": 12.313856786007646,
    "change": 2.3323512580061347
  },
  {
    "code": "1605",
    "name": "華新",
    "market": "TWSE",
    "three_inst_ratio": 16.333670520854753,
    "change": 2.3153565722094296
  },
  {
    "code": "2542",
    "name": "興富發",
    "market": "TWSE",
    "three_inst_ratio": 11.953548120779354,
    "change": 2.3020324631523508
  },
  {
    "code": "6120",
    "name": "達運",
    "market": "TWSE",
    "three_inst_ratio": 9.811118910359477,
    "change": 2.265993385985589
  },
  {
    "code": "9941",
    "name": "裕融",
    "market": "TWSE",
    "three_inst_ratio": 6.875385572230702,
    "change": 2.2414861487568407
  },
  {
    "code": "8150",
    "name": "南茂",
    "market": "TWSE",
    "three_inst_ratio": 44.89154250161548,
    "change": 2.2193481094898786
  },
  {
    "code": "00983D",
    "name": "主動富邦複合收益",
    "market": "TWSE",
    "three_inst_ratio": 2.8,
    "change": 2.21
  },
  {
    "code": "4771",
    "name": "望隼",
    "market": "TWSE",
    "three_inst_ratio": 7.0,
    "change": 2.21
  },
  {
    "code": "6446",
    "name": "藥華藥",
    "market": "TWSE",
    "three_inst_ratio": 25.69524641373256,
    "change": 2.1760059480393856
  },
  {
    "code": "00735",
    "name": "國泰臺韓科技",
    "market": "TWSE",
    "three_inst_ratio": 7.282515152399576,
    "change": 2.1625151523995756
  },
  {
    "code": "1806",
    "name": "冠軍",
    "market": "TWSE",
    "three_inst_ratio": 8.474095136147088,
    "change": 2.16
  },
  {
    "code": "4590",
    "name": "富田-創",
    "market": "TWSE",
    "three_inst_ratio": 2.47,
    "change": 2.14
  },
  {
    "code": "7750",
    "name": "新代",
    "market": "TWSE",
    "three_inst_ratio": 17.96865164316635,
    "change": 2.1203760978801007
  },
  {
    "code": "00917",
    "name": "中信特選金融",
    "market": "TWSE",
    "three_inst_ratio": 3.25,
    "change": 2.1
  },
  {
    "code": "6531",
    "name": "愛普*",
    "market": "TWSE",
    "three_inst_ratio": 37.30964369276744,
    "change": 2.0968431512621635
  },
  {
    "code": "3588",
    "name": "通嘉",
    "market": "TWSE",
    "three_inst_ratio": 4.63,
    "change": 2.09
  },
  {
    "code": "2428",
    "name": "興勤",
    "market": "TWSE",
    "three_inst_ratio": 19.349710056282778,
    "change": 2.0804673212558136
  },
  {
    "code": "00927",
    "name": "群益半導體收益",
    "market": "TWSE",
    "three_inst_ratio": 2.73,
    "change": 2.08
  },
  {
    "code": "2103",
    "name": "台橡",
    "market": "TWSE",
    "three_inst_ratio": 23.193445167838338,
    "change": 2.0375778420349917
  },
  {
    "code": "5292",
    "name": "華懋",
    "market": "TWSE",
    "three_inst_ratio": 6.3992428992115515,
    "change": 2.026007409518381
  },
  {
    "code": "00657",
    "name": "國泰日經225",
    "market": "TWSE",
    "three_inst_ratio": 8.04,
    "change": 2.009999999999999
  },
  {
    "code": "2615",
    "name": "萬海",
    "market": "TWSE",
    "three_inst_ratio": 38.602315900171064,
    "change": 1.999465046165355
  },
  {
    "code": "00944",
    "name": "野村趨勢動能高息",
    "market": "TWSE",
    "three_inst_ratio": 3.12,
    "change": 1.9600000000000002
  },
  {
    "code": "3665",
    "name": "貿聯-KY",
    "market": "TWSE",
    "three_inst_ratio": 52.71752683465912,
    "change": 1.958655862110973
  },
  {
    "code": "2472",
    "name": "立隆電",
    "market": "TWSE",
    "three_inst_ratio": 14.78116285009676,
    "change": 1.954127010681395
  },
  {
    "code": "4755",
    "name": "三福化",
    "market": "TWSE",
    "three_inst_ratio": 25.479847278215797,
    "change": 1.94293190078049
  }
]